Workbook

Sheet Cover
B3: Elan1 Govern · Series A Financial Model
B5: The governance platform for AI agents — it decides before every tool call, makes a named person approve the risky ones, refuses what it must, and produces the proof
B7: Prepared for Series A investors · Plan period October 2026 to March 2031 · 22 September 2026, revised 27 October 2026 · Strictly confidential
B9: Revised edition 27 October 2026 — see Revision log
B11: THE ASK
B12: Series A round | C12: Rs 180.0 crore / US$20.0 million, in three tranches against gates
B13: Founder and angel bridge | C13: Rs 8.0 crore, October 2026 — precedes the round and is not part of the Rs 180 crore
B14: Tranche 1 — close | C14: Rs 63.0 crore, March 2027
B15: Tranche 2 — Gate A | C15: Rs 72.0 crore, October 2028
B16: Tranche 3 — Gate B | C16: Rs 45.0 crore, July 2029
B17: Minimum cash on the plan | C17: Rs 4.4 crore, February 2027 — the month before tranche 1 closes
B19: CURRENCY CONVENTION
B20: Reporting currency | C20: Indian rupees. 1 crore = 10,000,000; 1 lakh = 100,000
B21: US dollar view | C21: Rs 90.00 = US$1.00 throughout. Rs crore ÷ 9 = US$ million
B22: Units | C22: Figures are in Rs crore unless the sheet states otherwise
B24: HOW THIS WORKBOOK IS BUILT
B25: One 54-month engine drives every number. Months run October 2026 to March 2031.
B26: The monthly, quarterly and annual views on the sheets that follow are aggregations of that single engine,
B27: so monthly, quarterly and annual figures tie to the rupee by construction — nothing is entered twice.
B28: Engine outputs are hardcoded. Derived lines — gross profit, margins, totals, percentages of revenue and the
B29: opening-to-closing cash chain — are live Excel formulas, so a reader can trace and re-run the arithmetic.
B30: Refusals are metered at quantity zero and are never billed. Prices are flat to March 2029, then 4% p.a.
B32: TAB INDEX
B33: Sheet | C33: What it shows
B34: Assumptions | C34: Every driver and price in one place — price book, ramps, bands, funding schedule
B35: Summary P&L | C35: Five financial years: revenue to EBIT, exit ARR, cash, headcount, tenants; US$ block
B36: Monthly FY2026-27 | C36: October 2026 to March 2027 month by month in Rs lakh, plus headcount by function
B37: Quarterly FY2027-28 | C37: The four FY2027-28 quarters in detail, then all 18 quarters of the plan
B38: Annual FY2028-31 | C38: The three scale years in full: P&L, revenue and opex by line, people, customers
B39: Revenue build | C39: Every revenue line by year and by quarter, with the channel contra and the mix
B40: Cost build | C40: COGS split and every operating cost line by year, with percentage of revenue
B41: Headcount | C41: All ten functions by month for 54 months, year-end bands and the people-cost bridge
B42: Unit economics | C42: Governed action volumes, revenue and cost per action, and the price anchors
B43: Cash and funding | C43: 54-month cash chain: opening, EBITDA, capex, working capital, funding, closing
B44: Scenarios | C44: Base, downside and upside side by side, with the scenario definitions
B45: Gate calendar | C45: The dated events that release tranches and turn on revenue lines
B47: All figures generated 22 September 2026 from the elan1 Series A engine. Do not alter engine outputs without re-running the model.
B49: Revised 27 October 2026. The product is renamed Elan1 Govern. In the original pages, 'elan1' meaning the product or kernel should be read as Elan1 Govern; 'elan1 Private Limited' remains the entity. Engine outputs are unchanged; every addition is listed on the Revision log, and the new Elan1 Govern switches on Assumptions are OFF in the base case.
B51: ADDED IN THE REVISED EDITION | C51: What it shows
B52: Govern overlay | C52: Elan1 Govern increments behind three switches — governance layer, reads billed, reads cost; zero when OFF
B53: Govern build status | C53: What the Elan1 Govern code does today, capability by capability, with evidence and its effect on the model
B54: Revision log | C54: Every cell changed or added on 27 October 2026, with old and new values, reason and provenance

Sheet Assumptions
A1: Assumptions and drivers
A2: Every price, ramp, rate and funding event that the 54-month engine reads. Change a driver here and the engine must be re-run.
A3: Units are stated on each line. Rs = Indian rupees; cr = crore (10,000,000); L = lakh (100,000).
A5: PRICE BOOK — Rs, annual unless stated
A6: Item | B6: Price (Rs) | C6: Unit
A7: Platform floor, L1 Guarded | B7: 180000 | C7: per tenant per year
A8: Platform floor, L2 Attested | B8: 600000 | C8: per tenant per year
A9: Platform floor, L3 Proven | B9: 2400000 | C9: per tenant per year
A10: Sovereign / on-premises deployment | B10: 12000000 | C10: per deployment per year
A11: Included governed actions, L1 | B11: 480000 | C11: actions per tenant per year
A12: Included governed actions, L2 | B12: 1500000 | C12: actions per tenant per year
A13: Included governed actions, L3 | B13: 4200000 | C13: actions per tenant per year
A14: Governed action beyond allowance, L1 | B14: 1.6 | C14: Rs per action
A15: Governed action beyond allowance, L2 | B15: 1.2 | C15: Rs per action
A16: Governed action beyond allowance, L3 | B16: 0.9 | C16: Rs per action
A17: Governed action, sovereign deployment | B17: 0.55 | C17: Rs per action
A18: Governed action, internal transfer to rung1 | B18: 0.4 | C18: Rs per action
... A23: Partner certification | B23: 150000 | C23: per firm per year
A24: Refusals are metered at quantity zero and are never billed. List prices are flat to March 2029 and escalate 4% per annum thereafter.
A25: Included-action allowances are consumed first; only actions beyond the allowance are billed at the per-action rate.
A27: DEMAND, MIX AND CHANNEL DRIVERS — monthly ramp, end of month
A28: Month | B28: Tenants, total | C28: of which L1 | D28: of which L2 | E28: of which L3 | F28: Sovereign | G28: Partner firms | H28: Internal GA / month | I28: Pack attach | J28: Channel share | K28: Cost per GA (Rs)
A29: Oct 2026 | B29: 0 | C29: 0 | D29: 0 | E29: 0 | F29: 0 | G29: 0 | H29: 0 | I29: 0 | J29: 0 | K29: 0.092
A30: Nov 2026 | B30: 0 | C30: 0 | D30: 0 | E30: 0 | F30: 0 | G30: 0 | H30: 0 | I30: 0 | J30: 0 | K30: 0.09076
A31: Dec 2026 | B31: 0 | C31: 0 | D31: 0 | E31: 0 | F31: 0 | G31: 0 | H31: 0 | I31: 0 | J31: 0 | K31: 0.08953
A32: Jan 2027 | B32: 0 | C32: 0 | D32: 0 | E32: 0 | F32: 0 | G32: 0 | H32: 60000 | I32: 0 | J32: 0 | K32: 0.08832
A33: Feb 2027 | B33: 0 | C33: 0 | D33: 0 | E33: 0 | F33: 0 | G33: 0 | H33: 120000 | I33: 0 | J33: 0 | K33: 0.08713
A34: Mar 2027 | B34: 0 | C34: 0 | D34: 0 | E34: 0 | F34: 0 | G34: 0 | H34: 180000 | I34: 0 | J34: 0 | K34: 0.08596
A35: Apr 2027 | B35: 0 | C35: 0 | D35: 0 | E35: 0 | F35: 0 | G35: 0 | H35: 260000 | I35: 0 | J35: 0 | K35: 0.0848
A36: May 2027 | B36: 0 | C36: 0 | D36: 0 | E36: 0 | F36: 0 | G36: 0 | H36: 340000 | I36: 0 | J36: 0 | K36: 0.08365
A37: Jun 2027 | B37: 0 | C37: 0 | D37: 0 | E37: 0 | F37: 0 | G37: 0 | H37: 420000 | I37: 0 | J37: 0 | K37: 0.08252
A38: Jul 2027 | B38: 3 | C38: 3 | D38: 0 | E38: 0 | F38: 0 | G38: 0 | H38: 580000 | I38: 0 | J38: 0 | K38: 0.08141
A39: Aug 2027 | B39: 6 | C39: 6 | D39: 0 | E39: 0 | F39: 0 | G39: 0 | H39: 740000 | I39: 0 | J39: 0 | K39: 0.08031
A40: Sep 2027 | B40: 9 | C40: 9 | D40: 0 | E40: 0 | F40: 0 | G40: 0 | H40: 900000 | I40: 0 | J40: 0 | K40: 0.07922
... A82: Mar 2031 | B82: 545 | C82: 278.86 | D82: 211.19 | E82: 54.95 | F82: 11 | G82: 140 | H82: 30000000 | I82: 1.32 | J82: 0.45 | K82: 0.052
A83: Tenant ramp anchors: first external paying tenant July 2027; 39 by March 2028; 148 by March 2029; 312 by March 2030; 545 by March 2031.
A84: Assurance mix: L1 only until April 2028; L2 general availability April 2028 ramps to 36-39% of tenants; L3 entry October 2029 reaching about 10%.
A85: External governed actions per tenant per month: L1 72,000 · L2 300,000 · L3 1,250,000, each growing 8% per annum.
A86: Channel: partners keep 18% of list on partner-sourced revenue; partner-sourced share of external revenue rises from 0% to 45% by March 2031, shown as a contra-revenue line.
A87: Cost per governed action is the blended runtime and infrastructure unit cost (stack1 internal cost plus 15%), falling from Rs 0.092 to Rs 0.052.
A89: PEOPLE — fully loaded salary bands by function
A90: Function | B90: Band Rs L/yr | C90: Mar 2027 | D90: Mar 2031
A91: Kernel engineering | B91: 34 | C91: 7 | D91: 38
A92: Evidence and cryptography | B92: 38 | C92: 3 | D92: 26
A93: Pack and regulatory engineering | B93: 30 | C93: 2 | D93: 50
A94: Platform and SRE | B94: 30 | C94: 3 | D94: 27
A95: Security, compliance, certification | B95: 32 | C95: 2 | D95: 21
A96: Product and design | B96: 28 | C96: 2 | D96: 16
A97: Solutions and field engineering | B97: 26 | C97: 2 | D97: 40
A98: Go to market and partners | B98: 27 | C98: 3 | D98: 50
A99: Standards, policy, regulator affairs | B99: 36 | C99: 1 | D99: 13
A100: Finance, legal and operations | B100: 24 | C100: 2 | D100: 24
A101: Total headcount | C101: =SUM(C91:C100) -> 27 | D101: =SUM(D91:D100) -> 305
A102: Salary escalation | B102: 0.08 | C102: per annum on all bands
A103: ESOP charge | B103: 0.11 | C103: of cash people cost, non-cash, charged below EBITDA
A104: Days sales outstanding (DSO) | B104: 55 | C104: days, on external revenue only; internal rung1 transfer settles same month
A105: Capex | B105: 60000 | C105: Rs 60,000 per month base plus Rs 3,200 per head, plus a Rs 14 lakh fit-out each April
A106: Contingency | B106: 0.055 | C106: of all other operating cost lines
A108: FUNDING SCHEDULE
A109: Event | B109: Month | C109: Amount (Rs cr) | D109: Amount (US$ m)
A110: Founder and angel bridge | B110: Oct 2026 | C110: 8 | D110: =C110/9 -> 0.88888889
A111: Series A tranche 1 (close, Mar 2027) | B111: Mar 2027 | C111: 63 | D111: =C111/9 -> 7
A112: Series A tranche 2 (Gate A, Oct 2028) | B112: Oct 2028 | C112: 72 | D112: =C112/9 -> 8
A113: Series A tranche 3 (Gate B, Jul 2029) | B113: Jul 2029 | C113: 45 | D113: =C113/9 -> 5
A114: Total funding into the plan | C114: =SUM(C110:C113) -> 188 | D114: =SUM(D110:D113) -> 20.888889
A115: of which Series A | C115: =SUM(C111:C113) -> 180 | D115: =SUM(D111:D113) -> 20
A116: Tranche 2 releases on Gate A (October 2028) and tranche 3 on Gate B (July 2029); see the Gate calendar sheet for the tested conditions.
A118: ELAN1 GOVERN DRIVERS AND SWITCHES — added 27 October 2026 (all switches OFF in the base case)
A119: Driver | B119: Value | C119: Unit | D119: Provenance | E119: Note
A120: Governance layer revenue switch | B120: 0 | C120: 1 = on, 0 = off | D120: MODELLED | E120: OFF in the base case. Turns on the AI inventory / assessments / frameworks add-on line on 'Govern overlay'.
A121: Governance layer price | B121: 90000 | C121: Rs per paying tenant per year | D121: MODELLED | E121: Half the L1 platform floor (B7). Per-tenant add-on: per-governed-action pricing and Rs 0 refusals are untouched.
A122: Governance layer attach, FY2026-27 | B122: 0 | C122: share of paying tenants | D122: MODELLED | E122: No paying tenants until July 2027.
A123: Governance layer attach, FY2027-28 | B123: 0.05 | C123: share of paying tenants | D123: MODELLED | E123: Rides the existing tenant ramp (B29:B82); adds no customers.
A124: Governance layer attach, FY2028-29 | B124: 0.1 | C124: share of paying tenants | D124: MODELLED
A125: Governance layer attach, FY2029-30 | B125: 0.15 | C125: share of paying tenants | D125: MODELLED
A126: Governance layer attach, FY2030-31 | B126: 0.2 | C126: share of paying tenants | D126: MODELLED
A127: Governance layer cost of revenue | B127: 0.15 | C127: of gross line revenue | D127: MODELLED | E127: Hosting and support for inventory, assessments and framework reports.
A128: Channel margin kept by partners | B128: 0.18 | C128: of list on partner-sourced revenue | D128: ENGINE (A86) | E128: Applied with the monthly channel share in column J.
A129: List price escalation from April 2029 | B129: 0.04 | C129: per annum | D129: ENGINE (A24) | E129: Flat to March 2029, then 4% a year, as for the price book.
A130: Reads metered switch | B130: 0 | C130: 1 = on, 0 = off | D130: MODELLED | E130: OFF: whether reads are billed is an unmade pricing decision. Scenario only. Billing reads implies governing them, so read with B134.
A131: Read : write ratio | B131: 2 | C131: reads per governed action | D131: MODELLED | E131: Applies to all governed actions (internal and external).
A132: Share of reads billed | B132: 0.5 | C132: beyond the included allowance | D132: MODELLED | E132: Allowance mechanics are not reproduced outside the engine.
A133: Read price | B133: 0.1 | C133: Rs per allowed read | D133: MODELLED | E133: Refusals stay at quantity zero and are never billed.
A134: Reads runtime-cost switch | B134: 0 | C134: 1 = on, 0 = off | D134: MODELLED | E134: OFF in the base case. TOP MODEL RISK: the code audit (commit 22388ad) shows a signed receipt for every governed call, reads included, but the engine's cost per governed action (K29:K82) covers writes only. Per-read cost is unmeasured.
A135: Read check cost | B135: 0.5 | C135: × cost per governed action (column K) | D135: MODELLED | E135: Per-read cost is still unmeasured (the 27 Oct 2026 code audit confirms reads are receipted but did not measure cost); replace with the measured figure.
A136: These drivers feed only the 'Govern overlay' sheet and the overlay blocks on Summary P&L (rows 39 to 50) and Scenarios (rows 43 to 62). Engine outputs are unchanged whatever the switches say. Shaded cells are inputs.

Sheet Summary P&L
A1: Summary profit and loss — five financial years
A2: The full plan at annual grain: revenue to EBIT, exit ARR, closing cash, headcount and paying tenants. Derived lines are live formulas.
A3: Rs crore, except margins (%), headcount and tenant counts. Financial years end 31 March. US$ block below at Rs 90.00 = US$1.00.
A5: Rs crore | B5: FY2026-27 | C5: FY2027-28 | D5: FY2028-29 | E5: FY2029-30 | F5: FY2030-31
A6: Revenue | B6: 0.0144 | C6: 1.8901325 | D6: 18.077531 | E6: 81.179988 | F6: 230.31755
A7: Cost of revenue | B7: 0.10940403 | C7: 1.6749955 | D7: 6.8355136 | E7: 16.566936 | F7: 32.245312
A8: Gross profit | B8: =B6-B7 -> -0.095004034 | C8: =C6-C7 -> 0.21513695 | D8: =D6-D7 -> 11.242018 | E8: =E6-E7 -> 64.613051 | F8: =F6-F7 -> 198.07224
A9: Gross margin % | B9: =IF(B6<0.05,"n/m",B8/B6) -> n/m | C9: =IF(C6<0.05,"n/m",C8/C6) -> 0.1138211 | D9: =IF(D6<0.05,"n/m",D8/D6) -> 0.62187793 | E9: =IF(E6<0.05,"n/m",E8/E6) -> 0.79592339 | F9: =IF(F6<0.05,"n/m",F8/F6) -> 0.85999629
A10: Operating expenses | B10: 4.3888685 | C10: 26.94154 | D10: 61.975186 | E10: 111.09423 | F10: 175.49629
A11: EBITDA | B11: =B8-B10 -> -4.4838725 | C11: =C8-C10 -> -26.726403 | D11: =D8-D10 -> -50.733168 | E11: =E8-E10 -> -46.481176 | F11: =F8-F10 -> 22.575951
A12: ESOP charge (non-cash) | B12: 0.33150223 | C12: 2.2835872 | D12: 5.2411212 | E12: 8.7037761 | F12: 12.393149
A13: EBIT | B13: =B11-B12 -> -4.8153748 | C13: =C11-C12 -> -29.009991 | D13: =D11-D12 -> -55.974289 | E13: =E11-E12 -> -55.184952 | F13: =F11-F12 -> 10.182802
A14: EBITDA margin % | B14: =IF(B6<0.05,"n/m",B11/B6) -> n/m | C14: =IF(C6<0.05,"n/m",C11/C6) -> -14.139963 | D14: =IF(D6<0.05,"n/m",D11/D6) -> -2.8064212 | E14: =IF(E6<0.05,"n/m",E11/E6) -> -0.57256939 | F14: =IF(F6<0.05,"n/m",F11/F6) -> 0.098020974
A16: POSITION AT YEAR END
A17: Exit ARR | B17: 0.0864 | C17: 5.0192216 | D17: 33.679223 | E17: 133.03688 | F17: 334.22544
A18: Closing cash | B18: 66.443647 | C18: 38.666766 | D18: 55.229826 | E18: 38.411427 | F18: 30.409496
A19: Funding received in year | B19: 71 | C19: 0 | D19: 72 | E19: 45 | F19: 0
A20: Capex | B20: 0.07248 | C20: 0.45328 | D20: 0.73232 | E20: 1.01648 | F20: 1.2744
A21: Headcount at year end | B21: 27 | C21: 95 | D21: 170 | E21: 243 | F21: 305
A22: Paying tenants at year end | B22: 0 | C22: 39 | D22: 148 | E22: 312 | F22: 545
A23: Certified partner firms at year end | B23: 0 | C23: 6 | D23: 28 | E23: 70 | F23: 140
A24: Sovereign deployments at year end | B24: 0 | C24: 0 | D24: 0 | E24: 4 | F24: 11
A26: US DOLLAR VIEW AT Rs 90.00 = US$1.00 (Rs crore ÷ 9 = US$ million)
A27: US$ million | B27: FY2026-27 | C27: FY2027-28 | D27: FY2028-29 | E27: FY2029-30 | F27: FY2030-31
A28: Revenue | B28: =B6/9 -> 0.0016 | C28: =C6/9 -> 0.21001472 | D28: =D6/9 -> 2.0086146 | E28: =E6/9 -> 9.0199987 | F28: =F6/9 -> 25.590839
A29: Cost of revenue | B29: =B7/9 -> 0.012156004 | C29: =C7/9 -> 0.18611061 | D29: =D7/9 -> 0.75950152 | E29: =E7/9 -> 1.8407707 | F29: =F7/9 -> 3.5828125
A30: Gross profit | B30: =B8/9 -> -0.010556004 | C30: =C8/9 -> 0.023904105 | D30: =D8/9 -> 1.2491131 | E30: =E8/9 -> 7.1792279 | F30: =F8/9 -> 22.008027
A31: Operating expenses | B31: =B10/9 -> 0.48765205 | C31: =C10/9 -> 2.9935045 | D31: =D10/9 -> 6.8861318 | E31: =E10/9 -> 12.343803 | F31: =F10/9 -> 19.499588
A32: EBITDA | B32: =B11/9 -> -0.49820806 | C32: =C11/9 -> -2.9696004 | D32: =D11/9 -> -5.6370187 | E32: =E11/9 -> -5.1645751 | F32: =F11/9 -> 2.508439
A33: ESOP charge (non-cash) | B33: =B12/9 -> 0.036833581 | C33: =C12/9 -> 0.25373191 | D33: =D12/9 -> 0.58234679 | E33: =E12/9 -> 0.96708623 | F33: =F12/9 -> 1.3770166
A34: EBIT | B34: =B13/9 -> -0.53504164 | C34: =C13/9 -> -3.2233323 | D34: =D13/9 -> -6.2193655 | E34: =E13/9 -> -6.1316613 | F34: =F13/9 -> 1.1314224
A35: Exit ARR | B35: =B17/9 -> 0.0096 | C35: =C17/9 -> 0.55769129 | D35: =D17/9 -> 3.7421359 | E35: =E17/9 -> 14.781875 | F35: =F17/9 -> 37.13616
A36: Closing cash | B36: =B18/9 -> 7.3826275 | C36: =C18/9 -> 4.2963074 | D36: =D18/9 -> 6.1366473 | E36: =E18/9 -> 4.2679364 | F36: =F18/9 -> 3.3788329
A37: US$ figures are a presentation of the rupee plan at a fixed rate; no currency hedging or translation gain is modelled.
A39: ELAN1 GOVERN OVERLAY — zero unless switched on at Assumptions B120, B130 or B134
A40: Rs crore | B40: FY2026-27 | C40: FY2027-28 | D40: FY2028-29 | E40: FY2029-30 | F40: FY2030-31
A41: Incremental revenue | B41: ='Govern overlay'!B88 -> 0 | C41: ='Govern overlay'!C88 -> 0 | D41: ='Govern overlay'!D88 -> 0 | E41: ='Govern overlay'!E88 -> 0 | F41: ='Govern overlay'!F88 -> 0
A42: Incremental cost of revenue | B42: ='Govern overlay'!B89 -> 0 | C42: ='Govern overlay'!C89 -> 0 | D42: ='Govern overlay'!D89 -> 0 | E42: ='Govern overlay'!E89 -> 0 | F42: ='Govern overlay'!F89 -> 0
A43: Incremental EBITDA | B43: =B41-B42 -> 0 | C43: =C41-C42 -> 0 | D43: =D41-D42 -> 0 | E43: =E41-E42 -> 0 | F43: =F41-F42 -> 0
A44: Revenue including overlay | B44: =B6+B41 -> 0.0144 | C44: =C6+C41 -> 1.8901325 | D44: =D6+D41 -> 18.077531 | E44: =E6+E41 -> 81.179988 | F44: =F6+F41 -> 230.31755
A45: Gross margin % including overlay | B45: =IF(B44<0.05,"n/m",(B44-B7-B42)/B44) -> n/m | C45: =IF(C44<0.05,"n/m",(C44-C7-C42)/C44) -> 0.1138211 | D45: =IF(D44<0.05,"n/m",(D44-D7-D42)/D44) -> 0.62187793 | E45: =IF(E44<0.05,"n/m",(E44-E7-E42)/E44) -> 0.79592339 | F45: =IF(F44<0.05,"n/m",(F44-F7-F42)/F44) -> 0.85999629
A46: EBITDA including overlay | B46: =B11+B43 -> -4.4838725 | C46: =C11+C43 -> -26.726403 | D46: =D11+D43 -> -50.733168 | E46: =E11+E43 -> -46.481176 | F46: =F11+F43 -> 22.575951
A47: Closing cash including overlay | B47: =B18+'Govern overlay'!B91 -> 66.443647 | C47: =C18+'Govern overlay'!C91 -> 38.666766 | D47: =D18+'Govern overlay'!D91 -> 55.229826 | E47: =E18+'Govern overlay'!E91 -> 38.411427 | F47: =F18+'Govern overlay'!F91 -> 30.409496
A48: Exit ARR including overlay | B48: =B17+'Govern overlay'!B92 -> 0.0864 | C48: =C17+'Govern overlay'!C92 -> 5.0192216 | D48: =D17+'Govern overlay'!D92 -> 33.679223 | E48: =E17+'Govern overlay'!E92 -> 133.03688 | F48: =F17+'Govern overlay'!F92 -> 334.22544
A49: =IF(Assumptions!B120+Assumptions!B130+Assumptions!B134=0,"All Elan1 Govern switches are OFF: rows 44 to 48 equal the engine base above.","One or more Elan1 Govern switches are ON: rows 44 to 48 differ from the engine base above; the gate thresholds in the IM are quoted on the engine base.") -> All Elan1 Govern switches are OFF: rows 44 to 48 equal the engine base above.
A50: Rows 6 to 24 remain the engine base on which the Information Memorandum and the tranche gates are quoted. See Scenarios rows 45 to 62 for each Elan1 Govern sensitivity.

Sheet Monthly FY2026-27
A1: Monthly detail — H2 FY2026-27 (October 2026 to March 2027)
A2: The six months from company formation to Series A close: burn, funding and the first internal governed actions.
A3: Rs lakh (1 lakh = 100,000), except headcount and governed actions, which are counts.
A5: Rs lakh | B5: Oct 2026 | C5: Nov 2026 | D5: Dec 2026 | E5: Jan 2027 | F5: Feb 2027 | G5: Mar 2027 | H5: H2 total
A6: Revenue | B6: 0 | C6: 0 | D6: 0 | E6: 0.24 | F6: 0.48 | G6: 0.72 | H6: =SUM(B6:G6) -> 1.44
A7: Cost of revenue | B7: 0.55 | C7: 0.55 | D7: 1.7570504 | E7: 1.8178111 | F7: 3.0998236 | G7: 3.1657183 | H7: =SUM(B7:G7) -> 10.940403
A8: Gross profit | B8: =B6-B7 -> -0.55 | C8: =C6-C7 -> -0.55 | D8: =D6-D7 -> -1.7570504 | E8: =E6-E7 -> -1.5778111 | F8: =F6-F7 -> -2.6198236 | G8: =G6-G7 -> -2.4457183 | H8: =H6-H7 -> -9.5004034
A9: Operating expenses | B9: 47.109267 | C9: 50.575437 | D9: 71.779573 | E9: 80.497293 | F9: 92.542053 | G9: 96.383226 | H9: =SUM(B9:G9) -> 438.88685
A10: EBITDA | B10: =B8-B9 -> -47.659267 | C10: =C8-C9 -> -51.125437 | D10: =D8-D9 -> -73.536624 | E10: =E8-E9 -> -82.075105 | F10: =F8-F9 -> -95.161877 | G10: =G8-G9 -> -98.828944 | H10: =H8-H9 -> -448.38725
A11: Capex | B11: 0.952 | C11: 0.984 | D11: 1.112 | E11: 1.304 | F11: 1.432 | G11: 1.464 | H11: =SUM(B11:G11) -> 7.248
A12: Net burn | B12: 48.611267 | C12: 52.109437 | D12: 74.648624 | E12: 83.379105 | F12: 96.593877 | G12: 100.29294 | H12: =SUM(B12:G12) -> 455.63525
A13: Funding in | B13: 800 | C13: 0 | D13: 0 | E13: 0 | F13: 0 | G13: 6300 | H13: =SUM(B13:G13) -> 7100
A14: Closing cash | B14: 751.38873 | C14: 699.2793 | D14: 624.63067 | E14: 541.25157 | F14: 444.65769 | G14: 6644.3647 | H14: =G14 -> 6644.3647
A16: OPERATING MEASURES
A17: Headcount at month end | B17: 11 | C17: 12 | D17: 16 | E17: 22 | F17: 26 | G17: 27 | H17: =G17 -> 27
A18: Governed actions in month | B18: 0 | C18: 0 | D18: 0 | E18: 60000 | F18: 120000 | G18: 180000 | H18: =SUM(B18:G18) -> 360000
A19: of which internal (rung1) | B19: 0 | C19: 0 | D19: 0 | E19: 60000 | F19: 120000 | G19: 180000 | H19: =SUM(B19:G19) -> 360000
A20: of which external | B20: 0 | C20: 0 | D20: 0 | E20: 0 | F20: 0 | G20: 0 | H20: =SUM(B20:G20) -> 0
A21: Paying tenants at month end | B21: 0 | C21: 0 | D21: 0 | E21: 0 | F21: 0 | G21: 0 | H21: =G21 -> 0
A23: HEADCOUNT BY FUNCTION — end of month
A24: Function | B24: Oct 2026 | C24: Nov 2026 | D24: Dec 2026 | E24: Jan 2027 | F24: Feb 2027 | G24: Mar 2027 | H24: Band Rs L/yr
A25: Kernel engineering | B25: 4 | C25: 5 | D25: 5 | E25: 6 | F25: 6 | G25: 7 | H25: 34
A26: Evidence and cryptography | B26: 1 | C26: 1 | D26: 2 | E26: 2 | F26: 3 | G26: 3 | H26: 38
A27: Pack and regulatory engineering | B27: 1 | C27: 1 | D27: 1 | E27: 2 | F27: 2 | G27: 2 | H27: 30
A28: Platform and SRE | B28: 2 | C28: 2 | D28: 2 | E28: 3 | F28: 3 | G28: 3 | H28: 30
A29: Security, compliance, certification | B29: 0 | C29: 0 | D29: 1 | E29: 1 | F29: 2 | G29: 2 | H29: 32
A30: Product and design | B30: 1 | C30: 1 | D30: 1 | E30: 2 | F30: 2 | G30: 2 | H30: 28
A31: Solutions and field engineering | B31: 0 | C31: 0 | D31: 1 | E31: 1 | F31: 2 | G31: 2 | H31: 26
A32: Go to market and partners | B32: 1 | C32: 1 | D32: 2 | E32: 2 | F32: 3 | G32: 3 | H32: 27
A33: Standards, policy, regulator affairs | B33: 0 | C33: 0 | D33: 0 | E33: 1 | F33: 1 | G33: 1 | H33: 36
A34: Finance, legal and operations | B34: 1 | C34: 1 | D34: 1 | E34: 2 | F34: 2 | G34: 2 | H34: 24
A35: Total headcount | B35: =SUM(B25:B34) -> 11 | C35: =SUM(C25:C34) -> 12 | D35: =SUM(D25:D34) -> 16 | E35: =SUM(E25:E34) -> 22 | F35: =SUM(F25:F34) -> 26 | G35: =SUM(G25:G34) -> 27
A36: Minimum cash across the whole plan occurs in February 2027 at Rs 444.66 lakh (Rs 4.4 crore), the month before the Rs 63 crore tranche 1 closes.

Sheet Quarterly FY2027-28
A1: Quarterly detail — FY2027-28, and the full 18-quarter arc
A2: The first year of external revenue quarter by quarter, then every quarter of the plan so the shape of the build is visible in one view.
A3: Rs crore, except margins (%) and counts. Quarters are financial-year quarters ending June, September, December and March.
A5: Rs crore | B5: Q1 Jun 27 | C5: Q2 Sep 27 | D5: Q3 Dec 27 | E5: Q4 Mar 28 | F5: FY2027-28
A6: Revenue | B6: 0.0408 | C6: 0.22217028 | D6: 0.56226022 | E6: 1.064902 | F6: =SUM(B6:E6) -> 1.8901325
A7: Cost of revenue | B7: 0.14973483 | C7: 0.29014539 | D7: 0.49256854 | E7: 0.74254676 | F7: =SUM(B7:E7) -> 1.6749955
A8: Gross profit | B8: =B6-B7 -> -0.10893483 | C8: =C6-C7 -> -0.067975112 | D8: =D6-D7 -> 0.069691684 | E8: =E6-E7 -> 0.3223552 | F8: =F6-F7 -> 0.21513695
A9: Gross margin % | B9: =IFERROR(B8/B6,"n/m") -> -2.6699713 | C9: =IFERROR(C8/C6,"n/m") -> -0.30595952 | D9: =IFERROR(D8/D6,"n/m") -> 0.12394916 | E9: =IFERROR(E8/E6,"n/m") -> 0.30270881 | F9: =IFERROR(F8/F6,"n/m") -> 0.1138211
A10: Operating expenses | B10: 4.1373859 | C10: 5.7045408 | D10: 7.6399773 | E10: 9.4596363 | F10: =SUM(B10:E10) -> 26.94154
A11: EBITDA | B11: =B8-B10 -> -4.2463207 | C11: =C8-C10 -> -5.7725159 | D11: =D8-D10 -> -7.5702856 | E11: =E8-E10 -> -9.1372811 | F11: =F8-F10 -> -26.726403
A12: ESOP charge (non-cash) | B12: 0.33950684 | C12: 0.48196528 | D12: 0.64589655 | E12: 0.81621852 | F12: =SUM(B12:E12) -> 2.2835872
A13: EBIT | B13: =B11-B12 -> -4.5858276 | C13: =C11-C12 -> -6.2544812 | D13: =D11-D12 -> -8.2161822 | E13: =E11-E12 -> -9.9534997 | F13: =F11-F12 -> -29.009991
A15: POSITION AT QUARTER END
A16: Exit ARR | B16: 0.2016 | C16: 1.2379027 | D16: 2.7664545 | E16: 5.0192216 | F16: =E16 -> 5.0192216
A17: Closing cash | B17: 62.002527 | C17: 56.039053 | D17: 48.195675 | E17: 38.666766 | F17: =E17 -> 38.666766
A18: Headcount | B18: 44 | C18: 59 | D18: 76 | E18: 95 | F18: =E18 -> 95
A19: Paying tenants | B19: 0 | C19: 9 | D19: 21 | E19: 39 | F19: =E19 -> 39
A20: Certified partner firms | B20: 0 | C20: 0 | D20: 2 | E20: 6 | F20: =E20 -> 6
A21: Governed actions in quarter (millions) | B21: 1.02 | C21: 3.6048 | D21: 7.8953 | E21: 13.8045 | F21: =SUM(B21:E21) -> 26.3246
A23: ALL 18 QUARTERS OF THE PLAN
A24: Quarter | B24: Revenue | C24: EBITDA | D24: Exit ARR | E24: Closing cash | F24: Paying tenants
A25: FY2026-27 Q3 | B25: 0 | C25: -1.7232133 | D25: 0 | E25: 6.2463067 | F25: 0
A26: FY2026-27 Q4 | B26: 0.0144 | C26: -2.7606593 | D26: 0.0864 | E26: 66.443647 | F26: 0
A27: FY2027-28 Q1 | B27: 0.0408 | C27: -4.2463207 | D27: 0.2016 | E27: 62.002527 | F27: 0
A28: FY2027-28 Q2 | B28: 0.22217028 | C28: -5.7725159 | D28: 1.2379027 | E28: 56.039053 | F28: 9
A29: FY2027-28 Q3 | B29: 0.56226022 | C29: -7.5702856 | D29: 2.7664545 | E29: 48.195675 | F29: 21
A30: FY2027-28 Q4 | B30: 1.064902 | C30: -9.1372811 | D30: 5.0192216 | E30: 38.666766 | F30: 39
A31: FY2028-29 Q1 | B31: 2.0478631 | C31: -10.714807 | D31: 9.6046266 | E31: 27.06868 | F31: 59
A32: FY2028-29 Q2 | B32: 3.3398867 | C32: -11.999438 | D32: 15.35343 | E32: 14.132096 | F32: 84
A33: FY2028-29 Q3 | B33: 5.1549781 | C33: -13.498415 | D33: 23.415086 | E33: 71.367227 | F33: 114
A34: FY2028-29 Q4 | B34: 7.5348036 | C34: -14.520507 | D34: 33.679223 | E34: 55.229826 | F34: 148
A35: FY2029-30 Q1 | B35: 10.735863 | C35: -14.275832 | D35: 48.138973 | E35: 38.587385 | F35: 186
A36: FY2029-30 Q2 | B36: 16.756142 | C36: -13.072542 | D36: 74.786412 | E36: 66.433493 | F36: 226
... A42: FY2030-31 Q4 | B42: 78.08113 | C42: 17.401821 | D42: 334.22544 | E42: 30.409496 | F42: 545
A43: Plan total / final quarter | B43: =SUM(B25:B42) -> 331.47961 | C43: =SUM(C25:C42) -> -105.84867 | D43: =D42 -> 334.22544 | E43: =E42 -> 30.409496 | F43: =F42 -> 545
A44: Revenue and EBITDA columns sum across the 18 quarters; exit ARR, cash and tenants are point-in-time and carry the final quarter.

Sheet Annual FY2028-31
A1: The three scale years — FY2028-29 to FY2030-31
A2: Full detail for the years the Series A is raised against: profit and loss, every revenue and cost line, people, customers and unit economics.
A3: Rs crore, except margins (%), counts, and per-action rates in Rs. Financial years end 31 March.
A5: Rs crore | B5: FY2028-29 | C5: FY2029-30 | D5: FY2030-31 | E5: CAGR / total
A6: Revenue | B6: 18.077531 | C6: 81.179988 | D6: 230.31755 | E6: =(D6/B6)^(1/2)-1 -> 2.5693896
A7: Cost of revenue | B7: 6.8355136 | C7: 16.566936 | D7: 32.245312 | E7: =SUM(B7:D7) -> 55.647762
A8: Gross profit | B8: =B6-B7 -> 11.242018 | C8: =C6-C7 -> 64.613051 | D8: =D6-D7 -> 198.07224 | E8: =SUM(B8:D8) -> 273.92731
A9: Gross margin % | B9: =IFERROR(B8/B6,"n/m") -> 0.62187793 | C9: =IFERROR(C8/C6,"n/m") -> 0.79592339 | D9: =IFERROR(D8/D6,"n/m") -> 0.85999629 | E9: =IFERROR(E8/SUM(B6:D6),"n/m") -> 0.831153
A10: Operating expenses | B10: 61.975186 | C10: 111.09423 | D10: 175.49629 | E10: =SUM(B10:D10) -> 348.5657
A11: EBITDA | B11: =B8-B10 -> -50.733168 | C11: =C8-C10 -> -46.481176 | D11: =D8-D10 -> 22.575951 | E11: =SUM(B11:D11) -> -74.638393
A12: ESOP charge (non-cash) | B12: 5.2411212 | C12: 8.7037761 | D12: 12.393149 | E12: =SUM(B12:D12) -> 26.338046
A13: EBIT | B13: =B11-B12 -> -55.974289 | C13: =C11-C12 -> -55.184952 | D13: =D11-D12 -> 10.182802 | E13: =SUM(B13:D13) -> -100.97644
A14: Capex | B14: 0.73232 | C14: 1.01648 | D14: 1.2744 | E14: =SUM(B14:D14) -> 3.0232
A15: Closing cash | B15: 55.229826 | C15: 38.411427 | D15: 30.409496 | E15: =D15 -> 30.409496
A16: Exit ARR | B16: 33.679223 | C16: 133.03688 | D16: 334.22544 | E16: =D16 -> 334.22544
A18: REVENUE BY LINE
A19: Rs crore | B19: FY2028-29 | C19: FY2029-30 | D19: FY2030-31 | E19: 3-year total
A20: Platform licence | B20: 2.367505 | C20: 9.0524532 | D20: 23.552328 | E20: =SUM(B20:D20) -> 34.972286
A21: Governed actions - external | B21: 11.960886 | C21: 58.704606 | D21: 176.9843 | E21: =SUM(B21:D21) -> 247.64979
A22: Governed actions - internal (rung1) | B22: 2.184 | C22: 5.58 | D22: 11.2 | E22: =SUM(B22:D22) -> 18.964
A23: Evidence SKU | B23: 1.0880612 | C23: 6.3160018 | D23: 17.841922 | E23: =SUM(B23:D23) -> 25.245986
A24: Regulatory packs | B24: 0.8291025 | C24: 3.2370353 | D24: 7.6295803 | E24: =SUM(B24:D24) -> 11.695718
A25: Sovereign deployments | B25: 0 | C25: 2.4626515 | D25: 9.4554723 | E25: =SUM(B25:D25) -> 11.918124
A26: Partner certification | B26: 0.255 | C26: 0.75431795 | D26: 1.6939738 | E26: =SUM(B26:D26) -> 2.7032918
A27: Channel margin (contra) | B27: -0.60702367 | C27: -4.9270781 | D27: -18.040023 | E27: =SUM(B27:D27) -> -23.574125
A28: Total revenue | B28: =SUM(B20:B27) -> 18.077531 | C28: =SUM(C20:C27) -> 81.179988 | D28: =SUM(D20:D27) -> 230.31755 | E28: =SUM(E20:E27) -> 329.57507
A30: OPERATING EXPENSE BY LINE
A31: Rs crore | B31: FY2028-29 | C31: FY2029-30 | D31: FY2030-31 | E31: 3-year total
A32: International expansion | B32: 0.54 | C32: 2.43 | D32: 4.92 | E32: =SUM(B32:D32) -> 7.89
A33: People (ex-COGS) | B33: 44.822125 | C33: 74.189567 | D33: 105.6075 | E33: =SUM(B33:D33) -> 224.6192
A34: Certification and audit | B34: 1.44 | C34: 1.82 | D34: 2.38 | E34: =SUM(B34:D34) -> 5.64
A35: Legal, IP and entities | B35: 1.47 | C35: 2.55 | D35: 2.26 | E35: =SUM(B35:D35) -> 6.28
A36: Standards and regulator affairs | B36: 0.552 | C36: 0.93 | D36: 1.14 | E36: =SUM(B36:D36) -> 2.622
A37: Sales and marketing programmes | B37: 4.5692667 | C37: 14.297698 | D37: 35.36007 | E37: =SUM(B37:D37) -> 54.227035
A38: R&D tooling and evaluation | B38: 1.8567 | C38: 2.7003 | D38: 3.466 | E38: =SUM(B38:D38) -> 8.023
A39: Insurance | B39: 0.33069778 | C39: 0.89861989 | D39: 2.240858 | E39: =SUM(B39:D39) -> 3.4701757
A40: Facilities, IT and G&A | B40: 3.163463 | C40: 5.4863998 | D40: 8.9727633 | E40: =SUM(B40:D40) -> 17.622626
A41: Contingency | B41: 3.2309339 | C41: 5.7916422 | D41: 9.1490957 | E41: =SUM(B41:D41) -> 18.171672
A42: Total operating expenses | B42: =SUM(B32:B41) -> 61.975186 | C42: =SUM(C32:C41) -> 111.09423 | D42: =SUM(D32:D41) -> 175.49629 | E42: =SUM(E32:E41) -> 348.5657
A44: HEADCOUNT BY FUNCTION — end of financial year
A45: Function | B45: FY2028-29 | C45: FY2029-30 | D45: FY2030-31 | E45: Band Rs L/yr
A46: Kernel engineering | B46: 25 | C46: 32 | D46: 38 | E46: 34
A47: Evidence and cryptography | B47: 15 | C47: 21 | D47: 26 | E47: 38
A48: Pack and regulatory engineering | B48: 23 | C48: 37 | D48: 50 | E48: 30
A49: Platform and SRE | B49: 15 | C49: 21 | D49: 27 | E49: 30
A50: Security, compliance, certification | B50: 11 | C50: 16 | D50: 21 | E50: 32
A51: Product and design | B51: 10 | C51: 13 | D51: 16 | E51: 28
A52: Solutions and field engineering | B52: 22 | C52: 32 | D52: 40 | E52: 26
A53: Go to market and partners | B53: 28 | C53: 42 | D53: 50 | E53: 27
A54: Standards, policy, regulator affairs | B54: 7 | C54: 10 | D54: 13 | E54: 36
A55: Finance, legal and operations | B55: 14 | C55: 19 | D55: 24 | E55: 24
A56: Total headcount | B56: =SUM(B46:B55) -> 170 | C56: =SUM(C46:C55) -> 243 | D56: =SUM(D46:D55) -> 305
A58: CUSTOMERS, CHANNEL AND DEPLOYMENTS — end of financial year
A59: Count | B59: FY2028-29 | C59: FY2029-30 | D59: FY2030-31
A60: L1 Guarded tenants | B60: 109 | C60: 186 | D60: 279
A61: L2 Attested tenants | B61: 39 | C61: 110 | D61: 211
A62: L3 Proven tenants | B62: 0 | C62: 16 | D62: 55
A63: Paying tenants, total | B63: =SUM(B60:B62) -> 148 | C63: =SUM(C60:C62) -> 312 | D63: =SUM(D60:D62) -> 545
A64: Sovereign / on-premises deployments | B64: 0 | C64: 4 | D64: 11
A65: Certified partner firms | B65: 28 | C65: 70 | D65: 140
A67: UNIT ECONOMICS
A68: Measure | B68: FY2028-29 | C68: FY2029-30 | D68: FY2030-31
A69: Governed actions (millions) | B69: 202.392 | C69: 885.588 | D69: 2491.458
A70: internal (rung1) | B70: 54.6 | C70: 139.5 | D70: 280
A71: external | B71: 147.792 | C71: 746.088 | D71: 2211.458
A72: Revenue per governed action (Rs) | B72: 0.8932 | C72: 0.9167 | D72: 0.9244
A73: Cost per governed action (Rs) | B73: 0.3377 | C73: 0.1871 | D73: 0.1294
A74: Contribution per governed action (Rs) | B74: =B72-B73 -> 0.5555 | C74: =C72-C73 -> 0.7296 | D74: =D72-D73 -> 0.795
A75: Gross margin % | B75: =IFERROR(B9,"n/m") -> 0.62187793 | C75: =IFERROR(C9,"n/m") -> 0.79592339 | D75: =IFERROR(D9,"n/m") -> 0.85999629
A76: Revenue per head (Rs lakh) | B76: 10.63 | C76: 33.41 | D76: 75.51
A77: ARR per paying tenant (Rs lakh) | B77: 22.76 | C77: 42.64 | D77: 61.33
A78: Revenue per head uses headcount at year end. ARR per tenant divides exit ARR by paying tenants at year end and includes the internal rung1 transfer.

Sheet Revenue build
A1: Revenue build by line
A2: Every revenue line by financial year and by quarter, including the channel-margin contra. Totals are formulas so the build ties to the Summary P&L.
A3: Rs crore. The channel-margin contra is negative: partners keep 18% of list on partner-sourced revenue.
A5: BY FINANCIAL YEAR
A6: Rs crore | B6: FY2026-27 | C6: FY2027-28 | D6: FY2028-29 | E6: FY2029-30 | F6: FY2030-31 | G6: Plan total
A7: Platform licence | B7: 0 | C7: 0.252 | D7: 2.367505 | E7: 9.0524532 | F7: 23.552328 | G7: =SUM(B7:F7) -> 35.224286
A8: Governed actions - external | B8: 0 | C8: 1.0503507 | D8: 11.960886 | E8: 58.704606 | F8: 176.9843 | G8: =SUM(B8:F8) -> 248.70014
A9: Governed actions - internal (rung1) | B9: 0.0144 | C9: 0.5216 | D9: 2.184 | E9: 5.58 | F9: 11.2 | G9: =SUM(B9:F9) -> 19.5
A10: Evidence SKU | B10: 0 | C10: 0 | D10: 1.0880612 | E10: 6.3160018 | F10: 17.841922 | G10: =SUM(B10:F10) -> 25.245986
A11: Regulatory packs | B11: 0 | C11: 0.0560385 | D11: 0.8291025 | E11: 3.2370353 | F11: 7.6295803 | G11: =SUM(B11:F11) -> 11.751757
A12: Sovereign deployments | B12: 0 | C12: 0 | D12: 0 | E12: 2.4626515 | F12: 9.4554723 | G12: =SUM(B12:F12) -> 11.918124
A13: Partner certification | B13: 0 | C13: 0.02 | D13: 0.255 | E13: 0.75431795 | F13: 1.6939738 | G13: =SUM(B13:F13) -> 2.7232918
A14: Channel margin (contra) | B14: 0 | C14: -0.0098566985 | D14: -0.60702367 | E14: -4.9270781 | F14: -18.040023 | G14: =SUM(B14:F14) -> -23.583981
A15: Total revenue | B15: =SUM(B7:B14) -> 0.0144 | C15: =SUM(C7:C14) -> 1.8901325 | D15: =SUM(D7:D14) -> 18.077531 | E15: =SUM(E7:E14) -> 81.179988 | F15: =SUM(F7:F14) -> 230.31755 | G15: =SUM(G7:G14) -> 331.47961
A17: REVENUE MIX — share of total revenue by financial year
A18: % of revenue | B18: FY2026-27 | C18: FY2027-28 | D18: FY2028-29 | E18: FY2029-30 | F18: FY2030-31 | G18: Plan total
A19: Platform licence | B19: =IFERROR(B7/B15,"n/m") -> 0 | C19: =IFERROR(C7/C15,"n/m") -> 0.13332399 | D19: =IFERROR(D7/D15,"n/m") -> 0.13096395 | E19: =IFERROR(E7/E15,"n/m") -> 0.1115109 | F19: =IFERROR(F7/F15,"n/m") -> 0.10226024 | G19: =IFERROR(G7/G15,"n/m") -> 0.10626381
A20: Governed actions - external | B20: =IFERROR(B8/B15,"n/m") -> 0 | C20: =IFERROR(C8/C15,"n/m") -> 0.55570214 | D20: =IFERROR(D8/D15,"n/m") -> 0.66164379 | E20: =IFERROR(E8/E15,"n/m") -> 0.72314135 | F20: =IFERROR(F8/F15,"n/m") -> 0.768436 | G20: =IFERROR(G8/G15,"n/m") -> 0.75027284
A21: Governed actions - internal (rung1) | B21: =IFERROR(B9/B15,"n/m") -> 1 | C21: =IFERROR(C9/C15,"n/m") -> 0.2759595 | D21: =IFERROR(D9/D15,"n/m") -> 0.12081296 | E21: =IFERROR(E9/E15,"n/m") -> 0.068736152 | F21: =IFERROR(F9/F15,"n/m") -> 0.048628512 | G21: =IFERROR(G9/G15,"n/m") -> 0.058827148
A22: Evidence SKU | B22: =IFERROR(B10/B15,"n/m") -> 0 | C22: =IFERROR(C10/C15,"n/m") -> 0 | D22: =IFERROR(D10/D15,"n/m") -> 0.060188597 | E22: =IFERROR(E10/E15,"n/m") -> 0.077802448 | F22: =IFERROR(F10/F15,"n/m") -> 0.07746662 | G22: =IFERROR(G10/G15,"n/m") -> 0.076161505
A23: Regulatory packs | B23: =IFERROR(B11/B15,"n/m") -> 0 | C23: =IFERROR(C11/C15,"n/m") -> 0.029647922 | D23: =IFERROR(D11/D15,"n/m") -> 0.045863701 | E23: =IFERROR(E11/E15,"n/m") -> 0.039874795 | F23: =IFERROR(F11/F15,"n/m") -> 0.033126352 | G23: =IFERROR(G11/G15,"n/m") -> 0.035452427
A24: Sovereign deployments | B24: =IFERROR(B12/B15,"n/m") -> 0 | C24: =IFERROR(C12/C15,"n/m") -> 0 | D24: =IFERROR(D12/D15,"n/m") -> 0 | E24: =IFERROR(E12/E15,"n/m") -> 0.030335696 | F24: =IFERROR(F12/F15,"n/m") -> 0.041054067 | G24: =IFERROR(G12/G15,"n/m") -> 0.03595432
A25: Partner certification | B25: =IFERROR(B13/B15,"n/m") -> 0 | C25: =IFERROR(C13/C15,"n/m") -> 0.010581269 | D25: =IFERROR(D13/D15,"n/m") -> 0.014105908 | E25: =IFERROR(E13/E15,"n/m") -> 0.00929192 | F25: =IFERROR(F13/F15,"n/m") -> 0.0073549487 | G25: =IFERROR(G13/G15,"n/m") -> 0.0082155635
A26: Channel margin (contra) | B26: =IFERROR(B14/B15,"n/m") -> 0 | C26: =IFERROR(C14/C15,"n/m") -> -0.0052148189 | D26: =IFERROR(D14/D15,"n/m") -> -0.033578902 | E26: =IFERROR(E14/E15,"n/m") -> -0.06069326 | F26: =IFERROR(F14/F15,"n/m") -> -0.078326739 | G26: =IFERROR(G14/G15,"n/m") -> -0.071147609
A27: Total | B27: =IFERROR(B15/B15,"n/m") -> 1 | C27: =IFERROR(C15/C15,"n/m") -> 1 | D27: =IFERROR(D15/D15,"n/m") -> 1 | E27: =IFERROR(E15/E15,"n/m") -> 1 | F27: =IFERROR(F15/F15,"n/m") -> 1 | G27: =IFERROR(G15/G15,"n/m") -> 1
A29: BY QUARTER — all 18 quarters of the plan
A30: Rs crore | B30: 2026/27 Q3 | C30: 2026/27 Q4 | D30: 2027/28 Q1 | E30: 2027/28 Q2 | F30: 2027/28 Q3 | G30: 2027/28 Q4 | H30: 2028/29 Q1 | I30: 2028/29 Q2 | J30: 2028/29 Q3 | K30: 2028/29 Q4 | L30: 2029/30 Q1 | M30: 2029/30 Q2 | N30: 2029/30 Q3 | O30: 2029/30 Q4 | P30: 2030/31 Q1 | Q30: 2030/31 Q2 | R30: 2030/31 Q3 | S30: 2030/31 Q4 | T30: Plan total
A31: Platform licence | B31: 0 | C31: 0 | D31: 0 | E31: 0.027 | F31: 0.0765 | G31: 0.1485 | H31: 0.27937833 | I31: 0.44752417 | J31: 0.67494333 | K31: 0.96565917 | L31: 1.3532829 | M31: 1.8860046 | N31: 2.527173 | O31: 3.2859928 | P31: 4.1797442 | Q31: 5.1884444 | R31: 6.3778575 | S31: 7.8062817 | T31: =SUM(B31:S31) -> 35.224286
A32: Governed actions - external | B32: 0 | C32: 0 | D32: 0 | E32: 0.10637028 | F32: 0.31285534 | G32: 0.63112504 | H32: 1.2787152 | I32: 2.1599341 | J32: 3.4163526 | K32: 5.1058844 | L32: 7.4302923 | M32: 11.92096 | N32: 16.77211 | O32: 22.581245 | P32: 29.508336 | Q32: 38.048692 | R32: 48.462831 | S32: 60.964442 | T32: =SUM(B32:S32) -> 248.70014
A33: Governed actions - internal (rung1) | B33: 0 | C33: 0.0144 | D33: 0.0408 | E33: 0.0888 | F33: 0.156 | G33: 0.236 | H33: 0.34 | I33: 0.454 | J33: 0.608 | K33: 0.782 | L33: 1 | M33: 1.24 | N33: 1.52 | O33: 1.82 | P33: 2.18 | Q33: 2.57 | R33: 3 | S33: 3.45 | T33: =SUM(B33:S33) -> 19.5
A34: Evidence SKU | B34: 0 | C34: 0 | D34: 0 | E34: 0 | F34: 0 | G34: 0 | H34: 0.067384583 | I34: 0.16435854 | J34: 0.31780583 | K34: 0.53851229 | L34: 0.83684453 | M34: 1.2833755 | N34: 1.7939114 | O34: 2.4018705 | P34: 3.1074267 | Q34: 3.9054195 | R34: 4.8521718 | S34: 5.9769045 | T34: =SUM(B34:S34) -> 25.245986
A35: Regulatory packs | B35: 0 | C35: 0 | D35: 0 | E35: 0 | F35: 0.015012 | G35: 0.0410265 | H35: 0.08413875 | I35: 0.14967 | J35: 0.239355 | K35: 0.35593875 | L35: 0.50571305 | M35: 0.69190416 | N35: 0.90138588 | O35: 1.1380322 | P35: 1.4033958 | Q35: 1.7040905 | R35: 2.0535208 | S35: 2.4685731 | T35: =SUM(B35:S35) -> 11.751757
A36: Sovereign deployments | B36: 0 | C36: 0 | D36: 0 | E36: 0 | F36: 0 | G36: 0 | H36: 0 | I36: 0 | J36: 0 | K36: 0 | L36: 0 | M36: 0.50691247 | N36: 0.81885112 | O36: 1.1368879 | P36: 1.4611126 | Q36: 2.0023547 | R36: 2.6605279 | S36: 3.3314772 | T36: =SUM(B36:S36) -> 11.918124
A37: Partner certification | B37: 0 | C37: 0 | D37: 0 | E37: 0 | F37: 0.0025 | G37: 0.0175 | H37: 0.03375 | I37: 0.05125 | J37: 0.0725 | K37: 0.0975 | L37: 0.12794245 | M37: 0.16339737 | N37: 0.20722053 | O37: 0.2557576 | P37: 0.31567793 | Q37: 0.38200981 | R37: 0.45760746 | S37: 0.53867861 | T37: =SUM(B37:S37) -> 2.7232918
A38: Channel margin (contra) | B38: 0 | C38: 0 | D38: 0 | E38: 0 | F38: -0.000607122 | G38: -0.0092495765 | H38: -0.035503754 | I38: -0.086850126 | J38: -0.17397868 | K38: -0.3106911 | L38: -0.51821243 | M38: -0.93641142 | N38: -1.4261009 | O38: -2.0463534 | P38: -2.8106059 | Q38: -3.7863078 | R38: -4.9878823 | S38: -6.455227 | T38: =SUM(B38:S38) -> -23.583981
A39: Total revenue | B39: =SUM(B31:B38) -> 0 | C39: =SUM(C31:C38) -> 0.0144 | D39: =SUM(D31:D38) -> 0.0408 | E39: =SUM(E31:E38) -> 0.22217028 | F39: =SUM(F31:F38) -> 0.56226022 | G39: =SUM(G31:G38) -> 1.064902 | H39: =SUM(H31:H38) -> 2.0478631 | I39: =SUM(I31:I38) -> 3.3398867 | ... T39: =SUM(T31:T38) -> 331.47961
A40: Quarterly columns are labelled by financial-year quarter; Q1 ends June, Q2 September, Q3 December and Q4 March.

Sheet Cost build
A1: Cost build — cost of revenue and operating expenses
A2: The COGS split and every operating cost line by financial year, with totals as formulas and each line as a percentage of revenue.
A3: Rs crore, except the percentage blocks. Percentages are of total revenue in the same financial year.
A5: Rs crore | B5: FY2026-27 | C5: FY2027-28 | D5: FY2028-29 | E5: FY2029-30 | F5: FY2030-31 | G5: Plan total
A6: Revenue (memo) | B6: 0.0144 | C6: 1.8901325 | D6: 18.077531 | E6: 81.179988 | F6: 230.31755 | G6: =SUM(B6:F6) -> 331.47961
A8: COST OF REVENUE
A9: Rs crore | B9: FY2026-27 | C9: FY2027-28 | D9: FY2028-29 | E9: FY2029-30 | F9: FY2030-31 | G9: Plan total
A10: Runtime and infrastructure (stack1 internal cost + 15%) | B10: 0.036122722 | C10: 0.65258599 | D10: 3.9364828 | E10: 11.479514 | F10: 24.898784 | G10: =SUM(B10:F10) -> 41.003489
A11: Timestamp anchoring (two authorities) | B11: 0 | C11: 0 | D11: 0.074599542 | E11: 0.15175244 | F11: 0.289041 | G11: =SUM(B11:F11) -> 0.51539298
A12: Delivery and customer success | B12: 0.073281312 | C12: 1.0224095 | D12: 2.8244313 | E12: 4.9356701 | F12: 7.0574877 | G12: =SUM(B12:F12) -> 15.91328
A13: Total cost of revenue | B13: =SUM(B10:B12) -> 0.10940403 | C13: =SUM(C10:C12) -> 1.6749955 | D13: =SUM(D10:D12) -> 6.8355136 | E13: =SUM(E10:E12) -> 16.566936 | F13: =SUM(F10:F12) -> 32.245312 | G13: =SUM(G10:G12) -> 57.432162
A14: Gross profit | B14: =B6-B13 -> -0.095004034 | C14: =C6-C13 -> 0.21513695 | D14: =D6-D13 -> 11.242018 | E14: =E6-E13 -> 64.613051 | F14: =F6-F13 -> 198.07224 | G14: =G6-G13 -> 274.04744
A15: Gross margin % | B15: =IF(B6<0.05,"n/m",B14/B6) -> n/m | C15: =IF(C6<0.05,"n/m",C14/C6) -> 0.1138211 | D15: =IF(D6<0.05,"n/m",D14/D6) -> 0.62187793 | E15: =IF(E6<0.05,"n/m",E14/E6) -> 0.79592339 | F15: =IF(F6<0.05,"n/m",F14/F6) -> 0.85999629 | G15: =IF(G6<0.05,"n/m",G14/G6) -> 0.82673998
A17: OPERATING EXPENSES BY LINE
A18: Rs crore | B18: FY2026-27 | C18: FY2027-28 | D18: FY2028-29 | E18: FY2029-30 | F18: FY2030-31 | G18: Plan total
A19: International expansion | B19: 0 | C19: 0 | D19: 0.54 | E19: 2.43 | F19: 4.92 | G19: =SUM(B19:F19) -> 7.89
A20: People (ex-COGS) | B20: 2.9403753 | C20: 19.737474 | D20: 44.822125 | E20: 74.189567 | F20: 105.6075 | G20: =SUM(B20:F20) -> 247.29705
A21: Certification and audit | B21: 0 | C21: 0.66 | D21: 1.44 | E21: 1.82 | F21: 2.38 | G21: =SUM(B21:F21) -> 6.3
A22: Legal, IP and entities | B22: 0.3 | C22: 0.86 | D22: 1.47 | E22: 2.55 | F22: 2.26 | G22: =SUM(B22:F22) -> 7.44
A23: Standards and regulator affairs | B23: 0.072 | C23: 0.264 | D23: 0.552 | E23: 0.93 | F23: 1.14 | G23: =SUM(B23:F23) -> 2.958
A24: Sales and marketing programmes | B24: 0.220344 | C24: 1.2751679 | D24: 4.5692667 | E24: 14.297698 | F24: 35.36007 | G24: =SUM(B24:F24) -> 55.722547
A25: R&D tooling and evaluation | B25: 0.2643 | C25: 1.0283 | D25: 1.8567 | E25: 2.7003 | F25: 3.466 | G25: =SUM(B25:F25) -> 9.3156
A26: Insurance | B26: 0.0001296 | C26: 0.14301119 | D26: 0.33069778 | E26: 0.89861989 | F26: 2.240858 | G26: =SUM(B26:F26) -> 3.6133165
A27: Facilities, IT and G&A | B27: 0.362916 | C27: 1.569052 | D27: 3.163463 | E27: 5.4863998 | F27: 8.9727633 | G27: =SUM(B27:F27) -> 19.554594
A28: Contingency | B28: 0.22880357 | C28: 1.4045353 | D28: 3.2309339 | E28: 5.7916422 | F28: 9.1490957 | G28: =SUM(B28:F28) -> 19.805011
A29: Total operating expenses | B29: =SUM(B19:B28) -> 4.3888685 | C29: =SUM(C19:C28) -> 26.94154 | D29: =SUM(D19:D28) -> 61.975186 | E29: =SUM(E19:E28) -> 111.09423 | F29: =SUM(F19:F28) -> 175.49629 | G29: =SUM(G19:G28) -> 379.89611
A30: EBITDA | B30: =B14-B29 -> -4.4838725 | C30: =C14-C29 -> -26.726403 | D30: =D14-D29 -> -50.733168 | E30: =E14-E29 -> -46.481176 | F30: =F14-F29 -> 22.575951 | G30: =G14-G29 -> -105.84867
A32: COST AS A PERCENTAGE OF REVENUE
A33: % of revenue | B33: FY2026-27 | C33: FY2027-28 | D33: FY2028-29 | E33: FY2029-30 | F33: FY2030-31 | G33: Plan total
A34: Total cost of revenue | B34: =IF(B6<0.05,"n/m",B13/B6) -> n/m | C34: =IF(C6<0.05,"n/m",C13/C6) -> 0.8861789 | D34: =IF(D6<0.05,"n/m",D13/D6) -> 0.37812207 | E34: =IF(E6<0.05,"n/m",E13/E6) -> 0.20407661 | F34: =IF(F6<0.05,"n/m",F13/F6) -> 0.14000371 | G34: =IF(G6<0.05,"n/m",G13/G6) -> 0.17326002
A35: Runtime and infrastructure (stack1 internal cost + 15%) | B35: =IF(B6<0.05,"n/m",B10/B6) -> n/m | C35: =IF(C6<0.05,"n/m",C10/C6) -> 0.34525939 | D35: =IF(D6<0.05,"n/m",D10/D6) -> 0.21775555 | E35: =IF(E6<0.05,"n/m",E10/E6) -> 0.14140817 | F35: =IF(F6<0.05,"n/m",F10/F6) -> 0.10810632 | G35: =IF(G6<0.05,"n/m",G10/G6) -> 0.12369838
A36: Timestamp anchoring (two authorities) | B36: =IF(B6<0.05,"n/m",B11/B6) -> n/m | C36: =IF(C6<0.05,"n/m",C11/C6) -> 0 | D36: =IF(D6<0.05,"n/m",D11/D6) -> 0.0041266443 | E36: =IF(E6<0.05,"n/m",E11/E6) -> 0.0018693332 | F36: =IF(F6<0.05,"n/m",F11/F6) -> 0.0012549673 | G36: =IF(G6<0.05,"n/m",G11/G6) -> 0.0015548256
A37: Delivery and customer success | B37: =IF(B6<0.05,"n/m",B12/B6) -> n/m | C37: =IF(C6<0.05,"n/m",C12/C6) -> 0.54091951 | D37: =IF(D6<0.05,"n/m",D12/D6) -> 0.15623988 | E37: =IF(E6<0.05,"n/m",E12/E6) -> 0.060799099 | F37: =IF(F6<0.05,"n/m",F12/F6) -> 0.030642422 | G37: =IF(G6<0.05,"n/m",G12/G6) -> 0.048006815
A38: International expansion | B38: =IF(B6<0.05,"n/m",B19/B6) -> n/m | C38: =IF(C6<0.05,"n/m",C19/C6) -> 0 | D38: =IF(D6<0.05,"n/m",D19/D6) -> 0.029871335 | E38: =IF(E6<0.05,"n/m",E19/E6) -> 0.029933486 | F38: =IF(F6<0.05,"n/m",F19/F6) -> 0.021361811 | G38: =IF(G6<0.05,"n/m",G19/G6) -> 0.023802369
A39: People (ex-COGS) | B39: =IF(B6<0.05,"n/m",B20/B6) -> n/m | C39: =IF(C6<0.05,"n/m",C20/C6) -> 10.442376 | D39: =IF(D6<0.05,"n/m",D20/D6) -> 2.4794383 | E39: =IF(E6<0.05,"n/m",E20/E6) -> 0.91388985 | F39: =IF(F6<0.05,"n/m",F20/F6) -> 0.45852998 | G39: =IF(G6<0.05,"n/m",G20/G6) -> 0.74604
A40: Certification and audit | B40: =IF(B6<0.05,"n/m",B21/B6) -> n/m | C40: =IF(C6<0.05,"n/m",C21/C6) -> 0.34918188 | D40: =IF(D6<0.05,"n/m",D21/D6) -> 0.079656894 | E40: =IF(E6<0.05,"n/m",E21/E6) -> 0.022419318 | F40: =IF(F6<0.05,"n/m",F21/F6) -> 0.010333559 | G40: =IF(G6<0.05,"n/m",G21/G6) -> 0.019005694
A41: Legal, IP and entities | B41: =IF(B6<0.05,"n/m",B22/B6) -> n/m | C41: =IF(C6<0.05,"n/m",C22/C6) -> 0.45499457 | D41: =IF(D6<0.05,"n/m",D22/D6) -> 0.081316412 | E41: =IF(E6<0.05,"n/m",E22/E6) -> 0.031411682 | F41: =IF(F6<0.05,"n/m",F22/F6) -> 0.0098125391 | G41: =IF(G6<0.05,"n/m",G22/G6) -> 0.02244482
A42: Standards and regulator affairs | B42: =IF(B6<0.05,"n/m",B23/B6) -> n/m | C42: =IF(C6<0.05,"n/m",C23/C6) -> 0.13967275 | D42: =IF(D6<0.05,"n/m",D23/D6) -> 0.030535143 | E42: =IF(E6<0.05,"n/m",E23/E6) -> 0.011456025 | F42: =IF(F6<0.05,"n/m",F23/F6) -> 0.0049496878 | G42: =IF(G6<0.05,"n/m",G23/G6) -> 0.0089236259
A43: Sales and marketing programmes | B43: =IF(B6<0.05,"n/m",B24/B6) -> n/m | C43: =IF(C6<0.05,"n/m",C24/C6) -> 0.67464472 | D43: =IF(D6<0.05,"n/m",D24/D6) -> 0.25275944 | E43: =IF(E6<0.05,"n/m",E24/E6) -> 0.17612344 | F43: =IF(F6<0.05,"n/m",F24/F6) -> 0.15352746 | G43: =IF(G6<0.05,"n/m",G24/G6) -> 0.16810249
A44: R&D tooling and evaluation | B44: =IF(B6<0.05,"n/m",B25/B6) -> n/m | C44: =IF(C6<0.05,"n/m",C25/C6) -> 0.54403594 | D44: =IF(D6<0.05,"n/m",D25/D6) -> 0.10270761 | E44: =IF(E6<0.05,"n/m",E25/E6) -> 0.033263124 | F44: =IF(F6<0.05,"n/m",F25/F6) -> 0.015048788 | G44: =IF(G6<0.05,"n/m",G25/G6) -> 0.028103086
A45: Insurance | B45: =IF(B6<0.05,"n/m",B26/B6) -> n/m | C45: =IF(C6<0.05,"n/m",C26/C6) -> 0.075661995 | D45: =IF(D6<0.05,"n/m",D26/D6) -> 0.018293304 | E45: =IF(E6<0.05,"n/m",E26/E6) -> 0.011069476 | F45: =IF(F6<0.05,"n/m",F26/F6) -> 0.0097294277 | G45: =IF(G6<0.05,"n/m",G26/G6) -> 0.010900569
A46: Facilities, IT and G&A | B46: =IF(B6<0.05,"n/m",B27/B6) -> n/m | C46: =IF(C6<0.05,"n/m",C27/C6) -> 0.83012806 | D46: =IF(D6<0.05,"n/m",D27/D6) -> 0.17499419 | E46: =IF(E6<0.05,"n/m",E27/E6) -> 0.067583156 | F46: =IF(F6<0.05,"n/m",F27/F6) -> 0.038958226 | G46: =IF(G6<0.05,"n/m",G27/G6) -> 0.058991847
A47: Contingency | B47: =IF(B6<0.05,"n/m",B28/B6) -> n/m | C47: =IF(C6<0.05,"n/m",C28/C6) -> 0.74308828 | D47: =IF(D6<0.05,"n/m",D28/D6) -> 0.1787265 | E47: =IF(E6<0.05,"n/m",E28/E6) -> 0.071343225 | F47: =IF(F6<0.05,"n/m",F28/F6) -> 0.039723832 | G47: =IF(G6<0.05,"n/m",G28/G6) -> 0.059747297
A48: Total operating expenses | B48: =IF(B6<0.05,"n/m",B29/B6) -> n/m | C48: =IF(C6<0.05,"n/m",C29/C6) -> 14.253784 | D48: =IF(D6<0.05,"n/m",D29/D6) -> 3.4282992 | E48: =IF(E6<0.05,"n/m",E29/E6) -> 1.3684928 | F48: =IF(F6<0.05,"n/m",F29/F6) -> 0.76197531 | G48: =IF(G6<0.05,"n/m",G29/G6) -> 1.1460618
A49: FY2026-27 percentages are not meaningful: revenue in that year is Rs 0.01 crore against a full engineering build.
A50: Contingency is set at 5.5% of all other operating cost lines and is held centrally, not allocated to functions.

Sheet Headcount
A1: Headcount plan — all ten functions, 54 months
A2: Headcount at the end of every month from October 2026 to March 2031, then the year-end picture with salary bands and the people-cost bridge.
A3: Counts of people. Months run down the rows; functions across the columns. Bands are fully loaded Rs lakh per year at FY2026-27 rates.
A5: Month end | B5: Kernel engineering | C5: Evidence and cryptography | D5: Pack and regulatory engineering | E5: Platform and SRE | F5: Security, compliance, certification | G5: Product and design | H5: Solutions and field engineering | I5: Go to market and partners | J5: Standards, policy, regulator affairs | K5: Finance, legal and operations | L5: Total
A6: Oct 2026 | B6: 4 | C6: 1 | D6: 1 | E6: 2 | F6: 0 | G6: 1 | H6: 0 | I6: 1 | J6: 0 | K6: 1 | L6: =SUM(B6:K6) -> 11
A7: Nov 2026 | B7: 5 | C7: 1 | D7: 1 | E7: 2 | F7: 0 | G7: 1 | H7: 0 | I7: 1 | J7: 0 | K7: 1 | L7: =SUM(B7:K7) -> 12
A8: Dec 2026 | B8: 5 | C8: 2 | D8: 1 | E8: 2 | F8: 1 | G8: 1 | H8: 1 | I8: 2 | J8: 0 | K8: 1 | L8: =SUM(B8:K8) -> 16
A9: Jan 2027 | B9: 6 | C9: 2 | D9: 2 | E9: 3 | F9: 1 | G9: 2 | H9: 1 | I9: 2 | J9: 1 | K9: 2 | L9: =SUM(B9:K9) -> 22
A10: Feb 2027 | B10: 6 | C10: 3 | D10: 2 | E10: 3 | F10: 2 | G10: 2 | H10: 2 | I10: 3 | J10: 1 | K10: 2 | L10: =SUM(B10:K10) -> 26
A11: Mar 2027 | B11: 7 | C11: 3 | D11: 2 | E11: 3 | F11: 2 | G11: 2 | H11: 2 | I11: 3 | J11: 1 | K11: 2 | L11: =SUM(B11:K11) -> 27
A12: Apr 2027 | B12: 8 | C12: 4 | D12: 3 | E12: 4 | F12: 2 | G12: 2 | H12: 3 | I12: 4 | J12: 1 | K12: 2 | L12: =SUM(B12:K12) -> 33
A13: May 2027 | B13: 9 | C13: 4 | D13: 3 | E13: 4 | F13: 3 | G13: 3 | H13: 3 | I13: 5 | J13: 1 | K13: 3 | L13: =SUM(B13:K13) -> 38
A14: Jun 2027 | B14: 10 | C14: 4 | D14: 4 | E14: 4 | F14: 3 | G14: 3 | H14: 4 | I14: 6 | J14: 2 | K14: 4 | L14: =SUM(B14:K14) -> 44
A15: Jul 2027 | B15: 10 | C15: 5 | D15: 5 | E15: 5 | F15: 3 | G15: 3 | H15: 5 | I15: 6 | J15: 2 | K15: 4 | L15: =SUM(B15:K15) -> 48
A16: Aug 2027 | B16: 11 | C16: 6 | D16: 5 | E16: 6 | F16: 4 | G16: 4 | H16: 5 | I16: 7 | J16: 2 | K16: 4 | L16: =SUM(B16:K16) -> 54
A17: Sep 2027 | B17: 12 | C17: 6 | D17: 6 | E17: 6 | F17: 4 | G17: 4 | H17: 6 | I17: 8 | J17: 2 | K17: 5 | L17: =SUM(B17:K17) -> 59
... A59: Mar 2031 | B59: 38 | C59: 26 | D59: 50 | E59: 27 | F59: 21 | G59: 16 | H59: 40 | I59: 50 | J59: 13 | K59: 24 | L59: =SUM(B59:K59) -> 305
A60: Peak headcount | B60: =MAX(B6:B59) -> 38 | C60: =MAX(C6:C59) -> 26 | D60: =MAX(D6:D59) -> 50 | E60: =MAX(E6:E59) -> 27 | F60: =MAX(F6:F59) -> 21 | G60: =MAX(G6:G59) -> 16 | H60: =MAX(H6:H59) -> 40 | I60: =MAX(I6:I59) -> 50 | ... L60: =MAX(L6:L59) -> 305
A62: HEADCOUNT AT END OF FINANCIAL YEAR, WITH SALARY BANDS
A63: Function | B63: Band Rs L/yr | C63: FY2026-27 | D63: FY2027-28 | E63: FY2028-29 | F63: FY2029-30 | G63: FY2030-31
A64: Kernel engineering | B64: 34 | C64: 7 | D64: 17 | E64: 25 | F64: 32 | G64: 38
A65: Evidence and cryptography | B65: 38 | C65: 3 | D65: 9 | E65: 15 | F65: 21 | G65: 26
A66: Pack and regulatory engineering | B66: 30 | C66: 2 | D66: 11 | E66: 23 | F66: 37 | G66: 50
A67: Platform and SRE | B67: 30 | C67: 3 | D67: 9 | E67: 15 | F67: 21 | G67: 27
A68: Security, compliance, certification | B68: 32 | C68: 2 | D68: 6 | E68: 11 | F68: 16 | G68: 21
A69: Product and design | B69: 28 | C69: 2 | D69: 6 | E69: 10 | F69: 13 | G69: 16
A70: Solutions and field engineering | B70: 26 | C70: 2 | D70: 11 | E70: 22 | F70: 32 | G70: 40
A71: Go to market and partners | B71: 27 | C71: 3 | D71: 14 | E71: 28 | F71: 42 | G71: 50
A72: Standards, policy, regulator affairs | B72: 36 | C72: 1 | D72: 4 | E72: 7 | F72: 10 | G72: 13
A73: Finance, legal and operations | B73: 24 | C73: 2 | D73: 8 | E73: 14 | F73: 19 | G73: 24
A74: Total headcount | C74: =SUM(C64:C73) -> 27 | D74: =SUM(D64:D73) -> 95 | E74: =SUM(E64:E73) -> 170 | F74: =SUM(F64:F73) -> 243 | G74: =SUM(G64:G73) -> 305
A75: Net additions in year | C75: =C74 -> 27 | D75: =D74-C74 -> 68 | E75: =E74-D74 -> 75 | F75: =F74-E74 -> 73 | G75: =G74-F74 -> 62
A76: Bands are fully loaded (salary, employer cost, recruitment, equipment) at FY2026-27 rates and escalate 8% per annum thereafter.
A78: PEOPLE COST BRIDGE
A79: Rs crore | B79: FY2026-27 | C79: FY2027-28 | D79: FY2028-29 | E79: FY2029-30 | F79: FY2030-31 | G79: Plan total
A80: People cost in operating expenses | B80: 2.9403753 | C80: 19.737474 | D80: 44.822125 | E80: 74.189567 | F80: 105.6075 | G80: =SUM(B80:F80) -> 247.29705
A81: Delivery and customer success in COGS | B81: 0.073281312 | C81: 1.0224095 | D81: 2.8244313 | E81: 4.9356701 | F81: 7.0574877 | G81: =SUM(B81:F81) -> 15.91328
A82: Total cash people cost | B82: =B80+B81 -> 3.0136566 | C82: =C80+C81 -> 20.759884 | D82: =D80+D81 -> 47.646556 | E82: =E80+E81 -> 79.125237 | F82: =F80+F81 -> 112.66499 | G82: =G80+G81 -> 263.21033
A83: ESOP charge (non-cash) | B83: 0.33150223 | C83: 2.2835872 | D83: 5.2411212 | E83: 8.7037761 | F83: 12.393149 | G83: =SUM(B83:F83) -> 28.953136
A84: ESOP as % of cash people cost | B84: =IFERROR(B83/B82,"n/m") -> 0.11 | C84: =IFERROR(C83/C82,"n/m") -> 0.11 | D84: =IFERROR(D83/D82,"n/m") -> 0.11 | E84: =IFERROR(E83/E82,"n/m") -> 0.11 | F84: =IFERROR(F83/F82,"n/m") -> 0.11 | G84: =IFERROR(G83/G82,"n/m") -> 0.11
A85: Total people cost including ESOP | B85: =B82+B83 -> 3.3451589 | C85: =C82+C83 -> 23.043471 | D85: =D82+D83 -> 52.887677 | E85: =E82+E83 -> 87.829013 | F85: =F82+F83 -> 125.05814 | G85: =G82+G83 -> 292.16346
A86: Headcount at year end | B86: 27 | C86: 95 | D86: 170 | E86: 243 | F86: 305 | G86: =F86 -> 305
A87: Average cash cost per head (Rs lakh) | B87: =IFERROR(B82*100/B86,0) -> 11.161691 | C87: =IFERROR(C82*100/C86,0) -> 21.852509 | D87: =IFERROR(D82*100/D86,0) -> 28.027386 | E87: =IFERROR(E82*100/E86,0) -> 32.561826 | F87: =IFERROR(F82*100/F86,0) -> 36.939342
A88: Average cash cost per head divides the year's total cash people cost by headcount at year end, so it understates the run-rate band in years of rapid hiring.
A89: The ESOP charge is modelled at 11% of cash people cost. It is non-cash and is charged below EBITDA, between EBITDA and EBIT.

Sheet Unit economics
A1: Unit economics — the governed action
A2: Volumes, revenue per governed action and cost per governed action by financial year and by quarter, with the external price anchors.
A3: Volumes in millions of governed actions. Rates in Rs per governed action, to three decimals. Margins in per cent.
A5: BY FINANCIAL YEAR
A6: Measure | B6: FY2026-27 | C6: FY2027-28 | D6: FY2028-29 | E6: FY2029-30 | F6: FY2030-31 | G6: Plan total
A7: Governed actions — internal (rung1), millions | B7: 0.36 | C7: 13.04 | D7: 54.6 | E7: 139.5 | F7: 280 | G7: =SUM(B7:F7) -> 487.5
A8: Governed actions — external, millions | B8: 0 | C8: 13.285 | D8: 147.792 | E8: 746.088 | F8: 2211.458 | G8: =SUM(B8:F8) -> 3118.623
A9: Governed actions — total, millions | B9: =B7+B8 -> 0.36 | C9: =C7+C8 -> 26.325 | D9: =D7+D8 -> 202.392 | E9: =E7+E8 -> 885.588 | F9: =F7+F8 -> 2491.458 | G9: =G7+G8 -> 3606.123
A10: Revenue (Rs crore) | B10: 0.0144 | C10: 1.8901325 | D10: 18.077531 | E10: 81.179988 | F10: 230.31755 | G10: =SUM(B10:F10) -> 331.47961
A11: Cost of revenue (Rs crore) | B11: 0.10940403 | C11: 1.6749955 | D11: 6.8355136 | E11: 16.566936 | F11: 32.245312 | G11: =SUM(B11:F11) -> 57.432162
A12: Revenue per governed action (Rs) | B12: =IFERROR(B10*10000000/(B9*1000000),0) -> 0.4 | C12: =IFERROR(C10*10000000/(C9*1000000),0) -> 0.71799904 | D12: =IFERROR(D10*10000000/(D9*1000000),0) -> 0.89319397 | E12: =IFERROR(E10*10000000/(E9*1000000),0) -> 0.91667895 | F12: =IFERROR(F10*10000000/(F9*1000000),0) -> 0.92442881 | G12: =IFERROR(G10*10000000/(G9*1000000),0) -> 0.91921326
A13: Cost per governed action (Rs) | B13: =IFERROR(B11*10000000/(B9*1000000),0) -> 3.039001 | C13: =IFERROR(C11*10000000/(C9*1000000),0) -> 0.6362756 | D13: =IFERROR(D11*10000000/(D9*1000000),0) -> 0.33773636 | E13: =IFERROR(E11*10000000/(E9*1000000),0) -> 0.18707273 | F13: =IFERROR(F11*10000000/(F9*1000000),0) -> 0.12942346 | G13: =IFERROR(G11*10000000/(G9*1000000),0) -> 0.1592629
A14: Contribution per governed action (Rs) | B14: =B12-B13 -> -2.639001 | C14: =C12-C13 -> 0.081723437 | D14: =D12-D13 -> 0.55545762 | E14: =E12-E13 -> 0.72960622 | F14: =F12-F13 -> 0.79500534 | G14: =G12-G13 -> 0.75995035
A15: Gross margin % | B15: =IFERROR((B10-B11)/B10,"n/m") -> -6.5975024 | C15: =IFERROR((C10-C11)/C10,"n/m") -> 0.1138211 | D15: =IFERROR((D10-D11)/D10,"n/m") -> 0.62187793 | E15: =IFERROR((E10-E11)/E10,"n/m") -> 0.79592339 | F15: =IFERROR((F10-F11)/F10,"n/m") -> 0.85999629 | G15: =IFERROR((G10-G11)/G10,"n/m") -> 0.82673998
A16: FY2026-27 revenue per action is the Rs 0.40 internal transfer price only; cost per action that year carries the fixed anchoring and platform floor across 0.36 million actions, so margin is not meaningful.
A18: BY QUARTER — all 18 quarters
A19: Measure | B19: 2026/27 Q3 | C19: 2026/27 Q4 | D19: 2027/28 Q1 | E19: 2027/28 Q2 | F19: 2027/28 Q3 | G19: 2027/28 Q4 | H19: 2028/29 Q1 | I19: 2028/29 Q2 | J19: 2028/29 Q3 | K19: 2028/29 Q4 | L19: 2029/30 Q1 | M19: 2029/30 Q2 | N19: 2029/30 Q3 | O19: 2029/30 Q4 | P19: 2030/31 Q1 | Q19: 2030/31 Q2 | R19: 2030/31 Q3 | S19: 2030/31 Q4 | T19: Plan
A20: Governed actions — internal, millions | B20: 0 | C20: 0.36 | D20: 1.02 | E20: 2.22 | F20: 3.9 | G20: 5.9 | H20: 8.5 | I20: 11.35 | J20: 15.2 | K20: 19.55 | L20: 25 | M20: 31 | N20: 38 | O20: 45.5 | P20: 54.5 | Q20: 64.25 | R20: 75 | S20: 86.25 | T20: =SUM(B20:S20) -> 487.5
A21: Governed actions — external, millions | B21: 0 | C21: 0 | D21: 0 | E21: 1.385 | F21: 3.995 | G21: 7.905 | H21: 16.01 | I21: 26.867 | J21: 42.22 | K21: 62.695 | L21: 90.822 | M21: 152.45 | N21: 214.884 | O21: 287.931 | P21: 373.005 | Q21: 478.435 | R21: 605.508 | S21: 754.51 | T21: =SUM(B21:S21) -> 3118.622
A22: Governed actions — total, millions | B22: =B20+B21 -> 0 | C22: =C20+C21 -> 0.36 | D22: =D20+D21 -> 1.02 | E22: =E20+E21 -> 3.605 | F22: =F20+F21 -> 7.895 | G22: =G20+G21 -> 13.805 | H22: =H20+H21 -> 24.51 | I22: =I20+I21 -> 38.217 | ... T22: =T20+T21 -> 3606.122
A23: Revenue (Rs crore) | B23: 0 | C23: 0.0144 | D23: 0.0408 | E23: 0.22217028 | F23: 0.56226022 | G23: 1.064902 | H23: 2.0478631 | I23: 3.3398867 | J23: 5.1549781 | K23: 7.5348036 | L23: 10.735863 | M23: 16.756142 | N23: 23.114551 | O23: 30.573432 | P23: 39.345087 | Q23: 50.014703 | R23: 62.876635 | S23: 78.08113 | T23: =SUM(B23:S23) -> 331.47961
A24: Cost of revenue (Rs crore) | B24: 0.028570504 | C24: 0.08083353 | D24: 0.14973483 | E24: 0.29014539 | F24: 0.49256854 | G24: 0.74254676 | H24: 1.0916936 | I24: 1.4607987 | J24: 1.8848339 | K24: 2.3981874 | L24: 2.9716191 | M24: 3.7362823 | N24: 4.5302562 | O24: 5.3287789 | P24: 6.2495625 | Q24: 7.3475933 | R24: 8.6058982 | S24: 10.042258 | T24: =SUM(B24:S24) -> 57.432162
A25: Revenue per governed action (Rs) | B25: =IFERROR(B23*10000000/(B22*1000000),0) -> 0 | C25: =IFERROR(C23*10000000/(C22*1000000),0) -> 0.4 | D25: =IFERROR(D23*10000000/(D22*1000000),0) -> 0.4 | E25: =IFERROR(E23*10000000/(E22*1000000),0) -> 0.61628372 | F25: =IFERROR(F23*10000000/(F22*1000000),0) -> 0.71217254 | G25: =IFERROR(G23*10000000/(G22*1000000),0) -> 0.7713886 | H25: =IFERROR(H23*10000000/(H22*1000000),0) -> 0.83552148 | I25: =IFERROR(I23*10000000/(I22*1000000),0) -> 0.87392696 | ... T25: =IFERROR(T23*10000000/(T22*1000000),0) -> 0.91921351
A26: Cost per governed action (Rs) | B26: =IFERROR(B24*10000000/(B22*1000000),0) -> 0 | C26: =IFERROR(C24*10000000/(C22*1000000),0) -> 2.2453758 | D26: =IFERROR(D24*10000000/(D22*1000000),0) -> 1.4679885 | E26: =IFERROR(E24*10000000/(E22*1000000),0) -> 0.80484159 | F26: =IFERROR(F24*10000000/(F22*1000000),0) -> 0.62389935 | G26: =IFERROR(G24*10000000/(G22*1000000),0) -> 0.53788248 | H26: =IFERROR(H24*10000000/(H22*1000000),0) -> 0.44540743 | I26: =IFERROR(I24*10000000/(I22*1000000),0) -> 0.38223793 | ... T26: =IFERROR(T24*10000000/(T22*1000000),0) -> 0.15926295
A27: Gross margin % | B27: =IFERROR((B23-B24)/B23,"n/m") -> n/m | C27: =IFERROR((C23-C24)/C23,"n/m") -> -4.6134396 | D27: =IFERROR((D23-D24)/D23,"n/m") -> -2.6699713 | E27: =IFERROR((E23-E24)/E23,"n/m") -> -0.30595952 | F27: =IFERROR((F23-F24)/F23,"n/m") -> 0.12394916 | G27: =IFERROR((G23-G24)/G23,"n/m") -> 0.30270881 | H27: =IFERROR((H23-H24)/H23,"n/m") -> 0.46691085 | I27: =IFERROR((I23-I24)/I23,"n/m") -> 0.56262028 | ... T27: =IFERROR((T23-T24)/T23,"n/m") -> 0.82673998
A29: PRICE ANCHORS — Rs per governed action
A30: Anchor | B30: Rs per action | C30: US$ per action | D30: Note
A31: Elan1 Govern — internal transfer price to rung1 | B31: 0.4 | C31: =B31/90 -> 0.0044444444 | D31: Cost-plus transfer inside the group; the floor of the price book
A32: Elan1 Govern — L1 Guarded, beyond allowance | B32: 1.6 | C32: =B32/90 -> 0.017777778 | D32: 480,000 actions included per tenant per year
A33: Elan1 Govern — L2 Attested, beyond allowance | B33: 1.2 | C33: =B33/90 -> 0.013333333 | D33: 1,500,000 actions included per tenant per year
A34: Elan1 Govern — L3 Proven, beyond allowance | B34: 0.9 | C34: =B34/90 -> 0.01 | D34: 4,200,000 actions included per tenant per year
A35: Elan1 Govern — sovereign deployment | B35: 0.55 | C35: =B35/90 -> 0.0061111111 | D35: On-premises; the platform floor carries the fixed cost
A36: Salesforce Agentforce | B36: 9 | C36: =B36/90 -> 0.1 | D36: US$0.10 per action (about Rs 8.80 at spot; Rs 9.00 at the workbook's Rs 90.00 rate)
A37: Elan1 Govern blended realised rate, FY2030-31 | B37: =F12 -> 0.92442881 | C37: =B37/90 -> 0.010271431 | D37: Blended across internal and external volume at plan mix
A38: Microsoft Agent 365 is priced at US$15 per user per month. That is a per-seat anchor, not a per-action one, and is not directly comparable to a governed-action rate; it is quoted here only to frame the buyer's alternative.
A39: Elan1 Govern prices governed actions, not seats. Refusals are metered at quantity zero and are never billed, so the buyer pays only for actions that were allowed to complete.

Sheet Cash and funding
A1: Cash and funding — 54-month chain
A2: Opening cash, EBITDA, capex, working capital and funding for every month of the plan. Closing cash is a live formula; the four funding events are highlighted.
A3: Rs crore. Working capital movement is the change in receivables at 55 days DSO on external revenue; a build in receivables is a cash outflow.
A5: Month | B5: Opening cash | C5: EBITDA | D5: Capex | E5: Working capital movement | F5: Funding in | G5: Closing cash | H5: Net burn
A6: Oct 2026 | B6: 0 | C6: -0.47659267 | D6: 0.00952 | E6: 0 | F6: 8 | G6: =B6+C6-D6+E6+F6 -> 7.5138873 | H6: =-C6+D6-E6 -> 0.48611267 | I6: Founder and angel bridge — Rs 8.0 cr
A7: Nov 2026 | B7: =G6 -> 7.5138873 | C7: -0.51125437 | D7: 0.00984 | E7: 0 | F7: 0 | G7: =B7+C7-D7+E7+F7 -> 6.992793 | H7: =-C7+D7-E7 -> 0.52109437
A8: Dec 2026 | B8: =G7 -> 6.992793 | C8: -0.73536624 | D8: 0.01112 | E8: 0 | F8: 0 | G8: =B8+C8-D8+E8+F8 -> 6.2463067 | H8: =-C8+D8-E8 -> 0.74648624
A9: Jan 2027 | B9: =G8 -> 6.2463067 | C9: -0.82075105 | D9: 0.01304 | E9: 0 | F9: 0 | G9: =B9+C9-D9+E9+F9 -> 5.4125157 | H9: =-C9+D9-E9 -> 0.83379105
A10: Feb 2027 | B10: =G9 -> 5.4125157 | C10: -0.95161877 | D10: 0.01432 | E10: 0 | F10: 0 | G10: =B10+C10-D10+E10+F10 -> 4.4465769 | H10: =-C10+D10-E10 -> 0.96593877
A11: Mar 2027 | B11: =G10 -> 4.4465769 | C11: -0.98828944 | D11: 0.01464 | E11: 0 | F11: 63 | G11: =B11+C11-D11+E11+F11 -> 66.443647 | H11: =-C11+D11-E11 -> 1.0029294 | I11: Series A tranche 1 (close, Mar 2027) — Rs 63.0 cr
A12: Apr 2027 | B12: =G11 -> 66.443647 | C12: -1.1829419 | D12: 0.15656 | E12: 0 | F12: 0 | G12: =B12+C12-D12+E12+F12 -> 65.104146 | H12: =-C12+D12-E12 -> 1.3395019
A13: May 2027 | B13: =G12 -> 65.104146 | C13: -1.3410407 | D13: 0.01816 | E13: 0 | F13: 0 | G13: =B13+C13-D13+E13+F13 -> 63.744945 | H13: =-C13+D13-E13 -> 1.3592007
A14: Jun 2027 | B14: =G13 -> 63.744945 | C14: -1.7223382 | D14: 0.02008 | E14: 0 | F14: 0 | G14: =B14+C14-D14+E14+F14 -> 62.002527 | H14: =-C14+D14-E14 -> 1.7424182
A15: Jul 2027 | B15: =G14 -> 62.002527 | C15: -1.6670095 | D15: 0.02136 | E15: -0.039624457 | F15: 0 | G15: =B15+C15-D15+E15+F15 -> 60.274533 | H15: =-C15+D15-E15 -> 1.727994
A16: Aug 2027 | B16: =G15 -> 60.274533 | C16: -1.862387 | D16: 0.02328 | E16: -0.040476391 | F16: 0 | G16: =B16+C16-D16+E16+F16 -> 58.348389 | H16: =-C16+D16-E16 -> 1.9261434
A17: Sep 2027 | B17: =G16 -> 58.348389 | C17: -2.2431193 | D17: 0.02488 | E17: -0.041336546 | F17: 0 | G17: =B17+C17-D17+E17+F17 -> 56.039053 | H17: =-C17+D17-E17 -> 2.3093359
A18: Oct 2027 | B18: =G17 -> 56.039053 | C18: -2.206644 | D18: 0.02648 | E18: -0.061659805 | F18: 0 | G18: =B18+C18-D18+E18+F18 -> 53.74427 | H18: =-C18+D18-E18 -> 2.2947838
A19: Nov 2027 | B19: =G18 -> 53.74427 | C19: -2.4963065 | D19: 0.02936 | E19: -0.060043263 | F19: 0 | G19: =B19+C19-D19+E19+F19 -> 51.15856 | H19: =-C19+D19-E19 -> 2.5857097
A20: Dec 2027 | B20: =G19 -> 51.15856 | C20: -2.8673351 | D20: 0.03032 | E20: -0.0652294 | F20: 0 | G20: =B20+C20-D20+E20+F20 -> 48.195675 | H20: =-C20+D20-E20 -> 2.9628845
A21: Jan 2028 | B21: =G20 -> 48.195675 | C21: -3.0062253 | D21: 0.03192 | E21: -0.093556072 | F21: 0 | G21: =B21+C21-D21+E21+F21 -> 45.063974 | H21: =-C21+D21-E21 -> 3.1317014
A22: Feb 2028 | B22: =G21 -> 45.063974 | C22: -2.9720448 | D22: 0.03448 | E22: -0.097786774 | F22: 0 | G22: =B22+C22-D22+E22+F22 -> 41.959662 | H22: =-C22+D22-E22 -> 3.1043116
A23: Mar 2028 | B23: =G22 -> 41.959662 | C23: -3.159011 | D23: 0.0364 | E23: -0.097485068 | F23: 0 | G23: =B23+C23-D23+E23+F23 -> 38.666766 | H23: =-C23+D23-E23 -> 3.292896
... A29: Sep 2028 | B29: =G28 -> 18.457982 | C29: -4.0019215 | D29: 0.04824 | E29: -0.27572453 | F29: 0 | G29: =B29+C29-D29+E29+F29 -> 14.132096 | H29: =-C29+D29-E29 -> 4.325886
A30: Oct 2028 | B30: =G29 -> 14.132096 | C30: -4.6835942 | D30: 0.05016 | E30: -0.34597661 | F30: 72 | G30: =B30+C30-D30+E30+F30 -> 81.052365 | H30: =-C30+D30-E30 -> 5.0797308 | I30: Series A tranche 2 (Gate A, Oct 2028) — Rs 72.0 cr
A31: Nov 2028 | B31: =G30 -> 81.052365 | C31: -4.3477123 | D31: 0.05208 | E31: -0.36913878 | F31: 0 | G31: =B31+C31-D31+E31+F31 -> 76.283434 | H31: =-C31+D31-E31 -> 4.768931
A32: Dec 2028 | B32: =G31 -> 76.283434 | C32: -4.4671088 | D32: 0.05432 | E32: -0.39477796 | F32: 0 | G32: =B32+C32-D32+E32+F32 -> 71.367227 | H32: =-C32+D32-E32 -> 4.9162067
A33: Jan 2029 | B33: =G32 -> 71.367227 | C33: -5.2838191 | D33: 0.05624 | E33: -0.44424927 | F33: 0 | G33: =B33+C33-D33+E33+F33 -> 65.582919 | H33: =-C33+D33-E33 -> 5.7843084
A34: Feb 2029 | B34: =G33 -> 65.582919 | C34: -4.5938847 | D34: 0.05848 | E34: -0.4996485 | F34: 0 | G34: =B34+C34-D34+E34+F34 -> 60.430906 | H34: =-C34+D34-E34 -> 5.1520132
A35: Mar 2029 | B35: =G34 -> 60.430906 | C35: -4.6428034 | D35: 0.0604 | E35: -0.49787638 | F35: 0 | G35: =B35+C35-D35+E35+F35 -> 55.229826 | H35: =-C35+D35-E35 -> 5.2010798
A36: Apr 2029 | B36: =G35 -> 55.229826 | C36: -5.1387535 | D36: 0.20232 | E36: -0.59155892 | F36: 0 | G36: =B36+C36-D36+E36+F36 -> 49.297193 | H36: =-C36+D36-E36 -> 5.9326324
A37: May 2029 | B37: =G36 -> 49.297193 | C37: -4.615336 | D37: 0.06424 | E37: -0.68129691 | F37: 0 | G37: =B37+C37-D37+E37+F37 -> 43.936321 | H37: =-C37+D37-E37 -> 5.3608729
A38: Jun 2029 | B38: =G37 -> 43.936321 | C38: -4.5217424 | D38: 0.06584 | E38: -0.76135307 | F38: 0 | G38: =B38+C38-D38+E38+F38 -> 38.587385 | H38: =-C38+D38-E38 -> 5.3489355
A39: Jul 2029 | B39: =G38 -> 38.587385 | C39: -5.1672947 | D39: 0.0684 | E39: -1.4272539 | F39: 45 | G39: =B39+C39-D39+E39+F39 -> 76.924436 | H39: =-C39+D39-E39 -> 6.6629486 | I39: Series A tranche 3 (Gate B, Jul 2029) — Rs 45.0 cr
A40: Aug 2029 | B40: =G39 -> 76.924436 | C40: -4.0368766 | D40: 0.07032 | E40: -1.5227914 | F40: 0 | G40: =B40+C40-D40+E40+F40 -> 71.294448 | H40: =-C40+D40-E40 -> 5.629988
A41: Sep 2029 | B41: =G40 -> 71.294448 | C41: -3.8683712 | D41: 0.07192 | E41: -0.92066464 | F41: 0 | G41: =B41+C41-D41+E41+F41 -> 66.433493 | H41: =-C41+D41-E41 -> 4.8609559
A42: Oct 2029 | B42: =G41 -> 66.433493 | C42: -4.3341625 | D42: 0.07384 | E42: -1.0214647 | F42: 0 | G42: =B42+C42-D42+E42+F42 -> 61.004025 | H42: =-C42+D42-E42 -> 5.4294672
A43: Nov 2029 | B43: =G42 -> 61.004025 | C43: -3.3341515 | D43: 0.07576 | E43: -1.7102325 | F43: 0 | G43: =B43+C43-D43+E43+F43 -> 55.883881 | H43: =-C43+D43-E43 -> 5.120144
A44: Dec 2029 | B44: =G43 -> 55.883881 | C44: -3.1859574 | D44: 0.07832 | E44: -1.1421148 | F44: 0 | G44: =B44+C44-D44+E44+F44 -> 51.477489 | H44: =-C44+D44-E44 -> 4.4063922
A45: Jan 2030 | B45: =G44 -> 51.477489 | C45: -3.8842952 | D45: 0.07992 | E45: -1.250105 | F45: 0 | G45: =B45+C45-D45+E45+F45 -> 46.263169 | H45: =-C45+D45-E45 -> 5.2143202
A46: Feb 2030 | B46: =G45 -> 46.263169 | C46: -2.3510754 | D46: 0.08184 | E46: -1.9081431 | F46: 0 | G46: =B46+C46-D46+E46+F46 -> 41.92211 | H46: =-C46+D46-E46 -> 4.3410584
A47: Mar 2030 | B47: =G46 -> 41.92211 | C47: -2.0431594 | D47: 0.08376 | E47: -1.3837637 | F47: 0 | G47: =B47+C47-D47+E47+F47 -> 38.411427 | H47: =-C47+D47-E47 -> 3.5106831
A48: Apr 2030 | B48: =G47 -> 38.411427 | C48: -2.4025569 | D48: 0.22504 | E48: -1.5635364 | F48: 0 | G48: =B48+C48-D48+E48+F48 -> 34.220294 | H48: =-C48+D48-E48 -> 4.1911333
A49: May 2030 | B49: =G48 -> 34.220294 | C49: -1.1286113 | D49: 0.08696 | E49: -2.1258107 | F49: 0 | G49: =B49+C49-D49+E49+F49 -> 30.878912 | H49: =-C49+D49-E49 -> 3.3413819
A50: Jun 2030 | B50: =G49 -> 30.878912 | C50: -0.70415446 | D50: 0.08856 | E50: -1.5922144 | F50: 0 | G50: =B50+C50-D50+E50+F50 -> 28.493983 | H50: =-C50+D50-E50 -> 2.3849289
A51: Jul 2030 | B51: =G50 -> 28.493983 | C51: -0.84148494 | D51: 0.0908 | E51: -2.3815511 | F51: 0 | G51: =B51+C51-D51+E51+F51 -> 25.180147 | H51: =-C51+D51-E51 -> 3.313836
... A59: Mar 2031 | B59: =G58 -> 26.907837 | C59: 7.0821679 | D59: 0.1036 | E59: -3.4769084 | F59: 0 | G59: =B59+C59-D59+E59+F59 -> 30.409496 | H59: =-C59+D59-E59 -> -3.5016595
A60: Plan total | C60: =SUM(C6:C59) -> -105.84867 | D60: =SUM(D6:D59) -> 3.54896 | E60: =SUM(E6:E59) -> -48.192875 | F60: =SUM(F6:F59) -> 188 | G60: =G59 -> 30.409496 | H60: =SUM(H6:H59) -> 157.5905
A62: FUNDING AND CASH SUMMARY
A63: Measure | B63: Value | C63: Note
A64: Total funding into the plan | B64: =SUM(F6:F59) -> 188 | C64: Rs 8.0 cr bridge plus Rs 180.0 cr Series A
A65: of which Series A | B65: =SUM(F6:F59)-F6 -> 180 | C65: Three tranches against gates
A66: Closing cash, March 2031 | B66: =G59 -> 30.409496 | C66: After the full plan, with no further raise
A67: Minimum cash across the plan | B67: =MIN(G6:G59) -> 4.4465769 | C67: The tightest month of the plan
A68: Month of minimum cash | B68: =INDEX(A6:A59,MATCH(MIN(G6:G59),G6:G59,0)) -> Feb 2027 | C68: The month before tranche 1 closes
A69: Cumulative EBITDA across the plan | B69: =SUM(C6:C59) -> -105.84867 | C69: Losses to FY2029-30, profit from FY2030-31
A70: Cumulative capex | B70: =SUM(D6:D59) -> 3.54896 | C70: Equipment, fit-out and platform hardware
A71: Peak monthly burn | B71: =MAX(H6:H59) -> 6.6629486 | C71: Worst single month of net cash outflow
A72: Peak monthly burn month | B72: =INDEX(A6:A59,MATCH(MAX(H6:H59),H6:H59,0)) -> Jul 2029 | C72: Peak burn precedes the crossover to profit
A73: Months of the plan | B73: 54 | C73: October 2026 to March 2031
A74: Net burn is EBITDA less capex less the working capital build, signed so that a positive figure is cash going out of the door.
A75: No debt, no interest income and no tax are modelled. Cash is held in rupees; the US$ view is presentational only.

Sheet Scenarios
A1: Scenarios — base, downside and upside
A2: The same engine run with three sets of drivers. Revenue and EBITDA by financial year, then the cash and ARR outcomes each scenario produces.
A3: Rs crore. Scenario drivers are stated in full below the tables; nothing is adjusted outside them.
A5: REVENUE BY FINANCIAL YEAR
A6: Rs crore | B6: Base | C6: Downside | D6: Upside | E6: Upside less downside
A7: FY2026-27 | B7: 0.0144 | C7: 0.0144 | D7: 0.0144 | E7: =D7-C7 -> 0
A8: FY2027-28 | B8: 1.8901325 | C8: 0.58503091 | D8: 2.5990323 | E8: =D8-C8 -> 2.0140014
A9: FY2028-29 | B9: 18.077531 | C9: 4.9562305 | D9: 26.310381 | E9: =D9-C9 -> 21.35415
A10: FY2029-30 | B10: 81.179988 | C10: 22.96403 | D10: 120.34078 | E10: =D10-C10 -> 97.376752
A11: FY2030-31 | B11: 230.31755 | C11: 75.385917 | D11: 343.82045 | E11: =D11-C11 -> 268.43453
A12: Plan total revenue | B12: =SUM(B7:B11) -> 331.47961 | C12: =SUM(C7:C11) -> 103.90561 | D12: =SUM(D7:D11) -> 493.08504 | E12: =SUM(E7:E11) -> 389.17943
A14: EBITDA BY FINANCIAL YEAR
A15: Rs crore | B15: Base | C15: Downside | D15: Upside | E15: Upside less downside
A16: FY2026-27 | B16: -4.4838725 | C16: -4.2007206 | D16: -4.6506749 | E16: =D16-C16 -> -0.44995432
A17: FY2027-28 | B17: -26.726403 | C17: -26.514096 | D17: -26.961166 | E17: =D17-C17 -> -0.44706941
A18: FY2028-29 | B18: -50.733168 | C18: -61.020019 | D18: -44.432485 | E18: =D18-C18 -> 16.587534
A19: FY2029-30 | B19: -46.481176 | C19: -100.56526 | D19: -10.438796 | E19: =D19-C19 -> 90.126468
A20: FY2030-31 | B20: 22.575951 | C20: -127.16491 | D20: 131.63862 | E20: =D20-C20 -> 258.80353
A21: Cumulative EBITDA | B21: =SUM(B16:B20) -> -105.84867 | C21: =SUM(C16:C20) -> -319.46501 | D21: =SUM(D16:D20) -> 45.155496 | E21: =SUM(E16:E20) -> 364.62051
A23: OUTCOMES
A24: Measure | B24: Base | C24: Downside | D24: Upside
A25: Closing cash, March 2031 | B25: 30.409496 | C25: -157.93451 | D25: 156.44975
A26: Minimum cash across the plan | B26: 4.4465769 | C26: -157.93451 | D26: 4.3157952
A27: Exit ARR, March 2031 | B27: 334.22544 | C27: 111.89285 | D27: 499.89502
A28: FY2030-31 revenue | B28: =B11 -> 230.31755 | C28: =C11 -> 75.385917 | D28: =D11 -> 343.82045
A29: Revenue vs base | B29: =IFERROR(B11/B11,"n/m") -> 1 | C29: =IFERROR(C11/B11,"n/m") -> 0.32731294 | D29: =IFERROR(D11/B11,"n/m") -> 1.4928104
A31: SCENARIO DEFINITIONS
A32: Scenario | B32: Tenant additions | C32: Pricing | D32: Unit cost | E32: Timing
A33: Base | B33: As modelled | C33: Price book as listed | D33: As modelled | E33: No slip
A34: Downside | B34: 58% of base | C34: 82% of base | D34: 122% of base | E34: Six-month slip in every revenue event
A35: Upside | B35: 138% of base | C35: 110% of base | D35: 92% of base | E35: No slip
A37: Each scenario is a clean re-run of the same engine with those four drivers changed. Nothing else is adjusted.
A38: The unmitigated downside runs out of cash: closing cash of Rs -157.9 crore in March 2031, with the shortfall opening in FY2029-30.
A39: The management response — hiring freeze, pack programme cut to the two funded packs, international expansion deferred — is a named action,
A40: not an assumption inside the scenario. It is deliberately excluded so that the downside shows the unmitigated shape of the risk.
A41: The upside needs no extra capital: minimum cash of Rs 4.3 crore is set in February 2027, before any of the upside drivers bite.
A43: Scope widening (27 October 2026): Elan1 Govern governs every agent tool call, reads and writes, in any industry, not only ERP writes in Indian finance. It is not in the base: there is no new customer evidence and the tenant ramp is not industry-specific. It is one reason the Upside's 138% tenant additions is plausible; no driver is changed.
A45: ELAN1 GOVERN SENSITIVITIES — TOP MODEL RISK: THE RUNTIME COST OF GOVERNING READS
A46: The code audit (commit 22388ad) confirms that every governed call, reads included, writes a signed hash-chained receipt; per-read cost is unmeasured, and the engine's cost per governed action covers writes only. Each column computes its case regardless of the live switches. Not part of the base: engine outputs above are unchanged. Indicative: reads at financial-year grain, no working-capital timing, no channel contra on read revenue.
A47: Measure | B47: Base (engine, all switches OFF) | C47: Governance layer on | D47: Reads governed: 2× volume, 0.5× cost | E47: Reads governed: 1× volume, 1× cost | F47: Reads governed: 2× volume, 1× cost (stress) | G47: Reads billed at Rs 0.10 for half, plus cost (2×, 0.5×)
A48: Read : write ratio | B48: 0 | C48: 0 | D48: 2 | E48: 1 | F48: 2 | G48: 2
A49: Read check cost (× cost per governed action) | B49: 0 | C49: 0 | D49: 0.5 | E49: 1 | F49: 1 | G49: 0.5
A50: Share of reads billed | B50: 0 | C50: 0 | D50: 0 | E50: 0 | F50: 0 | G50: 0.5
A51: Read price (Rs per billed read) | B51: 0 | C51: 0 | D51: 0 | E51: 0 | F51: 0 | G51: 0.1
A52: Governance layer included (1 = yes) | B52: 0 | C52: 1 | D52: 0 | E52: 0 | F52: 0 | G52: 0
A53: FY2030-31 revenue | B53: ='Summary P&L'!F6+(B$52*'Govern overlay'!F65+'Govern overlay'!F76*B$48*B$50*B$51) -> 230.31755 | C53: ='Summary P&L'!F6+(C$52*'Govern overlay'!F65+'Govern overlay'!F76*C$48*C$50*C$51) -> 231.09149 | D53: ='Summary P&L'!F6+(D$52*'Govern overlay'!F65+'Govern overlay'!F76*D$48*D$50*D$51) -> 230.31755 | E53: ='Summary P&L'!F6+(E$52*'Govern overlay'!F65+'Govern overlay'!F76*E$48*E$50*E$51) -> 230.31755 | F53: ='Summary P&L'!F6+(F$52*'Govern overlay'!F65+'Govern overlay'!F76*F$48*F$50*F$51) -> 230.31755 | G53: ='Summary P&L'!F6+(G$52*'Govern overlay'!F65+'Govern overlay'!F76*G$48*G$50*G$51) -> 252.43213
A54: FY2028-29 gross margin % | B54: =('Summary P&L'!D6+(B$52*'Govern overlay'!D65+'Govern overlay'!D76*B$48*B$50*B$51)-'Summary P&L'!D7-(B$52*'Govern overlay'!D66+'Govern overlay'!D75*B$48*B$49))/('Summary P&L'!D6+(B$52*'Govern overlay'!D65+'Govern overlay'!D76*B$48*B$50*B$51)) -> 0.62187793 | C54: =('Summary P&L'!D6+(C$52*'Govern overlay'!D65+'Govern overlay'!D76*C$48*C$50*C$51)-'Summary P&L'!D7-(C$52*'Govern overlay'!D66+'Govern overlay'!D75*C$48*C$49))/('Summary P&L'!D6+(C$52*'Govern overlay'!D65+'Govern overlay'!D76*C$48*C$50*C$51)) -> 0.62285779 | D54: =('Summary P&L'!D6+(D$52*'Govern overlay'!D65+'Govern overlay'!D76*D$48*D$50*D$51)-'Summary P&L'!D7-(D$52*'Govern overlay'!D66+'Govern overlay'!D75*D$48*D$49))/('Summary P&L'!D6+(D$52*'Govern overlay'!D65+'Govern overlay'!D76*D$48*D$50*D$51)) -> 0.54695766 | E54: =('Summary P&L'!D6+(E$52*'Govern overlay'!D65+'Govern overlay'!D76*E$48*E$50*E$51)-'Summary P&L'!D7-(E$52*'Govern overlay'!D66+'Govern overlay'!D75*E$48*E$49))/('Summary P&L'!D6+(E$52*'Govern overlay'!D65+'Govern overlay'!D76*E$48*E$50*E$51)) -> 0.54695766 | F54: =('Summary P&L'!D6+(F$52*'Govern overlay'!D65+'Govern overlay'!D76*F$48*F$50*F$51)-'Summary P&L'!D7-(F$52*'Govern overlay'!D66+'Govern overlay'!D75*F$48*F$49))/('Summary P&L'!D6+(F$52*'Govern overlay'!D65+'Govern overlay'!D76*F$48*F$50*F$51)) -> 0.47203739 | G54: =('Summary P&L'!D6+(G$52*'Govern overlay'!D65+'Govern overlay'!D76*G$48*G$50*G$51)-'Summary P&L'!D7-(G$52*'Govern overlay'!D66+'Govern overlay'!D75*G$48*G$49))/('Summary P&L'!D6+(G$52*'Govern overlay'!D65+'Govern overlay'!D76*G$48*G$50*G$51)) -> 0.58119672
A55: FY2028-29 gross margin change vs base (percentage points) | B55: =(B54-$B$54)*100 -> 0 | C55: =(C54-$B$54)*100 -> 0.097985706 | D55: =(D54-$B$54)*100 -> -7.492027 | E55: =(E54-$B$54)*100 -> -7.492027 | F55: =(F54-$B$54)*100 -> -14.984054 | G55: =(G54-$B$54)*100 -> -4.0681207
A56: FY2029-30 EBITDA | B56: ='Summary P&L'!E11+(B$52*'Govern overlay'!E65+'Govern overlay'!E76*B$48*B$50*B$51)-(B$52*'Govern overlay'!E66+'Govern overlay'!E75*B$48*B$49) -> -46.481176 | C56: ='Summary P&L'!E11+(C$52*'Govern overlay'!E65+'Govern overlay'!E76*C$48*C$50*C$51)-(C$52*'Govern overlay'!E66+'Govern overlay'!E75*C$48*C$49) -> -46.22147 | D56: ='Summary P&L'!E11+(D$52*'Govern overlay'!E65+'Govern overlay'!E76*D$48*D$50*D$51)-(D$52*'Govern overlay'!E66+'Govern overlay'!E75*D$48*D$49) -> -51.515522 | E56: ='Summary P&L'!E11+(E$52*'Govern overlay'!E65+'Govern overlay'!E76*E$48*E$50*E$51)-(E$52*'Govern overlay'!E66+'Govern overlay'!E75*E$48*E$49) -> -51.515522 | F56: ='Summary P&L'!E11+(F$52*'Govern overlay'!E65+'Govern overlay'!E76*F$48*F$50*F$51)-(F$52*'Govern overlay'!E66+'Govern overlay'!E75*F$48*F$49) -> -56.549869 | G56: ='Summary P&L'!E11+(G$52*'Govern overlay'!E65+'Govern overlay'!E76*G$48*G$50*G$51)-(G$52*'Govern overlay'!E66+'Govern overlay'!E75*G$48*G$49) -> -44.054642
A57: FY2030-31 gross margin % | B57: =('Summary P&L'!F6+(B$52*'Govern overlay'!F65+'Govern overlay'!F76*B$48*B$50*B$51)-'Summary P&L'!F7-(B$52*'Govern overlay'!F66+'Govern overlay'!F75*B$48*B$49))/('Summary P&L'!F6+(B$52*'Govern overlay'!F65+'Govern overlay'!F76*B$48*B$50*B$51)) -> 0.85999629 | C57: =('Summary P&L'!F6+(C$52*'Govern overlay'!F65+'Govern overlay'!F76*C$48*C$50*C$51)-'Summary P&L'!F7-(C$52*'Govern overlay'!F66+'Govern overlay'!F75*C$48*C$49))/('Summary P&L'!F6+(C$52*'Govern overlay'!F65+'Govern overlay'!F76*C$48*C$50*C$51)) -> 0.85992135 | D57: =('Summary P&L'!F6+(D$52*'Govern overlay'!F65+'Govern overlay'!F76*D$48*D$50*D$51)-'Summary P&L'!F7-(D$52*'Govern overlay'!F66+'Govern overlay'!F75*D$48*D$49))/('Summary P&L'!F6+(D$52*'Govern overlay'!F65+'Govern overlay'!F76*D$48*D$50*D$51)) -> 0.80374534 | E57: =('Summary P&L'!F6+(E$52*'Govern overlay'!F65+'Govern overlay'!F76*E$48*E$50*E$51)-'Summary P&L'!F7-(E$52*'Govern overlay'!F66+'Govern overlay'!F75*E$48*E$49))/('Summary P&L'!F6+(E$52*'Govern overlay'!F65+'Govern overlay'!F76*E$48*E$50*E$51)) -> 0.80374534 | F57: =('Summary P&L'!F6+(F$52*'Govern overlay'!F65+'Govern overlay'!F76*F$48*F$50*F$51)-'Summary P&L'!F7-(F$52*'Govern overlay'!F66+'Govern overlay'!F75*F$48*F$49))/('Summary P&L'!F6+(F$52*'Govern overlay'!F65+'Govern overlay'!F76*F$48*F$50*F$51)) -> 0.74749439 | G57: =('Summary P&L'!F6+(G$52*'Govern overlay'!F65+'Govern overlay'!F76*G$48*G$50*G$51)-'Summary P&L'!F7-(G$52*'Govern overlay'!F66+'Govern overlay'!F75*G$48*G$49))/('Summary P&L'!F6+(G$52*'Govern overlay'!F65+'Govern overlay'!F76*G$48*G$50*G$51)) -> 0.82093843
A58: FY2030-31 EBITDA | B58: ='Summary P&L'!F11+(B$52*'Govern overlay'!F65+'Govern overlay'!F76*B$48*B$50*B$51)-(B$52*'Govern overlay'!F66+'Govern overlay'!F75*B$48*B$49) -> 22.575951 | C58: ='Summary P&L'!F11+(C$52*'Govern overlay'!F65+'Govern overlay'!F76*C$48*C$50*C$51)-(C$52*'Govern overlay'!F66+'Govern overlay'!F75*C$48*C$49) -> 23.22422 | D58: ='Summary P&L'!F11+(D$52*'Govern overlay'!F65+'Govern overlay'!F76*D$48*D$50*D$51)-(D$52*'Govern overlay'!F66+'Govern overlay'!F75*D$48*D$49) -> 9.6203694 | E58: ='Summary P&L'!F11+(E$52*'Govern overlay'!F65+'Govern overlay'!F76*E$48*E$50*E$51)-(E$52*'Govern overlay'!F66+'Govern overlay'!F75*E$48*E$49) -> 9.6203694 | F58: ='Summary P&L'!F11+(F$52*'Govern overlay'!F65+'Govern overlay'!F76*F$48*F$50*F$51)-(F$52*'Govern overlay'!F66+'Govern overlay'!F75*F$48*F$49) -> -3.3352122 | G58: ='Summary P&L'!F11+(G$52*'Govern overlay'!F65+'Govern overlay'!F76*G$48*G$50*G$51)-(G$52*'Govern overlay'!F66+'Govern overlay'!F75*G$48*G$49) -> 31.734949
A59: Closing cash, March 2031 | B59: ='Summary P&L'!F18+B$52*'Govern overlay'!F68+SUM('Govern overlay'!B76:F76)*B$48*B$50*B$51-SUM('Govern overlay'!B75:F75)*B$48*B$49 -> 30.409496 | C59: ='Summary P&L'!F18+C$52*'Govern overlay'!F68+SUM('Govern overlay'!B76:F76)*C$48*C$50*C$51-SUM('Govern overlay'!B75:F75)*C$48*C$49 -> 31.243283 | D59: ='Summary P&L'!F18+D$52*'Govern overlay'!F68+SUM('Govern overlay'!B76:F76)*D$48*D$50*D$51-SUM('Govern overlay'!B75:F75)*D$48*D$49 -> 10.85462 | E59: ='Summary P&L'!F18+E$52*'Govern overlay'!F68+SUM('Govern overlay'!B76:F76)*E$48*E$50*E$51-SUM('Govern overlay'!B75:F75)*E$48*E$49 -> 10.85462 | F59: ='Summary P&L'!F18+F$52*'Govern overlay'!F68+SUM('Govern overlay'!B76:F76)*F$48*F$50*F$51-SUM('Govern overlay'!B75:F75)*F$48*F$49 -> -8.7002571 | G59: ='Summary P&L'!F18+G$52*'Govern overlay'!F68+SUM('Govern overlay'!B76:F76)*G$48*G$50*G$51-SUM('Govern overlay'!B75:F75)*G$48*G$49 -> 42.04085
A60: Closing cash, 30 September 2028, approx. (Gate A floor Rs 14.13 cr MODELLED) | B60: ='Cash and funding'!G29+B$52*'Govern overlay'!M29+('Govern overlay'!B76+'Govern overlay'!C76+0.5*'Govern overlay'!D76)*B$48*B$50*B$51-('Govern overlay'!B75+'Govern overlay'!C75+0.5*'Govern overlay'!D75)*B$48*B$49 -> 14.132096 | C60: ='Cash and funding'!G29+C$52*'Govern overlay'!M29+('Govern overlay'!B76+'Govern overlay'!C76+0.5*'Govern overlay'!D76)*C$48*C$50*C$51-('Govern overlay'!B75+'Govern overlay'!C75+0.5*'Govern overlay'!D75)*C$48*C$49 -> 14.15011 | D60: ='Cash and funding'!G29+D$52*'Govern overlay'!M29+('Govern overlay'!B76+'Govern overlay'!C76+0.5*'Govern overlay'!D76)*D$48*D$50*D$51-('Govern overlay'!B75+'Govern overlay'!C75+0.5*'Govern overlay'!D75)*D$48*D$49 -> 13.244334 | E60: ='Cash and funding'!G29+E$52*'Govern overlay'!M29+('Govern overlay'!B76+'Govern overlay'!C76+0.5*'Govern overlay'!D76)*E$48*E$50*E$51-('Govern overlay'!B75+'Govern overlay'!C75+0.5*'Govern overlay'!D75)*E$48*E$49 -> 13.244334 | F60: ='Cash and funding'!G29+F$52*'Govern overlay'!M29+('Govern overlay'!B76+'Govern overlay'!C76+0.5*'Govern overlay'!D76)*F$48*F$50*F$51-('Govern overlay'!B75+'Govern overlay'!C75+0.5*'Govern overlay'!D75)*F$48*F$49 -> 12.356572 | G60: ='Cash and funding'!G29+G$52*'Govern overlay'!M29+('Govern overlay'!B76+'Govern overlay'!C76+0.5*'Govern overlay'!D76)*G$48*G$50*G$51-('Govern overlay'!B75+'Govern overlay'!C75+0.5*'Govern overlay'!D75)*G$48*G$49 -> 14.116144
A61: The 2× volume at 0.5× cost and 1× volume at 1× cost cases give identical results because cost is linear in ratio × cost factor. The Sep 2028 figure adds half of the FY2028-29 read amounts to the engine's closing cash (Cash and funding G29); the governance-layer column uses the monthly overlay (Govern overlay M29).
A62: Live switches: Assumptions B120 (governance layer), B130 (reads metered), B134 (reads runtime cost) — all OFF in the base case. The founder has not decided read pricing. The code audit (commit 22388ad) confirms a signed receipt for every governed call, reads included; the per-read cost is still unmeasured.

Sheet Govern overlay
A1: Govern overlay — Elan1 Govern increments behind three switches
A2: Monthly governance-layer line (54 months, with channel contra and 55-day DSO), and reads at financial-year grain. Every amount is computed as if switched on; only the 'switched' rows at the foot apply the switches on Assumptions B120, B130 and B134.
A3: Rs crore unless stated. All drivers are MODELLED except the engine's own tenant ramp, channel share, cost per governed action and volumes, which are read from Assumptions and Unit economics.
A4: GOVERNANCE LAYER BY MONTH — as if switched on
A5: Month | B5: Financial year | C5: Paying tenants | D5: Attach | E5: Price index | F5: Gross line revenue | G5: Channel contra | H5: Net revenue | I5: Cost of revenue | J5: EBITDA delta | K5: Receivables | L5: WC movement | M5: Cash delta, cumulative
A6: =Assumptions!A29 -> Oct 2026 | B6: FY2026-27 | C6: =Assumptions!B29 -> 0 | D6: =Assumptions!$B$122 -> 0 | E6: =1 -> 1 | F6: =C6*D6*Assumptions!$B$121*E6/12/10^7 -> 0 | G6: =-F6*Assumptions!$B$128*Assumptions!J29 -> 0 | H6: =F6+G6 -> 0 | I6: =F6*Assumptions!$B$127 -> 0 | J6: =H6-I6 -> 0 | K6: =H6*Assumptions!$B$104/30.4 -> 0 | L6: =-K6 -> 0 | M6: =J6+L6 -> 0
A7: =Assumptions!A30 -> Nov 2026 | B7: FY2026-27 | C7: =Assumptions!B30 -> 0 | D7: =Assumptions!$B$122 -> 0 | E7: =1 -> 1 | F7: =C7*D7*Assumptions!$B$121*E7/12/10^7 -> 0 | G7: =-F7*Assumptions!$B$128*Assumptions!J30 -> 0 | H7: =F7+G7 -> 0 | I7: =F7*Assumptions!$B$127 -> 0 | J7: =H7-I7 -> 0 | K7: =H7*Assumptions!$B$104/30.4 -> 0 | L7: =-(K7-K6) -> 0 | M7: =M6+J7+L7 -> 0
A8: =Assumptions!A31 -> Dec 2026 | B8: FY2026-27 | C8: =Assumptions!B31 -> 0 | D8: =Assumptions!$B$122 -> 0 | E8: =1 -> 1 | F8: =C8*D8*Assumptions!$B$121*E8/12/10^7 -> 0 | G8: =-F8*Assumptions!$B$128*Assumptions!J31 -> 0 | H8: =F8+G8 -> 0 | I8: =F8*Assumptions!$B$127 -> 0 | J8: =H8-I8 -> 0 | K8: =H8*Assumptions!$B$104/30.4 -> 0 | L8: =-(K8-K7) -> 0 | M8: =M7+J8+L8 -> 0
A9: =Assumptions!A32 -> Jan 2027 | B9: FY2026-27 | C9: =Assumptions!B32 -> 0 | D9: =Assumptions!$B$122 -> 0 | E9: =1 -> 1 | F9: =C9*D9*Assumptions!$B$121*E9/12/10^7 -> 0 | G9: =-F9*Assumptions!$B$128*Assumptions!J32 -> 0 | H9: =F9+G9 -> 0 | I9: =F9*Assumptions!$B$127 -> 0 | J9: =H9-I9 -> 0 | K9: =H9*Assumptions!$B$104/30.4 -> 0 | L9: =-(K9-K8) -> 0 | M9: =M8+J9+L9 -> 0
A10: =Assumptions!A33 -> Feb 2027 | B10: FY2026-27 | C10: =Assumptions!B33 -> 0 | D10: =Assumptions!$B$122 -> 0 | E10: =1 -> 1 | F10: =C10*D10*Assumptions!$B$121*E10/12/10^7 -> 0 | G10: =-F10*Assumptions!$B$128*Assumptions!J33 -> 0 | H10: =F10+G10 -> 0 | I10: =F10*Assumptions!$B$127 -> 0 | J10: =H10-I10 -> 0 | K10: =H10*Assumptions!$B$104/30.4 -> 0 | L10: =-(K10-K9) -> 0 | M10: =M9+J10+L10 -> 0
A11: =Assumptions!A34 -> Mar 2027 | B11: FY2026-27 | C11: =Assumptions!B34 -> 0 | D11: =Assumptions!$B$122 -> 0 | E11: =1 -> 1 | F11: =C11*D11*Assumptions!$B$121*E11/12/10^7 -> 0 | G11: =-F11*Assumptions!$B$128*Assumptions!J34 -> 0 | H11: =F11+G11 -> 0 | I11: =F11*Assumptions!$B$127 -> 0 | J11: =H11-I11 -> 0 | K11: =H11*Assumptions!$B$104/30.4 -> 0 | L11: =-(K11-K10) -> 0 | M11: =M10+J11+L11 -> 0
A12: =Assumptions!A35 -> Apr 2027 | B12: FY2027-28 | C12: =Assumptions!B35 -> 0 | D12: =Assumptions!$B$123 -> 0.05 | E12: =1 -> 1 | F12: =C12*D12*Assumptions!$B$121*E12/12/10^7 -> 0 | G12: =-F12*Assumptions!$B$128*Assumptions!J35 -> 0 | H12: =F12+G12 -> 0 | I12: =F12*Assumptions!$B$127 -> 0 | J12: =H12-I12 -> 0 | K12: =H12*Assumptions!$B$104/30.4 -> 0 | L12: =-(K12-K11) -> 0 | M12: =M11+J12+L12 -> 0
A13: =Assumptions!A36 -> May 2027 | B13: FY2027-28 | C13: =Assumptions!B36 -> 0 | D13: =Assumptions!$B$123 -> 0.05 | E13: =1 -> 1 | F13: =C13*D13*Assumptions!$B$121*E13/12/10^7 -> 0 | G13: =-F13*Assumptions!$B$128*Assumptions!J36 -> 0 | H13: =F13+G13 -> 0 | I13: =F13*Assumptions!$B$127 -> 0 | J13: =H13-I13 -> 0 | K13: =H13*Assumptions!$B$104/30.4 -> 0 | L13: =-(K13-K12) -> 0 | M13: =M12+J13+L13 -> 0
A14: =Assumptions!A37 -> Jun 2027 | B14: FY2027-28 | C14: =Assumptions!B37 -> 0 | D14: =Assumptions!$B$123 -> 0.05 | E14: =1 -> 1 | F14: =C14*D14*Assumptions!$B$121*E14/12/10^7 -> 0 | G14: =-F14*Assumptions!$B$128*Assumptions!J37 -> 0 | H14: =F14+G14 -> 0 | I14: =F14*Assumptions!$B$127 -> 0 | J14: =H14-I14 -> 0 | K14: =H14*Assumptions!$B$104/30.4 -> 0 | L14: =-(K14-K13) -> 0 | M14: =M13+J14+L14 -> 0
A15: =Assumptions!A38 -> Jul 2027 | B15: FY2027-28 | C15: =Assumptions!B38 -> 3 | D15: =Assumptions!$B$123 -> 0.05 | E15: =1 -> 1 | F15: =C15*D15*Assumptions!$B$121*E15/12/10^7 -> 0.0001125 | G15: =-F15*Assumptions!$B$128*Assumptions!J38 -> 0 | H15: =F15+G15 -> 0.0001125 | I15: =F15*Assumptions!$B$127 -> 1.6875e-05 | J15: =H15-I15 -> 9.5625e-05 | K15: =H15*Assumptions!$B$104/30.4 -> 0.00020353618 | L15: =-(K15-K14) -> -0.00020353618 | M15: =M14+J15+L15 -> -0.00010791118
A16: =Assumptions!A39 -> Aug 2027 | B16: FY2027-28 | C16: =Assumptions!B39 -> 6 | D16: =Assumptions!$B$123 -> 0.05 | E16: =1 -> 1 | F16: =C16*D16*Assumptions!$B$121*E16/12/10^7 -> 0.000225 | G16: =-F16*Assumptions!$B$128*Assumptions!J39 -> 0 | H16: =F16+G16 -> 0.000225 | I16: =F16*Assumptions!$B$127 -> 3.375e-05 | J16: =H16-I16 -> 0.00019125 | K16: =H16*Assumptions!$B$104/30.4 -> 0.00040707237 | L16: =-(K16-K15) -> -0.00020353618 | M16: =M15+J16+L16 -> -0.00012019737
A17: =Assumptions!A40 -> Sep 2027 | B17: FY2027-28 | C17: =Assumptions!B40 -> 9 | D17: =Assumptions!$B$123 -> 0.05 | E17: =1 -> 1 | F17: =C17*D17*Assumptions!$B$121*E17/12/10^7 -> 0.0003375 | G17: =-F17*Assumptions!$B$128*Assumptions!J40 -> 0 | H17: =F17+G17 -> 0.0003375 | I17: =F17*Assumptions!$B$127 -> 5.0625e-05 | J17: =H17-I17 -> 0.000286875 | K17: =H17*Assumptions!$B$104/30.4 -> 0.00061060855 | L17: =-(K17-K16) -> -0.00020353618 | M17: =M16+J17+L17 -> -3.6858553e-05
A18: =Assumptions!A41 -> Oct 2027 | B18: FY2027-28 | C18: =Assumptions!B41 -> 13 | D18: =Assumptions!$B$123 -> 0.05 | E18: =1 -> 1 | F18: =C18*D18*Assumptions!$B$121*E18/12/10^7 -> 0.0004875 | G18: =-F18*Assumptions!$B$128*Assumptions!J41 -> 0 | H18: =F18+G18 -> 0.0004875 | I18: =F18*Assumptions!$B$127 -> 7.3125e-05 | J18: =H18-I18 -> 0.000414375 | K18: =H18*Assumptions!$B$104/30.4 -> 0.00088199013 | L18: =-(K18-K17) -> -0.00027138158 | M18: =M17+J18+L18 -> 0.00010613487
A19: =Assumptions!A42 -> Nov 2027 | B19: FY2027-28 | C19: =Assumptions!B42 -> 17 | D19: =Assumptions!$B$123 -> 0.05 | E19: =1 -> 1 | F19: =C19*D19*Assumptions!$B$121*E19/12/10^7 -> 0.0006375 | G19: =-F19*Assumptions!$B$128*Assumptions!J42 -> 0 | H19: =F19+G19 -> 0.0006375 | I19: =F19*Assumptions!$B$127 -> 9.5625e-05 | J19: =H19-I19 -> 0.000541875 | K19: =H19*Assumptions!$B$104/30.4 -> 0.0011533717 | L19: =-(K19-K18) -> -0.00027138158 | M19: =M18+J19+L19 -> 0.00037662829
A20: =Assumptions!A43 -> Dec 2027 | B20: FY2027-28 | C20: =Assumptions!B43 -> 21 | D20: =Assumptions!$B$123 -> 0.05 | E20: =1 -> 1 | F20: =C20*D20*Assumptions!$B$121*E20/12/10^7 -> 0.0007875 | G20: =-F20*Assumptions!$B$128*Assumptions!J43 -> -2.835e-06 | H20: =F20+G20 -> 0.000784665 | I20: =F20*Assumptions!$B$127 -> 0.000118125 | J20: =H20-I20 -> 0.00066654 | K20: =H20*Assumptions!$B$104/30.4 -> 0.0014196242 | L20: =-(K20-K19) -> -0.00026625247 | M20: =M19+J20+L20 -> 0.00077691582
A21: =Assumptions!A44 -> Jan 2028 | B21: FY2027-28 | C21: =Assumptions!B44 -> 27 | D21: =Assumptions!$B$123 -> 0.05 | E21: =1 -> 1 | F21: =C21*D21*Assumptions!$B$121*E21/12/10^7 -> 0.0010125 | G21: =-F21*Assumptions!$B$128*Assumptions!J44 -> -7.29e-06 | H21: =F21+G21 -> 0.00100521 | I21: =F21*Assumptions!$B$127 -> 0.000151875 | J21: =H21-I21 -> 0.000853335 | K21: =H21*Assumptions!$B$104/30.4 -> 0.0018186365 | L21: =-(K21-K20) -> -0.00039901234 | M21: =M20+J21+L21 -> 0.0012312385
A22: =Assumptions!A45 -> Feb 2028 | B22: FY2027-28 | C22: =Assumptions!B45 -> 33 | D22: =Assumptions!$B$123 -> 0.05 | E22: =1 -> 1 | F22: =C22*D22*Assumptions!$B$121*E22/12/10^7 -> 0.0012375 | G22: =-F22*Assumptions!$B$128*Assumptions!J45 -> -1.3365e-05 | H22: =F22+G22 -> 0.001224135 | I22: =F22*Assumptions!$B$127 -> 0.000185625 | J22: =H22-I22 -> 0.00103851 | K22: =H22*Assumptions!$B$104/30.4 -> 0.0022147179 | L22: =-(K22-K21) -> -0.00039608141 | M22: =M21+J22+L22 -> 0.0018736671
A23: =Assumptions!A46 -> Mar 2028 | B23: FY2027-28 | C23: =Assumptions!B46 -> 39 | D23: =Assumptions!$B$123 -> 0.05 | E23: =1 -> 1 | F23: =C23*D23*Assumptions!$B$121*E23/12/10^7 -> 0.0014625 | G23: =-F23*Assumptions!$B$128*Assumptions!J46 -> -2.106e-05 | H23: =F23+G23 -> 0.00144144 | I23: =F23*Assumptions!$B$127 -> 0.000219375 | J23: =H23-I23 -> 0.001222065 | K23: =H23*Assumptions!$B$104/30.4 -> 0.0026078684 | L23: =-(K23-K22) -> -0.00039315049 | M23: =M22+J23+L23 -> 0.0027025816
A24: =Assumptions!A47 -> Apr 2028 | B24: FY2028-29 | C24: =Assumptions!B47 -> 46 | D24: =Assumptions!$B$124 -> 0.1 | E24: =1 -> 1 | F24: =C24*D24*Assumptions!$B$121*E24/12/10^7 -> 0.00345 | G24: =-F24*Assumptions!$B$128*Assumptions!J47 -> -6.0237e-05 | H24: =F24+G24 -> 0.003389763 | I24: =F24*Assumptions!$B$127 -> 0.0005175 | J24: =H24-I24 -> 0.002872263 | K24: =H24*Assumptions!$B$104/30.4 -> 0.0061327949 | L24: =-(K24-K23) -> -0.0035249265 | M24: =M23+J24+L24 -> 0.0020499181
A25: =Assumptions!A48 -> May 2028 | B25: FY2028-29 | C25: =Assumptions!B48 -> 52 | D25: =Assumptions!$B$124 -> 0.1 | E25: =1 -> 1 | F25: =C25*D25*Assumptions!$B$121*E25/12/10^7 -> 0.0039 | G25: =-F25*Assumptions!$B$128*Assumptions!J48 -> -7.9326e-05 | H25: =F25+G25 -> 0.003820674 | I25: =F25*Assumptions!$B$127 -> 0.000585 | J25: =H25-I25 -> 0.003235674 | K25: =H25*Assumptions!$B$104/30.4 -> 0.0069124036 | L25: =-(K25-K24) -> -0.00077960872 | M25: =M24+J25+L25 -> 0.0045059834
A26: =Assumptions!A49 -> Jun 2028 | B26: FY2028-29 | C26: =Assumptions!B49 -> 59 | D26: =Assumptions!$B$124 -> 0.1 | E26: =1 -> 1 | F26: =C26*D26*Assumptions!$B$121*E26/12/10^7 -> 0.004425 | G26: =-F26*Assumptions!$B$128*Assumptions!J49 -> -0.000103545 | H26: =F26+G26 -> 0.004321455 | I26: =F26*Assumptions!$B$127 -> 0.00066375 | J26: =H26-I26 -> 0.003657705 | K26: =H26*Assumptions!$B$104/30.4 -> 0.0078184219 | L26: =-(K26-K25) -> -0.00090601826 | M26: =M25+J26+L26 -> 0.0072576701
A27: =Assumptions!A50 -> Jul 2028 | B27: FY2028-29 | C27: =Assumptions!B50 -> 67 | D27: =Assumptions!$B$124 -> 0.1 | E27: =1 -> 1 | F27: =C27*D27*Assumptions!$B$121*E27/12/10^7 -> 0.005025 | G27: =-F27*Assumptions!$B$128*Assumptions!J50 -> -0.0001329615 | H27: =F27+G27 -> 0.0048920385 | I27: =F27*Assumptions!$B$127 -> 0.00075375 | J27: =H27-I27 -> 0.0041382885 | K27: =H27*Assumptions!$B$104/30.4 -> 0.0088507275 | L27: =-(K27-K26) -> -0.0010323057 | M27: =M26+J27+L27 -> 0.010363653
A28: =Assumptions!A51 -> Aug 2028 | B28: FY2028-29 | C28: =Assumptions!B51 -> 76 | D28: =Assumptions!$B$124 -> 0.1 | E28: =1 -> 1 | F28: =C28*D28*Assumptions!$B$121*E28/12/10^7 -> 0.0057 | G28: =-F28*Assumptions!$B$128*Assumptions!J51 -> -0.000167238 | H28: =F28+G28 -> 0.005532762 | I28: =F28*Assumptions!$B$127 -> 0.000855 | J28: =H28-I28 -> 0.004677762 | K28: =H28*Assumptions!$B$104/30.4 -> 0.010009931 | L28: =-(K28-K27) -> -0.0011592037 | M28: =M27+J28+L28 -> 0.013882211
A29: =Assumptions!A52 -> Sep 2028 | B29: FY2028-29 | C29: =Assumptions!B52 -> 84 | D29: =Assumptions!$B$124 -> 0.1 | E29: =1 -> 1 | F29: =C29*D29*Assumptions!$B$121*E29/12/10^7 -> 0.0063 | G29: =-F29*Assumptions!$B$128*Assumptions!J52 -> -0.00020412 | H29: =F29+G29 -> 0.00609588 | I29: =F29*Assumptions!$B$127 -> 0.000945 | J29: =H29-I29 -> 0.00515088 | K29: =H29*Assumptions!$B$104/30.4 -> 0.01102873 | L29: =-(K29-K28) -> -0.001018799 | M29: =M28+J29+L29 -> 0.018014292
A30: =Assumptions!A53 -> Oct 2028 | B30: FY2028-29 | C30: =Assumptions!B53 -> 94 | D30: =Assumptions!$B$124 -> 0.1 | E30: =1 -> 1 | F30: =C30*D30*Assumptions!$B$121*E30/12/10^7 -> 0.00705 | G30: =-F30*Assumptions!$B$128*Assumptions!J53 -> -0.000244917 | H30: =F30+G30 -> 0.006805083 | I30: =F30*Assumptions!$B$127 -> 0.0010575 | J30: =H30-I30 -> 0.005747583 | K30: =H30*Assumptions!$B$104/30.4 -> 0.012311828 | L30: =-(K30-K29) -> -0.0012830975 | M30: =M29+J30+L30 -> 0.022478778
A31: =Assumptions!A54 -> Nov 2028 | B31: FY2028-29 | C31: =Assumptions!B54 -> 104 | D31: =Assumptions!$B$124 -> 0.1 | E31: =1 -> 1 | F31: =C31*D31*Assumptions!$B$121*E31/12/10^7 -> 0.0078 | G31: =-F31*Assumptions!$B$128*Assumptions!J54 -> -0.000290628 | H31: =F31+G31 -> 0.007509372 | I31: =F31*Assumptions!$B$127 -> 0.00117 | J31: =H31-I31 -> 0.006339372 | K31: =H31*Assumptions!$B$104/30.4 -> 0.013586035 | L31: =-(K31-K30) -> -0.0012742071 | M31: =M30+J31+L31 -> 0.027543943
A32: =Assumptions!A55 -> Dec 2028 | B32: FY2028-29 | C32: =Assumptions!B55 -> 114 | D32: =Assumptions!$B$124 -> 0.1 | E32: =1 -> 1 | F32: =C32*D32*Assumptions!$B$121*E32/12/10^7 -> 0.00855 | G32: =-F32*Assumptions!$B$128*Assumptions!J55 -> -0.00033858 | H32: =F32+G32 -> 0.00821142 | I32: =F32*Assumptions!$B$127 -> 0.0012825 | J32: =H32-I32 -> 0.00692892 | K32: =H32*Assumptions!$B$104/30.4 -> 0.014856187 | L32: =-(K32-K31) -> -0.0012701526 | M32: =M31+J32+L32 -> 0.03320271
A33: =Assumptions!A56 -> Jan 2029 | B33: FY2028-29 | C33: =Assumptions!B56 -> 125 | D33: =Assumptions!$B$124 -> 0.1 | E33: =1 -> 1 | F33: =C33*D33*Assumptions!$B$121*E33/12/10^7 -> 0.009375 | G33: =-F33*Assumptions!$B$128*Assumptions!J56 -> -0.0003931875 | H33: =F33+G33 -> 0.0089818125 | I33: =F33*Assumptions!$B$127 -> 0.00140625 | J33: =H33-I33 -> 0.0075755625 | K33: =H33*Assumptions!$B$104/30.4 -> 0.01624999 | L33: =-(K33-K32) -> -0.0013938022 | M33: =M32+J33+L33 -> 0.03938447
A34: =Assumptions!A57 -> Feb 2029 | B34: FY2028-29 | C34: =Assumptions!B57 -> 137 | D34: =Assumptions!$B$124 -> 0.1 | E34: =1 -> 1 | F34: =C34*D34*Assumptions!$B$121*E34/12/10^7 -> 0.010275 | G34: =-F34*Assumptions!$B$128*Assumptions!J57 -> -0.0004568265 | H34: =F34+G34 -> 0.0098181735 | I34: =F34*Assumptions!$B$127 -> 0.00154125 | J34: =H34-I34 -> 0.0082769235 | K34: =H34*Assumptions!$B$104/30.4 -> 0.017763143 | L34: =-(K34-K33) -> -0.0015131531 | M34: =M33+J34+L34 -> 0.046148241
A35: =Assumptions!A58 -> Mar 2029 | B35: FY2028-29 | C35: =Assumptions!B58 -> 148 | D35: =Assumptions!$B$124 -> 0.1 | E35: =1 -> 1 | F35: =C35*D35*Assumptions!$B$121*E35/12/10^7 -> 0.0111 | G35: =-F35*Assumptions!$B$128*Assumptions!J58 -> -0.00051948 | H35: =F35+G35 -> 0.01058052 | I35: =F35*Assumptions!$B$127 -> 0.001665 | J35: =H35-I35 -> 0.00891552 | K35: =H35*Assumptions!$B$104/30.4 -> 0.019142388 | L35: =-(K35-K34) -> -0.0013792453 | M35: =M34+J35+L35 -> 0.053684515
A36: =Assumptions!A59 -> Apr 2029 | B36: FY2029-30 | C36: =Assumptions!B59 -> 161 | D36: =Assumptions!$B$125 -> 0.15 | E36: =(1+Assumptions!$B$129) -> 1.04 | F36: =C36*D36*Assumptions!$B$121*E36/12/10^7 -> 0.018837 | G36: =-F36*Assumptions!$B$128*Assumptions!J59 -> -0.00092225952 | H36: =F36+G36 -> 0.01791474 | I36: =F36*Assumptions!$B$127 -> 0.00282555 | J36: =H36-I36 -> 0.01508919 | K36: =H36*Assumptions!$B$104/30.4 -> 0.032411537 | L36: =-(K36-K35) -> -0.013269149 | M36: =M35+J36+L36 -> 0.055504557
A37: =Assumptions!A60 -> May 2029 | B37: FY2029-30 | C37: =Assumptions!B60 -> 173 | D37: =Assumptions!$B$125 -> 0.15 | E37: =(1+Assumptions!$B$129) -> 1.04 | F37: =C37*D37*Assumptions!$B$121*E37/12/10^7 -> 0.020241 | G37: =-F37*Assumptions!$B$128*Assumptions!J60 -> -0.0010310765 | H37: =F37+G37 -> 0.019209923 | I37: =F37*Assumptions!$B$127 -> 0.00303615 | J37: =H37-I37 -> 0.016173773 | K37: =H37*Assumptions!$B$104/30.4 -> 0.034754796 | L37: =-(K37-K36) -> -0.0023432587 | M37: =M36+J37+L37 -> 0.069335072
A38: =Assumptions!A61 -> Jun 2029 | B38: FY2029-30 | C38: =Assumptions!B61 -> 186 | D38: =Assumptions!$B$125 -> 0.15 | E38: =(1+Assumptions!$B$129) -> 1.04 | F38: =C38*D38*Assumptions!$B$121*E38/12/10^7 -> 0.021762 | G38: =-F38*Assumptions!$B$128*Assumptions!J61 -> -0.0011555622 | H38: =F38+G38 -> 0.020606438 | I38: =F38*Assumptions!$B$127 -> 0.0032643 | J38: =H38-I38 -> 0.017342138 | K38: =H38*Assumptions!$B$104/30.4 -> 0.037281384 | L38: =-(K38-K37) -> -0.0025265884 | M38: =M37+J38+L38 -> 0.084150621
A39: =Assumptions!A62 -> Jul 2029 | B39: FY2029-30 | C39: =Assumptions!B62 -> 199 | D39: =Assumptions!$B$125 -> 0.15 | E39: =(1+Assumptions!$B$129) -> 1.04 | F39: =C39*D39*Assumptions!$B$121*E39/12/10^7 -> 0.023283 | G39: =-F39*Assumptions!$B$128*Assumptions!J62 -> -0.0012866186 | H39: =F39+G39 -> 0.021996381 | I39: =F39*Assumptions!$B$127 -> 0.00349245 | J39: =H39-I39 -> 0.018503931 | K39: =H39*Assumptions!$B$104/30.4 -> 0.039796085 | L39: =-(K39-K38) -> -0.0025147006 | M39: =M38+J39+L39 -> 0.10013985
A40: =Assumptions!A63 -> Aug 2029 | B40: FY2029-30 | C40: =Assumptions!B63 -> 213 | D40: =Assumptions!$B$125 -> 0.15 | E40: =(1+Assumptions!$B$129) -> 1.04 | F40: =C40*D40*Assumptions!$B$121*E40/12/10^7 -> 0.024921 | G40: =-F40*Assumptions!$B$128*Assumptions!J63 -> -0.001426478 | H40: =F40+G40 -> 0.023494522 | I40: =F40*Assumptions!$B$127 -> 0.00373815 | J40: =H40-I40 -> 0.019756372 | K40: =H40*Assumptions!$B$104/30.4 -> 0.042506536 | L40: =-(K40-K39) -> -0.0027104516 | M40: =M39+J40+L40 -> 0.11718577
A41: =Assumptions!A64 -> Sep 2029 | B41: FY2029-30 | C41: =Assumptions!B64 -> 226 | D41: =Assumptions!$B$125 -> 0.15 | E41: =(1+Assumptions!$B$129) -> 1.04 | F41: =C41*D41*Assumptions!$B$121*E41/12/10^7 -> 0.026442 | G41: =-F41*Assumptions!$B$128*Assumptions!J64 -> -0.0015706548 | H41: =F41+G41 -> 0.024871345 | I41: =F41*Assumptions!$B$127 -> 0.0039663 | J41: =H41-I41 -> 0.020905045 | K41: =H41*Assumptions!$B$104/30.4 -> 0.0449975 | L41: =-(K41-K40) -> -0.0024909631 | M41: =M40+J41+L41 -> 0.13559985
A42: =Assumptions!A65 -> Oct 2029 | B42: FY2029-30 | C42: =Assumptions!B65 -> 240 | D42: =Assumptions!$B$125 -> 0.15 | E42: =(1+Assumptions!$B$129) -> 1.04 | F42: =C42*D42*Assumptions!$B$121*E42/12/10^7 -> 0.02808 | G42: =-F42*Assumptions!$B$128*Assumptions!J65 -> -0.0017083872 | H42: =F42+G42 -> 0.026371613 | I42: =F42*Assumptions!$B$127 -> 0.004212 | J42: =H42-I42 -> 0.022159613 | K42: =H42*Assumptions!$B$104/30.4 -> 0.047711799 | L42: =-(K42-K41) -> -0.0027142999 | M42: =M41+J42+L42 -> 0.15504517
A43: =Assumptions!A66 -> Nov 2029 | B43: FY2029-30 | C43: =Assumptions!B66 -> 254 | D43: =Assumptions!$B$125 -> 0.15 | E43: =(1+Assumptions!$B$129) -> 1.04 | F43: =C43*D43*Assumptions!$B$121*E43/12/10^7 -> 0.029718 | G43: =-F43*Assumptions!$B$128*Assumptions!J66 -> -0.0018561863 | H43: =F43+G43 -> 0.027861814 | I43: =F43*Assumptions!$B$127 -> 0.0044577 | J43: =H43-I43 -> 0.023404114 | K43: =H43*Assumptions!$B$104/30.4 -> 0.050407887 | L43: =-(K43-K42) -> -0.0026960872 | M43: =M42+J43+L43 -> 0.17575319
A44: =Assumptions!A67 -> Dec 2029 | B44: FY2029-30 | C44: =Assumptions!B67 -> 268 | D44: =Assumptions!$B$125 -> 0.15 | E44: =(1+Assumptions!$B$129) -> 1.04 | F44: =C44*D44*Assumptions!$B$121*E44/12/10^7 -> 0.031356 | G44: =-F44*Assumptions!$B$128*Assumptions!J67 -> -0.0020036484 | H44: =F44+G44 -> 0.029352352 | I44: =F44*Assumptions!$B$127 -> 0.0047034 | J44: =H44-I44 -> 0.024648952 | K44: =H44*Assumptions!$B$104/30.4 -> 0.053104583 | L44: =-(K44-K43) -> -0.0026966968 | M44: =M43+J44+L44 -> 0.19770545
A45: =Assumptions!A68 -> Jan 2030 | B45: FY2029-30 | C45: =Assumptions!B68 -> 283 | D45: =Assumptions!$B$125 -> 0.15 | E45: =(1+Assumptions!$B$129) -> 1.04 | F45: =C45*D45*Assumptions!$B$121*E45/12/10^7 -> 0.033111 | G45: =-F45*Assumptions!$B$128*Assumptions!J68 -> -0.0021634727 | H45: =F45+G45 -> 0.030947527 | I45: =F45*Assumptions!$B$127 -> 0.00496665 | J45: =H45-I45 -> 0.025980877 | K45: =H45*Assumptions!$B$104/30.4 -> 0.055990592 | L45: =-(K45-K44) -> -0.0028860086 | M45: =M44+J45+L45 -> 0.22080032
A46: =Assumptions!A69 -> Feb 2030 | B46: FY2029-30 | C46: =Assumptions!B69 -> 297 | D46: =Assumptions!$B$125 -> 0.15 | E46: =(1+Assumptions!$B$129) -> 1.04 | F46: =C46*D46*Assumptions!$B$121*E46/12/10^7 -> 0.034749 | G46: =-F46*Assumptions!$B$128*Assumptions!J69 -> -0.002326793 | H46: =F46+G46 -> 0.032422207 | I46: =F46*Assumptions!$B$127 -> 0.00521235 | J46: =H46-I46 -> 0.027209857 | K46: =H46*Assumptions!$B$104/30.4 -> 0.058658598 | L46: =-(K46-K45) -> -0.002668006 | M46: =M45+J46+L46 -> 0.24534217
A47: =Assumptions!A70 -> Mar 2030 | B47: FY2029-30 | C47: =Assumptions!B70 -> 312 | D47: =Assumptions!$B$125 -> 0.15 | E47: =(1+Assumptions!$B$129) -> 1.04 | F47: =C47*D47*Assumptions!$B$121*E47/12/10^7 -> 0.036504 | G47: =-F47*Assumptions!$B$128*Assumptions!J70 -> -0.0024968736 | H47: =F47+G47 -> 0.034007126 | I47: =F47*Assumptions!$B$127 -> 0.0054756 | J47: =H47-I47 -> 0.028531526 | K47: =H47*Assumptions!$B$104/30.4 -> 0.061526051 | L47: =-(K47-K46) -> -0.0028674529 | M47: =M46+J47+L47 -> 0.27100624
A48: =Assumptions!A71 -> Apr 2030 | B48: FY2030-31 | C48: =Assumptions!B71 -> 329 | D48: =Assumptions!$B$126 -> 0.2 | E48: =(1+Assumptions!$B$129)^2 -> 1.0816 | F48: =C48*D48*Assumptions!$B$121*E48/12/10^7 -> 0.05337696 | G48: =-F48*Assumptions!$B$128*Assumptions!J71 -> -0.003718239 | H48: =F48+G48 -> 0.049658721 | I48: =F48*Assumptions!$B$127 -> 0.008006544 | J48: =H48-I48 -> 0.041652177 | K48: =H48*Assumptions!$B$104/30.4 -> 0.089843081 | L48: =-(K48-K47) -> -0.02831703 | M48: =M47+J48+L48 -> 0.28434139
A49: =Assumptions!A72 -> May 2030 | B49: FY2030-31 | C49: =Assumptions!B72 -> 345 | D49: =Assumptions!$B$126 -> 0.2 | E49: =(1+Assumptions!$B$129)^2 -> 1.0816 | F49: =C49*D49*Assumptions!$B$121*E49/12/10^7 -> 0.0559728 | G49: =-F49*Assumptions!$B$128*Assumptions!J72 -> -0.0039595159 | H49: =F49+G49 -> 0.052013284 | I49: =F49*Assumptions!$B$127 -> 0.00839592 | J49: =H49-I49 -> 0.043617364 | K49: =H49*Assumptions!$B$104/30.4 -> 0.094102981 | L49: =-(K49-K48) -> -0.0042599005 | M49: =M48+J49+L49 -> 0.32369885
A50: =Assumptions!A73 -> Jun 2030 | B50: FY2030-31 | C50: =Assumptions!B73 -> 362 | D50: =Assumptions!$B$126 -> 0.2 | E50: =(1+Assumptions!$B$129)^2 -> 1.0816 | F50: =C50*D50*Assumptions!$B$121*E50/12/10^7 -> 0.05873088 | G50: =-F50*Assumptions!$B$128*Assumptions!J73 -> -0.0042286234 | H50: =F50+G50 -> 0.054502257 | I50: =F50*Assumptions!$B$127 -> 0.008809632 | J50: =H50-I50 -> 0.045692625 | K50: =H50*Assumptions!$B$104/30.4 -> 0.098606056 | L50: =-(K50-K49) -> -0.0045030753 | M50: =M49+J50+L50 -> 0.3648884
A51: =Assumptions!A74 -> Jul 2030 | B51: FY2030-31 | C51: =Assumptions!B74 -> 380 | D51: =Assumptions!$B$126 -> 0.2 | E51: =(1+Assumptions!$B$129)^2 -> 1.0816 | F51: =C51*D51*Assumptions!$B$121*E51/12/10^7 -> 0.0616512 | G51: =-F51*Assumptions!$B$128*Assumptions!J74 -> -0.0045165669 | H51: =F51+G51 -> 0.057134633 | I51: =F51*Assumptions!$B$127 -> 0.00924768 | J51: =H51-I51 -> 0.047886953 | K51: =H51*Assumptions!$B$104/30.4 -> 0.10336858 | L51: =-(K51-K50) -> -0.0047625232 | M51: =M50+J51+L51 -> 0.40801283
A52: =Assumptions!A75 -> Aug 2030 | B52: FY2030-31 | C52: =Assumptions!B75 -> 398 | D52: =Assumptions!$B$126 -> 0.2 | E52: =(1+Assumptions!$B$129)^2 -> 1.0816 | F52: =C52*D52*Assumptions!$B$121*E52/12/10^7 -> 0.06457152 | G52: =-F52*Assumptions!$B$128*Assumptions!J75 -> -0.0048002468 | H52: =F52+G52 -> 0.059771273 | I52: =F52*Assumptions!$B$127 -> 0.009685728 | J52: =H52-I52 -> 0.050085545 | K52: =H52*Assumptions!$B$104/30.4 -> 0.10813882 | L52: =-(K52-K51) -> -0.0047702371 | M52: =M51+J52+L52 -> 0.45332814
A53: =Assumptions!A76 -> Sep 2030 | B53: FY2030-31 | C53: =Assumptions!B76 -> 416 | D53: =Assumptions!$B$126 -> 0.2 | E53: =(1+Assumptions!$B$129)^2 -> 1.0816 | F53: =C53*D53*Assumptions!$B$121*E53/12/10^7 -> 0.06749184 | G53: =-F53*Assumptions!$B$128*Assumptions!J76 -> -0.0051023831 | H53: =F53+G53 -> 0.062389457 | I53: =F53*Assumptions!$B$127 -> 0.010123776 | J53: =H53-I53 -> 0.052265681 | K53: =H53*Assumptions!$B$104/30.4 -> 0.11287566 | L53: =-(K53-K52) -> -0.0047368455 | M53: =M52+J53+L53 -> 0.50085698
A54: =Assumptions!A77 -> Oct 2030 | B54: FY2030-31 | C54: =Assumptions!B77 -> 436 | D54: =Assumptions!$B$126 -> 0.2 | E54: =(1+Assumptions!$B$129)^2 -> 1.0816 | F54: =C54*D54*Assumptions!$B$121*E54/12/10^7 -> 0.07073664 | G54: =-F54*Assumptions!$B$128*Assumptions!J77 -> -0.005411353 | H54: =F54+G54 -> 0.065325287 | I54: =F54*Assumptions!$B$127 -> 0.010610496 | J54: =H54-I54 -> 0.054714791 | K54: =H54*Assumptions!$B$104/30.4 -> 0.1181872 | L54: =-(K54-K53) -> -0.0053115348 | M54: =M53+J54+L54 -> 0.55026023
A55: =Assumptions!A78 -> Nov 2030 | B55: FY2030-31 | C55: =Assumptions!B78 -> 456 | D55: =Assumptions!$B$126 -> 0.2 | E55: =(1+Assumptions!$B$129)^2 -> 1.0816 | F55: =C55*D55*Assumptions!$B$121*E55/12/10^7 -> 0.07398144 | G55: =-F55*Assumptions!$B$128*Assumptions!J78 -> -0.0057261635 | H55: =F55+G55 -> 0.068255277 | I55: =F55*Assumptions!$B$127 -> 0.011097216 | J55: =H55-I55 -> 0.057158061 | K55: =H55*Assumptions!$B$104/30.4 -> 0.12348816 | L55: =-(K55-K54) -> -0.0053009679 | M55: =M54+J55+L55 -> 0.60211732
A56: =Assumptions!A79 -> Dec 2030 | B56: FY2030-31 | C56: =Assumptions!B79 -> 476 | D56: =Assumptions!$B$126 -> 0.2 | E56: =(1+Assumptions!$B$129)^2 -> 1.0816 | F56: =C56*D56*Assumptions!$B$121*E56/12/10^7 -> 0.07722624 | G56: =-F56*Assumptions!$B$128*Assumptions!J79 -> -0.0060468146 | H56: =F56+G56 -> 0.071179425 | I56: =F56*Assumptions!$B$127 -> 0.011583936 | J56: =H56-I56 -> 0.059595489 | K56: =H56*Assumptions!$B$104/30.4 -> 0.12877857 | L56: =-(K56-K55) -> -0.0052904009 | M56: =M55+J56+L56 -> 0.65642241
A57: =Assumptions!A80 -> Jan 2031 | B57: FY2030-31 | C57: =Assumptions!B80 -> 499 | D57: =Assumptions!$B$126 -> 0.2 | E57: =(1+Assumptions!$B$129)^2 -> 1.0816 | F57: =C57*D57*Assumptions!$B$121*E57/12/10^7 -> 0.08095776 | G57: =-F57*Assumptions!$B$128*Assumptions!J80 -> -0.0064118546 | H57: =F57+G57 -> 0.074545905 | I57: =F57*Assumptions!$B$127 -> 0.012143664 | J57: =H57-I57 -> 0.062402241 | K57: =H57*Assumptions!$B$104/30.4 -> 0.13486924 | L57: =-(K57-K56) -> -0.0060906711 | M57: =M56+J57+L57 -> 0.71273398
A58: =Assumptions!A81 -> Feb 2031 | B58: FY2030-31 | C58: =Assumptions!B81 -> 522 | D58: =Assumptions!$B$126 -> 0.2 | E58: =(1+Assumptions!$B$129)^2 -> 1.0816 | F58: =C58*D58*Assumptions!$B$121*E58/12/10^7 -> 0.08468928 | G58: =-F58*Assumptions!$B$128*Assumptions!J81 -> -0.0067836113 | H58: =F58+G58 -> 0.077905669 | I58: =F58*Assumptions!$B$127 -> 0.012703392 | J58: =H58-I58 -> 0.065202277 | K58: =H58*Assumptions!$B$104/30.4 -> 0.14094776 | L58: =-(K58-K57) -> -0.0060785191 | M58: =M57+J58+L58 -> 0.77185774
A59: =Assumptions!A82 -> Mar 2031 | B59: FY2030-31 | C59: =Assumptions!B82 -> 545 | D59: =Assumptions!$B$126 -> 0.2 | E59: =(1+Assumptions!$B$129)^2 -> 1.0816 | F59: =C59*D59*Assumptions!$B$121*E59/12/10^7 -> 0.0884208 | G59: =-F59*Assumptions!$B$128*Assumptions!J82 -> -0.0071620848 | H59: =F59+G59 -> 0.081258715 | I59: =F59*Assumptions!$B$127 -> 0.01326312 | J59: =H59-I59 -> 0.067995595 | K59: =H59*Assumptions!$B$104/30.4 -> 0.14701412 | L59: =-(K59-K58) -> -0.0060663671 | M59: =M58+J59+L59 -> 0.83378697
A60: Receivables use the engine's 55-day DSO (Assumptions B104) on a 30.4-day month; a build in receivables is a cash outflow, as on 'Cash and funding'.
A62: BY FINANCIAL YEAR
A63: Rs crore | B63: FY2026-27 | C63: FY2027-28 | D63: FY2028-29 | E63: FY2029-30 | F63: FY2030-31
A64: Governance layer — as if switched on
A65: Revenue, net of channel contra | B65: =SUMIF($B$6:$B$59,B$63,$H$6:$H$59) -> 0 | C65: =SUMIF($B$6:$B$59,C$63,$H$6:$H$59) -> 0.00625545 | D65: =SUMIF($B$6:$B$59,D$63,$H$6:$H$59) -> 0.079958953 | E65: =SUMIF($B$6:$B$59,E$63,$H$6:$H$59) -> 0.30905599 | F65: =SUMIF($B$6:$B$59,F$63,$H$6:$H$59) -> 0.7739399
A66: Cost of revenue | B66: =SUMIF($B$6:$B$59,B$63,$I$6:$I$59) -> 0 | C66: =SUMIF($B$6:$B$59,C$63,$I$6:$I$59) -> 0.000945 | D66: =SUMIF($B$6:$B$59,D$63,$I$6:$I$59) -> 0.0124425 | E66: =SUMIF($B$6:$B$59,E$63,$I$6:$I$59) -> 0.0493506 | F66: =SUMIF($B$6:$B$59,F$63,$I$6:$I$59) -> 0.1256711
A67: EBITDA delta | B67: =B65-B66 -> 0 | C67: =C65-C66 -> 0.00531045 | D67: =D65-D66 -> 0.067516454 | E67: =E65-E66 -> 0.25970539 | F67: =F65-F66 -> 0.6482688
A68: Cash delta at year end (after working capital) | B68: =M11 -> 0 | C68: =M23 -> 0.0027025816 | D68: =M35 -> 0.053684515 | E68: =M47 -> 0.27100624 | F68: =M59 -> 0.83378697
A69: Exit ARR delta at year end | B69: =H11*12 -> 0 | C69: =H23*12 -> 0.01729728 | D69: =H35*12 -> 0.12696624 | E69: =H47*12 -> 0.40808552 | F69: =H59*12 -> 0.97510458
A71: Reads — unit amounts (read : write ratio × cost or price = 1)
A72: Governed actions, total (millions) | B72: ='Unit economics'!B9 -> 0.36 | C72: ='Unit economics'!C9 -> 26.325 | D72: ='Unit economics'!D9 -> 202.392 | E72: ='Unit economics'!E9 -> 885.588 | F72: ='Unit economics'!F9 -> 2491.458
A73: Governed actions, external (millions) | B73: ='Unit economics'!B8 -> 0 | C73: ='Unit economics'!C8 -> 13.285 | D73: ='Unit economics'!D8 -> 147.792 | E73: ='Unit economics'!E8 -> 746.088 | F73: ='Unit economics'!F8 -> 2211.458
A74: Average cost per governed action (Rs) | B74: =AVERAGE(Assumptions!K29:K34) -> 0.08895 | C74: =AVERAGE(Assumptions!K35:K46) -> 0.078774167 | D74: =AVERAGE(Assumptions!K47:K58) -> 0.066918333 | E74: =AVERAGE(Assumptions!K59:K70) -> 0.0568475 | F74: =AVERAGE(Assumptions!K71:K82) -> 0.052
A75: Runtime cost if every governed action brings one read at full write cost | B75: =B72*10^6*B74/10^7 -> 0.0032022 | C75: =C72*10^6*C74/10^7 -> 0.20737299 | D75: =D72*10^6*D74/10^7 -> 1.3543735 | E75: =E72*10^6*E74/10^7 -> 5.0343464 | F75: =F72*10^6*F74/10^7 -> 12.955582
A76: Revenue if every external governed action brings one billed read at Rs 1 | B76: =B73*10^6/10^7 -> 0 | C76: =C73*10^6/10^7 -> 1.3285 | D76: =D73*10^6/10^7 -> 14.7792 | E76: =E73*10^6/10^7 -> 74.6088 | F76: =F73*10^6/10^7 -> 221.1458
A78: Reads — at the Assumptions drivers, as if switched on
A79: Read checks (millions) | B79: =B72*Assumptions!$B$131 -> 0.72 | C79: =C72*Assumptions!$B$131 -> 52.65 | D79: =D72*Assumptions!$B$131 -> 404.784 | E79: =E72*Assumptions!$B$131 -> 1771.176 | F79: =F72*Assumptions!$B$131 -> 4982.916
A80: Read runtime cost | B80: =B75*Assumptions!$B$131*Assumptions!$B$135 -> 0.0032022 | C80: =C75*Assumptions!$B$131*Assumptions!$B$135 -> 0.20737299 | D80: =D75*Assumptions!$B$131*Assumptions!$B$135 -> 1.3543735 | E80: =E75*Assumptions!$B$131*Assumptions!$B$135 -> 5.0343464 | F80: =F75*Assumptions!$B$131*Assumptions!$B$135 -> 12.955582
A81: Billed reads (millions) | B81: =B73*Assumptions!$B$131*Assumptions!$B$132 -> 0 | C81: =C73*Assumptions!$B$131*Assumptions!$B$132 -> 13.285 | D81: =D73*Assumptions!$B$131*Assumptions!$B$132 -> 147.792 | E81: =E73*Assumptions!$B$131*Assumptions!$B$132 -> 746.088 | F81: =F73*Assumptions!$B$131*Assumptions!$B$132 -> 2211.458
A82: Read revenue | B82: =B76*Assumptions!$B$131*Assumptions!$B$132*Assumptions!$B$133 -> 0 | C82: =C76*Assumptions!$B$131*Assumptions!$B$132*Assumptions!$B$133 -> 0.13285 | D82: =D76*Assumptions!$B$131*Assumptions!$B$132*Assumptions!$B$133 -> 1.47792 | E82: =E76*Assumptions!$B$131*Assumptions!$B$132*Assumptions!$B$133 -> 7.46088 | F82: =F76*Assumptions!$B$131*Assumptions!$B$132*Assumptions!$B$133 -> 22.11458
A84: SWITCHED OVERLAY — what flows to Summary P&L rows 41 to 48
A85: Governance layer switch (Assumptions B120) | B85: =Assumptions!B120 -> 0
A86: Reads metered switch (Assumptions B130) | B86: =Assumptions!B130 -> 0
A87: Reads runtime-cost switch (Assumptions B134) | B87: =Assumptions!B134 -> 0
A88: Incremental revenue | B88: =B65*$B$85+B82*$B$86 -> 0 | C88: =C65*$B$85+C82*$B$86 -> 0 | D88: =D65*$B$85+D82*$B$86 -> 0 | E88: =E65*$B$85+E82*$B$86 -> 0 | F88: =F65*$B$85+F82*$B$86 -> 0
A89: Incremental cost of revenue | B89: =B66*$B$85+B80*$B$87 -> 0 | C89: =C66*$B$85+C80*$B$87 -> 0 | D89: =D66*$B$85+D80*$B$87 -> 0 | E89: =E66*$B$85+E80*$B$87 -> 0 | F89: =F66*$B$85+F80*$B$87 -> 0
A90: Incremental EBITDA | B90: =B88-B89 -> 0 | C90: =C88-C89 -> 0 | D90: =D88-D89 -> 0 | E90: =E88-E89 -> 0 | F90: =F88-F89 -> 0
A91: Cash delta at year end | B91: =B68*$B$85+SUM($B$82:B82)*$B$86-SUM($B$80:B80)*$B$87 -> 0 | C91: =C68*$B$85+SUM($B$82:C82)*$B$86-SUM($B$80:C80)*$B$87 -> 0 | D91: =D68*$B$85+SUM($B$82:D82)*$B$86-SUM($B$80:D80)*$B$87 -> 0 | E91: =E68*$B$85+SUM($B$82:E82)*$B$86-SUM($B$80:E80)*$B$87 -> 0 | F91: =F68*$B$85+SUM($B$82:F82)*$B$86-SUM($B$80:F80)*$B$87 -> 0
A92: Exit ARR delta at year end | B92: =B69*$B$85 -> 0 | C92: =C69*$B$85 -> 0 | D92: =D69*$B$85 -> 0 | E92: =E69*$B$85 -> 0 | F92: =F69*$B$85 -> 0
A94: Reads are indicative: financial-year grain, no working-capital timing, no channel contra or escalation on read revenue, and the engine's included-action allowances are not reproduced. Exit ARR includes the governance layer only. Billing reads implies governing them, so a real read-billing case turns on both B130 and B134.

Sheet Gate calendar
A1: Gate calendar — the dated spine of the plan
A2: Every date that turns on a revenue line, releases a tranche or opens an assurance level, with the financial consequence attached to it.
A3: Dates are month of occurrence. Amounts in Rs crore. Gates are tested on evidence, not on forecast.
A5: Date | B5: Event | C5: Financial consequence | D5: Amount / effect | E5: Elan1 Govern build status, 27 Oct 2026 (code audit at commit 22388ad; see 'Govern build status')
A6: March 2027 | B6: Series A close — tranche 1 | C6: Releases the first tranche and takes cash from the Rs 4.4 crore February trough to Rs 66.4 crore | D6: Rs 63.0 cr in | E6: No change. Funding event; tranche 1 is released at close, not against build status.
A7: Q2 CY2027 | B7: L1 Guarded general availability | C7: Opens external platform licence and governed-action billing; until now revenue is the internal rung1 transfer only | D7: Revenue line on | E7: Built (code audit, commit 22388ad): allow / ask a person / refuse with default refuse; signed rulebooks; Ed25519 + SHA-256 hash-chained receipts for every governed call, reads included; hourly signed checkpoints; offline 'govern verify'; approvals; MCP, REST and SDK (enforcement on the MCP path; REST and SDK are advisory). Not built: metering and billing, assurance levels L1 to L3. Date unchanged: GA is a readiness test, not a code test.
A8: July 2027 | B8: First external paying tenant | C8: Starts the external tenant ramp: 3 tenants in July 2027 to 39 by March 2028 | D8: First external Rs | E8: No change. The repo shows no customer, pilot or production deployment; all data is demo or seed data.
A9: October 2027 | B9: First regulatory pack live (ledger1) | C9: Turns on the pack line; pack attach begins at 0.22 per tenant and reaches 1.32 by March 2031 | D9: Pack line on | E9: Built: 10 framework libraries, 13 controls and 7 industry packs, all marked 'Draft — needs legal review'. ledger1 in production with a named statutory auditor is not evidenced. Date unchanged.
A10: April 2028 | B10: L2 Attested general availability | C10: Opens the Rs 6.0 lakh platform floor and the 1.5 million included actions; L2 mix ramps to 28% of tenants by March 2030 | D10: Price step up | E10: Not built: Seal Spec v6, a second independent implementation and test vectors, RFC 3161 timestamp anchoring, KMS/HSM key custody. Date unchanged.
A11: April 2028 | B11: Second regulatory pack live (invoice1) | C11: Lifts pack attach from 0.40 toward 0.62 per tenant | D11: Pack attach up | E11: As for row 9: framework library built; invoice1 production not evidenced. Date unchanged.
A12: October 2028 | B12: Third regulatory pack live (collect1) | C12: Completes the funded pack programme; pack attach 0.62 per tenant | D12: Pack attach up | E12: As for row 9: collect1 production not evidenced. Date unchanged.
A13: October 2028 | B13: Tranche 2 gate (Gate A) | C13: Releases tranche 2 on evidence of L2 general availability, the pack programme and the tenant ramp | D13: Rs 72.0 cr in | E13: No change. Gate A conditions are evidence tests; MODELLED thresholds unchanged (engine base).
A14: July 2029 | B14: Tranche 3 gate (Gate B) | C14: Releases tranche 3 on evidence of L3 entry readiness, sovereign pipeline and unit economics | D14: Rs 45.0 cr in | E14: No change. Gate B conditions are evidence tests; MODELLED thresholds unchanged (engine base).
A15: July 2029 | B15: First sovereign deployment | C15: Opens the Rs 1.2 crore per-year sovereign line; 4 deployments by March 2030, 11 by March 2031 | D15: Rs 2.5 cr in FY30 | E15: Not built: data residency; no deployment configuration beyond Dockerfile and docker-compose. Date unchanged.
A16: October 2029 | B16: L3 Proven entry | C16: Opens the Rs 24.0 lakh platform floor and the 4.2 million included actions; L3 reaches 55 tenants by March 2031 | D16: Price step up | E16: Not built: assurance levels L1 to L3, verifier profiles, selective disclosure. Date unchanged.
... A19: 27 October 2026 (added) | B19: Product renamed Elan1 Govern; working code (audited at commit 22388ad) governs every agent tool call, reads and writes, via MCP, REST and SDK | C19: No revenue date, price or tranche changes. Build status recorded on 'Govern build status'; new lines sit behind switches on Assumptions B120, B130 and B134, all OFF | D19: None | E19: See 'Govern build status' for the audited capability list.
A20: WHAT A GATE TESTS
A21: Gates are tested on shipped evidence — a general availability declaration, an audited pack, a signed tenant, a measured unit cost —
A22: and never on a forecast. A missed gate defers the tranche; it does not resize it.
A23: The Rs 8.0 crore founder and angel bridge lands in October 2026 and is not part of the Rs 180.0 crore Series A.

Sheet Govern build status
A1: Govern build status — what the Elan1 Govern code does today
A2: Capability by capability: status, evidence, and what it means for the financial model. Nothing on this sheet changes a number in the engine.
A3: Filled from the code audit work/facts/govern-facts.md (27 October 2026) at commit 22388ad. Nothing on this sheet changes a number in the engine; the financial consequence column says where the model is affected.
A5: Audit source | B5: work/facts/govern-facts.md, audit date 27 October 2026
A6: Repository | B6: https://github.com/Hasif-Elan1/elan1-govern (full history; not shallow)
A7: Audited commit | B7: 22388ad85fc082369f28ce51968efa4b5337ec91, 2026-10-27T10:10:47+05:30
A8: Commit history | B8: 47 commits (9 merges), first 2026-10-26T18:39:08+05:30, last 2026-10-27T10:10:47+05:30: about 15.5 hours. One identity: elan1 <hello@elan1.ai>
A9: Code size | B9: About 33,567 lines of code (TypeScript, Python, Prisma, SQL); 400 tracked files
A10: Test results (as reported) | B10: pnpm test (Vitest, 25 s): 397 passed, 1 failed, 398 collected. 41 test files: 21 passed, 20 failed. 19 of the 20 failed files (in db, gate and web) collected 0 tests, with "@prisma/client did not initialize yet. Please run prisma generate" (Prisma engine download blocked by the sandbox network, not a code fault). The one failed test, apps/gate/test/env.test.ts › refuses the .env.example secrets in production, failed because no .env file exists; with the .env.example values exported it passes (3/3). Per project: core 245/245, cli 6/6, sdk 8/8, connectors 18/18, web 118/118 (3 of 9 files), gate env 3/3. Python SDK: 40 tests OK.
A11: Not run | B11: DB-backed integration tests (db, most of gate, 6 web files), Playwright e2e, coverage, lint and typecheck. GUIDE.md's claim of 580 + 40 + 23 tests is unverified.
A12: CI and security | B12: CI status unknown (gh returned 403). pnpm audit --audit-level high: "No known vulnerabilities found". semgrep, gitleaks, ZAP not run by the audit.
A14: Capability | B14: Model / IM item it maps to | C14: Status | D14: Evidence | E14: Audited? | F14: Financial consequence in the model
A15: Guard: allow / ask a person / refuse; default refuse; strictest rule wins | B15: L1 Guarded gate check (Gate calendar row 7) | C15: BUILT | D15: packages/core/src/rulebook.ts; packages/core/src/engine.ts; apps/gate/src/guard.ts | E15: VERIFIED | F15: None: L1 GA date and tenant ramp unchanged (GA is a readiness test)
A16: Fail closed when Govern itself fails | B16: Kernel refuses on error | C16: BUILT (PARTIAL) | D16: apps/gate/src/guard.ts (gate-error refusal receipt); DECISIONS #15; SECURITY.md Known limits | E16: PARTIAL: in MCP execute mode an allowed action runs before its receipt is written | F16: None
A17: Agent access by MCP, REST API, TypeScript and Python SDK | B17: Integration surface | C17: BUILT | D17: apps/gate/src/mcp.ts; apps/gate/src/routes/agent-api.ts; packages/sdk; packages/sdk-python | E17: VERIFIED: enforcement only on the MCP path; REST/SDK path is advisory | F17: None
A18: Signed hash-chained receipt for every governed call, reads included (Ed25519 + SHA-256) | B18: Proof record; runtime cost per governed action | C18: BUILT | D18: packages/core/src/receipt.ts; packages/core/src/crypto.ts; packages/db/src/chain.ts; single decision path in apps/gate/src/guard.ts (no write-specific door) | E18: VERIFIED | F18: Reads also incur receipt cost: reads runtime-cost sensitivity kept (Assumptions B134, OFF; Scenarios rows 45-62). Per-read cost unmeasured
A19: Hourly signed checkpoints | B19: Chain standing | C19: BUILT | D19: apps/gate/src/jobs.ts (cron 0 * * * *); packages/db/src/chain.ts | E19: VERIFIED: self-signed by the org key, no external timestamp | F19: None
A20: Offline verifier 'govern verify' | B20: Offline verifier, priced Rs 0 (IM Appendix A.3) | C20: BUILT (PARTIAL) | D20: packages/cli/src/cli.ts; packages/core/src/bundle.ts | E20: PARTIAL: trusts the key inside the bundle unless --key or a fingerprint check is used; 3 exit codes (0, 1, 2), not 6 | F20: None: stays free
A21: Rulebooks: rule builder with YAML, risk tags, quotas, try an action, test on past actions, versions, sign and publish, rule suggestions | B21: Declaration / Studio | C21: BUILT | D21: packages/core/src/rulebook.ts; rulebook-sign.ts; apps/gate/src/replay.ts; packages/core/src/suggest.ts | E21: VERIFIED: quotas checked outside the chain lock (SECURITY.md) | F21: None
A22: Approvals: web, signed single-use email/phone links, Slack and WhatsApp; expiry refuses | B22: Human approval (ask a person) | C22: BUILT (PARTIAL) | D22: apps/gate/src/approvals.ts; packages/core/src/chat.ts; apps/web/src/server/session.ts | E22: PARTIAL: password asked only if sign-in is more than 10 minutes old | F22: None
A23: Connectors: Gmail, Zoho Books, any MCP server behind Govern, SSRF guard | B23: Connected systems; IM plan is ERPNext-first | C23: BUILT | D23: packages/connectors/src/index.ts; apps/gate/src/upstream.ts; apps/gate/src/upstream-net.ts | E23: VERIFIED: live Gmail/Zoho never run against real accounts; no ERPNext connector | F23: None; ERPNext design-partner gates escalated
A24: Evidence: auditor pack (bundle + PDF) and compliance map | B24: Evidence SKU (bundle Rs 2,500, Assumptions B20) | C24: BUILT | D24: apps/gate/src/evidence.ts; packages/core/src/bundle.ts | E24: VERIFIED | F24: None: evidence line unchanged
A25: AI inventory | B25: Governance layer (new line) | C25: BUILT (PARTIAL) | D25: packages/core/src/inventory.ts; apps/web/src/server/inventory.ts | E25: PARTIAL: no model field; risk tier and review date come only from approved assessments | F25: Governance-layer line behind Assumptions B120 (OFF)
... A42: Production deployment, customers, usage telemetry, certification | B42: Tenant ramp; certification and audit opex | C42: NOT BUILT | D42: Audit §8: all data is seed or demo (Demo Traders Pvt Ltd) | E42: ABSENT | F42: None: tenant ramp unchanged
A44: Status: BUILT = the audit verified the code does what the brief says; BUILT (PARTIAL) = code exists but differs in a way that matters; NOT BUILT = specification item absent from the code.
A45: Every governed call, reads included, passes through one decision path and writes a signed receipt. The engine's cost per governed action covers writes only, so the reads runtime-cost sensitivity is kept on Scenarios rows 45 to 62 (switch Assumptions B134, OFF). Per-read cost is still unmeasured.
A46: Open questions from the audit for the founder: who wrote and reviewed the code; whether CI is green; whether any real account or customer has been run through it; code licence and IP ownership (no LICENSE file).

Sheet Revision log
A1: Revision log — revised edition, 27 October 2026
A2: In the original pages, 'elan1' meaning the product or kernel should be read as Elan1 Govern; 'elan1 Private Limited' remains the entity. Engine outputs (every hardcoded figure from the 22 September 2026 engine run) are unchanged.
A3: Provenance: LABEL = naming or explanatory text only; FACT-BRIEF = stated in the 27 Oct 2026 brief; FACT-AUDIT = from the code audit; MODELLED = new commercial assumption with no customer evidence; ENGINE = an existing engine driver restated; FOUND = pre-existing issue, not changed.
A5: No. | B5: Date | C5: Sheet | D5: Cell(s) | E5: Old value | F5: New value | G5: Reason | H5: Provenance | I5: Effect on headline outputs | J5: Reversal
A6: 1 | B6: 2026-10-27 | C6: Cover | D6: B3 | E6: elan1 · Series A Financial Model | F6: Elan1 Govern · Series A Financial Model | G6: Founder update 27 Oct 2026: product renamed Elan1 Govern; workbook title carries the new name | H6: LABEL | I6: None | J6: Restore old value
A7: 2 | B7: 2026-10-27 | C7: Cover | D7: B5 | E7: Governed Intelligence Platform · October 2026 to March 2031 | F7: The governance platform for AI agents — it decides before every tool call, makes a named person approve the risky ones, refuses what it must, and produces the proof | G7: Tagline for Elan1 Govern as instructed (coordinator decision 2); describes the built product in the brief | H7: LABEL | I7: None | J7: Restore old value
A8: 3 | B8: 2026-10-27 | C8: Cover | D8: B7 | E8: Prepared for Series A investors · 22 September 2026 · Strictly confidential | F8: Prepared for Series A investors · Plan period October 2026 to March 2031 · 22 September 2026, revised 27 October 2026 · Strictly confidential | G8: Revised edition date; plan period moved here from the old B5 tagline so it is not lost | H8: LABEL | I8: None | J8: Restore old value
A9: 4 | B9: 2026-10-27 | C9: Cover | D9: B9 | E9: (empty) | F9: Revised edition 27 October 2026 — see Revision log | G9: Cover note required by coordinator decision 2 | H9: LABEL | I9: None | J9: Clear cell
A10: 5 | B10: 2026-10-27 | C10: Cover | D10: B49 | E10: (empty) | F10: Revised 27 October 2026. The product is renamed Elan1 Govern. In the original pages, 'elan1' meaning the product or kernel should be read as Elan1 Govern; 'elan1 Private Limited' remains the entity. Engine outputs are unchanged; every addition is listed on the Revision log, and the new Elan1 Govern switches on Assumptions are OFF in the base case. | G10: Required read-across sentence (brief UPDATE 27 Oct 2026); entity confirmed unchanged by founder | H10: LABEL | I10: None | J10: Clear cell
A11: 6 | B11: 2026-10-27 | C11: Cover | D11: B51 | E11: (empty) | F11: ADDED IN THE REVISED EDITION | G11: Tab index for the new sheets | H11: LABEL | I11: None | J11: Clear cell
A12: 7 | B12: 2026-10-27 | C12: Cover | D12: C51 | E12: (empty) | F12: What it shows | G12: Tab index for the new sheets | H12: LABEL | I12: None | J12: Clear cell
A13: 8 | B13: 2026-10-27 | C13: Cover | D13: B52 | E13: (empty) | F13: Govern overlay | G13: Tab index for the new sheets | H13: LABEL | I13: None | J13: Clear cell
A14: 9 | B14: 2026-10-27 | C14: Cover | D14: C52 | E14: (empty) | F14: Elan1 Govern increments behind three switches — governance layer, reads billed, reads cost; zero when OFF | G14: Tab index for the new sheets | H14: LABEL | I14: None | J14: Clear cell
A15: 10 | B15: 2026-10-27 | C15: Cover | D15: B53 | E15: (empty) | F15: Govern build status | G15: Tab index for the new sheets | H15: LABEL | I15: None | J15: Clear cell
A16: 11 | B16: 2026-10-27 | C16: Cover | D16: C53 | E16: (empty) | F16: What the Elan1 Govern code does today, capability by capability, with evidence and its effect on the model | G16: Tab index for the new sheets | H16: LABEL | I16: None | J16: Clear cell
A17: 12 | B17: 2026-10-27 | C17: Cover | D17: B54 | E17: (empty) | F17: Revision log | G17: Tab index for the new sheets | H17: LABEL | I17: None | J17: Clear cell
... A32: 27 | B32: 2026-10-27 | C32: Assumptions | D32: A120 | E32: (empty) | F32: Governance layer revenue switch | G32: Brief: built governance layer 'similar to Credo AI' (AI inventory, assessments, 10 frameworks); no revenue line existed | H32: MODELLED | I32: None | J32: Clear cell
A33: 28 | B33: 2026-10-27 | C33: Assumptions | D33: B120 | E33: (empty) | F33: 0 | G33: Brief: built governance layer 'similar to Credo AI' (AI inventory, assessments, 10 frameworks); no revenue line existed | H33: MODELLED | I33: None while the switches are OFF | J33: Clear cell
A34: 29 | B34: 2026-10-27 | C34: Assumptions | D34: C120 | E34: (empty) | F34: 1 = on, 0 = off | G34: Brief: built governance layer 'similar to Credo AI' (AI inventory, assessments, 10 frameworks); no revenue line existed | H34: MODELLED | I34: None | J34: Clear cell
A35: 30 | B35: 2026-10-27 | C35: Assumptions | D35: D120 | E35: (empty) | F35: MODELLED | G35: Brief: built governance layer 'similar to Credo AI' (AI inventory, assessments, 10 frameworks); no revenue line existed | H35: MODELLED | I35: None | J35: Clear cell
A36: 31 | B36: 2026-10-27 | C36: Assumptions | D36: E120 | E36: (empty) | F36: OFF in the base case. Turns on the AI inventory / assessments / frameworks add-on line on 'Govern overlay'. | G36: Brief: built governance layer 'similar to Credo AI' (AI inventory, assessments, 10 frameworks); no revenue line existed | H36: MODELLED | I36: None | J36: Clear cell
A37: 32 | B37: 2026-10-27 | C37: Assumptions | D37: A121 | E37: (empty) | F37: Governance layer price | G37: Conservative sizing of the new governance-layer line; no customer has been quoted it | H37: MODELLED | I37: None | J37: Clear cell
A38: 33 | B38: 2026-10-27 | C38: Assumptions | D38: B121 | E38: (empty) | F38: 90000 | G38: Conservative sizing of the new governance-layer line; no customer has been quoted it | H38: MODELLED | I38: None while the switches are OFF | J38: Clear cell
A39: 34 | B39: 2026-10-27 | C39: Assumptions | D39: C121 | E39: (empty) | F39: Rs per paying tenant per year | G39: Conservative sizing of the new governance-layer line; no customer has been quoted it | H39: MODELLED | I39: None | J39: Clear cell
A40: 35 | B40: 2026-10-27 | C40: Assumptions | D40: D121 | E40: (empty) | F40: MODELLED | G40: Conservative sizing of the new governance-layer line; no customer has been quoted it | H40: MODELLED | I40: None | J40: Clear cell
A41: 36 | B41: 2026-10-27 | C41: Assumptions | D41: E121 | E41: (empty) | F41: Half the L1 platform floor (B7). Per-tenant add-on: per-governed-action pricing and Rs 0 refusals are untouched. | G41: Conservative sizing of the new governance-layer line; no customer has been quoted it | H41: MODELLED | I41: None | J41: Clear cell
A42: 37 | B42: 2026-10-27 | C42: Assumptions | D42: A122 | E42: (empty) | F42: Governance layer attach, FY2026-27 | G42: Attach ramp for the new line | H42: MODELLED | I42: None | J42: Clear cell
A43: 38 | B43: 2026-10-27 | C43: Assumptions | D43: B122 | E43: (empty) | F43: 0 | G43: Attach ramp for the new line | H43: MODELLED | I43: None while the switches are OFF | J43: Clear cell
A44: 39 | B44: 2026-10-27 | C44: Assumptions | D44: C122 | E44: (empty) | F44: share of paying tenants | G44: Attach ramp for the new line | H44: MODELLED | I44: None | J44: Clear cell
A45: 40 | B45: 2026-10-27 | C45: Assumptions | D45: D122 | E45: (empty) | F45: MODELLED | G45: Attach ramp for the new line | H45: MODELLED | I45: None | J45: Clear cell
A46: 41 | B46: 2026-10-27 | C46: Assumptions | D46: E122 | E46: (empty) | F46: No paying tenants until July 2027. | G46: Attach ramp for the new line | H46: MODELLED | I46: None | J46: Clear cell
A47: 42 | B47: 2026-10-27 | C47: Assumptions | D47: A123 | E47: (empty) | F47: Governance layer attach, FY2027-28 | G47: Attach ramp for the new line | H47: MODELLED | I47: None | J47: Clear cell
A48: 43 | B48: 2026-10-27 | C48: Assumptions | D48: B123 | E48: (empty) | F48: 0.05 | G48: Attach ramp for the new line | H48: MODELLED | I48: None while the switches are OFF | J48: Clear cell
A49: 44 | B49: 2026-10-27 | C49: Assumptions | D49: C123 | E49: (empty) | F49: share of paying tenants | G49: Attach ramp for the new line | H49: MODELLED | I49: None | J49: Clear cell
A50: 45 | B50: 2026-10-27 | C50: Assumptions | D50: D123 | E50: (empty) | F50: MODELLED | G50: Attach ramp for the new line | H50: MODELLED | I50: None | J50: Clear cell
A51: 46 | B51: 2026-10-27 | C51: Assumptions | D51: E123 | E51: (empty) | F51: Rides the existing tenant ramp (B29:B82); adds no customers. | G51: Attach ramp for the new line | H51: MODELLED | I51: None | J51: Clear cell
A52: 47 | B52: 2026-10-27 | C52: Assumptions | D52: A124 | E52: (empty) | F52: Governance layer attach, FY2028-29 | G52: Attach ramp for the new line | H52: MODELLED | I52: None | J52: Clear cell
A53: 48 | B53: 2026-10-27 | C53: Assumptions | D53: B124 | E53: (empty) | F53: 0.1 | G53: Attach ramp for the new line | H53: MODELLED | I53: None while the switches are OFF | J53: Clear cell
A54: 49 | B54: 2026-10-27 | C54: Assumptions | D54: C124 | E54: (empty) | F54: share of paying tenants | G54: Attach ramp for the new line | H54: MODELLED | I54: None | J54: Clear cell
A55: 50 | B55: 2026-10-27 | C55: Assumptions | D55: D124 | E55: (empty) | F55: MODELLED | G55: Attach ramp for the new line | H55: MODELLED | I55: None | J55: Clear cell
A56: 51 | B56: 2026-10-27 | C56: Assumptions | D56: E124 | E56: (empty) | G56: Attach ramp for the new line | H56: MODELLED | I56: None | J56: Clear cell
A57: 52 | B57: 2026-10-27 | C57: Assumptions | D57: A125 | E57: (empty) | F57: Governance layer attach, FY2029-30 | G57: Attach ramp for the new line | H57: MODELLED | I57: None | J57: Clear cell
A58: 53 | B58: 2026-10-27 | C58: Assumptions | D58: B125 | E58: (empty) | F58: 0.15 | G58: Attach ramp for the new line | H58: MODELLED | I58: None while the switches are OFF | J58: Clear cell
A59: 54 | B59: 2026-10-27 | C59: Assumptions | D59: C125 | E59: (empty) | F59: share of paying tenants | G59: Attach ramp for the new line | H59: MODELLED | I59: None | J59: Clear cell
A60: 55 | B60: 2026-10-27 | C60: Assumptions | D60: D125 | E60: (empty) | F60: MODELLED | G60: Attach ramp for the new line | H60: MODELLED | I60: None | J60: Clear cell
A61: 56 | B61: 2026-10-27 | C61: Assumptions | D61: E125 | E61: (empty) | G61: Attach ramp for the new line | H61: MODELLED | I61: None | J61: Clear cell
A62: 57 | B62: 2026-10-27 | C62: Assumptions | D62: A126 | E62: (empty) | F62: Governance layer attach, FY2030-31 | G62: Attach ramp for the new line | H62: MODELLED | I62: None | J62: Clear cell
A63: 58 | B63: 2026-10-27 | C63: Assumptions | D63: B126 | E63: (empty) | F63: 0.2 | G63: Attach ramp for the new line | H63: MODELLED | I63: None while the switches are OFF | J63: Clear cell
A64: 59 | B64: 2026-10-27 | C64: Assumptions | D64: C126 | E64: (empty) | F64: share of paying tenants | G64: Attach ramp for the new line | H64: MODELLED | I64: None | J64: Clear cell
A65: 60 | B65: 2026-10-27 | C65: Assumptions | D65: D126 | E65: (empty) | F65: MODELLED | G65: Attach ramp for the new line | H65: MODELLED | I65: None | J65: Clear cell
A66: 61 | B66: 2026-10-27 | C66: Assumptions | D66: E126 | E66: (empty) | G66: Attach ramp for the new line | H66: MODELLED | I66: None | J66: Clear cell
A67: 62 | B67: 2026-10-27 | C67: Assumptions | D67: A127 | E67: (empty) | F67: Governance layer cost of revenue | G67: Cost of the new line | H67: MODELLED | I67: None | J67: Clear cell
A68: 63 | B68: 2026-10-27 | C68: Assumptions | D68: B127 | E68: (empty) | F68: 0.15 | G68: Cost of the new line | H68: MODELLED | I68: None while the switches are OFF | J68: Clear cell
A69: 64 | B69: 2026-10-27 | C69: Assumptions | D69: C127 | E69: (empty) | F69: of gross line revenue | G69: Cost of the new line | H69: MODELLED | I69: None | J69: Clear cell
A70: 65 | B70: 2026-10-27 | C70: Assumptions | D70: D127 | E70: (empty) | F70: MODELLED | G70: Cost of the new line | H70: MODELLED | I70: None | J70: Clear cell
A71: 66 | B71: 2026-10-27 | C71: Assumptions | D71: E127 | E71: (empty) | F71: Hosting and support for inventory, assessments and framework reports. | G71: Cost of the new line | H71: MODELLED | I71: None | J71: Clear cell
A72: 67 | B72: 2026-10-27 | C72: Assumptions | D72: A128 | E72: (empty) | F72: Channel margin kept by partners | G72: Makes an engine driver stated in text (A86) usable by the overlay | H72: ENGINE (A86) | I72: None | J72: Clear cell
A73: 68 | B73: 2026-10-27 | C73: Assumptions | D73: B128 | E73: (empty) | F73: 0.18 | G73: Makes an engine driver stated in text (A86) usable by the overlay | H73: ENGINE (A86) | I73: None (documentation of an engine driver) | J73: Clear cell
A74: 69 | B74: 2026-10-27 | C74: Assumptions | D74: C128 | E74: (empty) | F74: of list on partner-sourced revenue | G74: Makes an engine driver stated in text (A86) usable by the overlay | H74: ENGINE (A86) | I74: None | J74: Clear cell
A75: 70 | B75: 2026-10-27 | C75: Assumptions | D75: D128 | E75: (empty) | F75: ENGINE (A86) | G75: Makes an engine driver stated in text (A86) usable by the overlay | H75: ENGINE (A86) | I75: None | J75: Clear cell
A76: 71 | B76: 2026-10-27 | C76: Assumptions | D76: E128 | E76: (empty) | F76: Applied with the monthly channel share in column J. | G76: Makes an engine driver stated in text (A86) usable by the overlay | H76: ENGINE (A86) | I76: None | J76: Clear cell
A77: 72 | B77: 2026-10-27 | C77: Assumptions | D77: A129 | E77: (empty) | F77: List price escalation from April 2029 | G77: Makes an engine driver stated in text (A24) usable by the overlay | H77: ENGINE (A24) | I77: None | J77: Clear cell
A78: 73 | B78: 2026-10-27 | C78: Assumptions | D78: B129 | E78: (empty) | F78: 0.04 | G78: Makes an engine driver stated in text (A24) usable by the overlay | H78: ENGINE (A24) | I78: None (documentation of an engine driver) | J78: Clear cell
A79: 74 | B79: 2026-10-27 | C79: Assumptions | D79: C129 | E79: (empty) | F79: per annum | G79: Makes an engine driver stated in text (A24) usable by the overlay | H79: ENGINE (A24) | I79: None | J79: Clear cell
A80: 75 | B80: 2026-10-27 | C80: Assumptions | D80: D129 | E80: (empty) | F80: ENGINE (A24) | G80: Makes an engine driver stated in text (A24) usable by the overlay | H80: ENGINE (A24) | I80: None | J80: Clear cell
A81: 76 | B81: 2026-10-27 | C81: Assumptions | D81: E129 | E81: (empty) | F81: Flat to March 2029, then 4% a year, as for the price book. | G81: Makes an engine driver stated in text (A24) usable by the overlay | H81: ENGINE (A24) | I81: None | J81: Clear cell
A82: 77 | B82: 2026-10-27 | C82: Assumptions | D82: A130 | E82: (empty) | F82: Reads metered switch | G82: Brief: Elan1 Govern governs EVERY tool call (reads and writes); read pricing undecided | H82: MODELLED | I82: None | J82: Clear cell
A83: 78 | B83: 2026-10-27 | C83: Assumptions | D83: B130 | E83: (empty) | F83: 0 | G83: Brief: Elan1 Govern governs EVERY tool call (reads and writes); read pricing undecided | H83: MODELLED | I83: None while the switches are OFF | J83: Clear cell
A84: 79 | B84: 2026-10-27 | C84: Assumptions | D84: C130 | E84: (empty) | F84: 1 = on, 0 = off | G84: Brief: Elan1 Govern governs EVERY tool call (reads and writes); read pricing undecided | H84: MODELLED | I84: None | J84: Clear cell
A85: 80 | B85: 2026-10-27 | C85: Assumptions | D85: D130 | E85: (empty) | F85: MODELLED | G85: Brief: Elan1 Govern governs EVERY tool call (reads and writes); read pricing undecided | H85: MODELLED | I85: None | J85: Clear cell
A86: 81 | B86: 2026-10-27 | C86: Assumptions | D86: E130 | E86: (empty) | F86: OFF: whether reads are billed is an unmade pricing decision. Scenario only. Billing reads implies governing them, so read with B134. | G86: Brief: Elan1 Govern governs EVERY tool call (reads and writes); read pricing undecided | H86: MODELLED | I86: None | J86: Clear cell
A87: 82 | B87: 2026-10-27 | C87: Assumptions | D87: A131 | E87: (empty) | F87: Read : write ratio | G87: Reads sensitivity driver | H87: MODELLED | I87: None | J87: Clear cell
A88: 83 | B88: 2026-10-27 | C88: Assumptions | D88: B131 | E88: (empty) | F88: 2 | G88: Reads sensitivity driver | H88: MODELLED | I88: None while the switches are OFF | J88: Clear cell
A89: 84 | B89: 2026-10-27 | C89: Assumptions | D89: C131 | E89: (empty) | F89: reads per governed action | G89: Reads sensitivity driver | H89: MODELLED | I89: None | J89: Clear cell
A90: 85 | B90: 2026-10-27 | C90: Assumptions | D90: D131 | E90: (empty) | F90: MODELLED | G90: Reads sensitivity driver | H90: MODELLED | I90: None | J90: Clear cell
A91: 86 | B91: 2026-10-27 | C91: Assumptions | D91: E131 | E91: (empty) | F91: Applies to all governed actions (internal and external). | G91: Reads sensitivity driver | H91: MODELLED | I91: None | J91: Clear cell
A92: 87 | B92: 2026-10-27 | C92: Assumptions | D92: A132 | E92: (empty) | F92: Share of reads billed | G92: Reads sensitivity driver | H92: MODELLED | I92: None | J92: Clear cell
A93: 88 | B93: 2026-10-27 | C93: Assumptions | D93: B132 | E93: (empty) | F93: 0.5 | G93: Reads sensitivity driver | H93: MODELLED | I93: None while the switches are OFF | J93: Clear cell
A94: 89 | B94: 2026-10-27 | C94: Assumptions | D94: C132 | E94: (empty) | F94: beyond the included allowance | G94: Reads sensitivity driver | H94: MODELLED | I94: None | J94: Clear cell
A95: 90 | B95: 2026-10-27 | C95: Assumptions | D95: D132 | E95: (empty) | F95: MODELLED | G95: Reads sensitivity driver | H95: MODELLED | I95: None | J95: Clear cell
A96: 91 | B96: 2026-10-27 | C96: Assumptions | D96: E132 | E96: (empty) | F96: Allowance mechanics are not reproduced outside the engine. | G96: Reads sensitivity driver | H96: MODELLED | I96: None | J96: Clear cell
A97: 92 | B97: 2026-10-27 | C97: Assumptions | D97: A133 | E97: (empty) | F97: Read price | G97: Reads sensitivity driver | H97: MODELLED | I97: None | J97: Clear cell
A98: 93 | B98: 2026-10-27 | C98: Assumptions | D98: B133 | E98: (empty) | F98: 0.1 | G98: Reads sensitivity driver | H98: MODELLED | I98: None while the switches are OFF | J98: Clear cell
A99: 94 | B99: 2026-10-27 | C99: Assumptions | D99: C133 | E99: (empty) | F99: Rs per allowed read | G99: Reads sensitivity driver | H99: MODELLED | I99: None | J99: Clear cell
A100: 95 | B100: 2026-10-27 | C100: Assumptions | D100: D133 | E100: (empty) | F100: MODELLED | G100: Reads sensitivity driver | H100: MODELLED | I100: None | J100: Clear cell
A101: 96 | B101: 2026-10-27 | C101: Assumptions | D101: E133 | E101: (empty) | F101: Refusals stay at quantity zero and are never billed. | G101: Reads sensitivity driver | H101: MODELLED | I101: None | J101: Clear cell
A102: 97 | B102: 2026-10-27 | C102: Assumptions | D102: A134 | E102: (empty) | F102: Reads runtime-cost switch | G102: Code audit 27 Oct 2026: every governed call, reads included, writes a signed hash-chained receipt; per-read cost not yet measured | H102: MODELLED | I102: None | J102: Clear cell
A103: 98 | B103: 2026-10-27 | C103: Assumptions | D103: B134 | E103: (empty) | F103: 0 | G103: Code audit 27 Oct 2026: every governed call, reads included, writes a signed hash-chained receipt; per-read cost not yet measured | H103: MODELLED | I103: None while the switches are OFF | J103: Clear cell
A104: 99 | B104: 2026-10-27 | C104: Assumptions | D104: C134 | E104: (empty) | F104: 1 = on, 0 = off | G104: Code audit 27 Oct 2026: every governed call, reads included, writes a signed hash-chained receipt; per-read cost not yet measured | H104: MODELLED | I104: None | J104: Clear cell
A105: 100 | B105: 2026-10-27 | C105: Assumptions | D105: D134 | E105: (empty) | F105: MODELLED | G105: Code audit 27 Oct 2026: every governed call, reads included, writes a signed hash-chained receipt; per-read cost not yet measured | H105: MODELLED | I105: None | J105: Clear cell
A106: 101 | B106: 2026-10-27 | C106: Assumptions | D106: E134 | E106: (empty) | F106: OFF in the base case. TOP MODEL RISK: the code audit (commit 22388ad) shows a signed receipt for every governed call, reads included, but the engine's cost per governed action (K29:K82) covers writes only. Per-read cost is unmeasured. | G106: Code audit 27 Oct 2026: every governed call, reads included, writes a signed hash-chained receipt; per-read cost not yet measured | H106: MODELLED | I106: None | J106: Clear cell
A107: 102 | B107: 2026-10-27 | C107: Assumptions | D107: A135 | E107: (empty) | F107: Read check cost | G107: Reads sensitivity driver | H107: MODELLED | I107: None | J107: Clear cell
A108: 103 | B108: 2026-10-27 | C108: Assumptions | D108: B135 | E108: (empty) | F108: 0.5 | G108: Reads sensitivity driver | H108: MODELLED | I108: None while the switches are OFF | J108: Clear cell
A109: 104 | B109: 2026-10-27 | C109: Assumptions | D109: C135 | E109: (empty) | F109: × cost per governed action (column K) | G109: Reads sensitivity driver | H109: MODELLED | I109: None | J109: Clear cell
A110: 105 | B110: 2026-10-27 | C110: Assumptions | D110: D135 | E110: (empty) | F110: MODELLED | G110: Reads sensitivity driver | H110: MODELLED | I110: None | J110: Clear cell
A111: 106 | B111: 2026-10-27 | C111: Assumptions | D111: E135 | E111: (empty) | F111: Per-read cost is still unmeasured (the 27 Oct 2026 code audit confirms reads are receipted but did not measure cost); replace with the measured figure. | G111: Reads sensitivity driver | H111: MODELLED | I111: None | J111: Clear cell
A112: 107 | B112: 2026-10-27 | C112: Assumptions | D112: A136 | E112: (empty) | F112: These drivers feed only the 'Govern overlay' sheet and the overlay blocks on Summary P&L (rows 39 to 50) and Scenarios (rows 43 to 62). Engine outputs are unchanged whatever the switches say. Shaded cells are inputs. | G112: Explains scope of the new drivers | H112: LABEL | I112: None | J112: Clear cell
A113: 108 | B113: 2026-10-27 | C113: Govern overlay | D113: whole sheet | E113: (sheet did not exist) | F113: New sheet: monthly governance-layer line A4:M60; FY block A62:F92 | G113: Transparent overlay: engine outputs are hardcoded, so new drivers cannot flow through the engine | H113: MODELLED | I113: Zero while all switches are OFF | J113: Delete the sheet and Summary P&L rows 39-50, Scenarios rows 43-62
A114: 109 | B114: 2026-10-27 | C114: Summary P&L | D114: A39 | E114: (empty) | F114: ELAN1 GOVERN OVERLAY — zero unless switched on at Assumptions B120, B130 or B134 | G114: Shows Elan1 Govern switches beside the untouched engine base | H114: LABEL | I114: None | J114: Clear cell
A115: 110 | B115: 2026-10-27 | C115: Summary P&L | D115: A40 | E115: (empty) | F115: Rs crore | G115: Header | H115: LABEL | I115: None | J115: Clear cell
...
